Workbook

Sheet 0-Паспорт проекта
G1: header_first | H1: HeaderFirst
A2: Номер | B2: Название | C2: Значение | E2: ИсточникИнформации | F2: Рекомендации | G2: key | H2: k9 | I2: needToSend | J2: Значение_raw | K2: type
B3: Насосное оборудование | G3: formulaColl | K3: enumeration
B4: Компрессоры | G4: var_key | K4: user
B5: Электротовары | G5: var_name | K5: money
B6: Запчасти | G6: var_value | K6: datetime
G7: hide_col | K7: boolean
G8: header_08 | K8: staf
A9: № | B9: Название | C9: Значение | D9: Проверка | E9: Источник информации | F9: Рекомендации | G9: header_last | H9: key | K9: raw
A10: № | B10: Название | C10: Значение | D10: Проверка | E10: Источник информации | F10: Рекомендации | G10: Индификатор поля | H10: HeaderLast
A11: 1 | B11: Номер проекта | C11: PTZ-А-1480 | G11: ufCrm_69EA3A22F3CA9 | H11: НомерПроекта | I11: Да | J11: PTZ-А-1480 | K11: raw
B12: ID_Bitrix | C12: 255 | G12: ID | K12: raw
A13: 0 | B13: URL_Bitrix | G13: URL_Bitrix | K13: raw
B14: Ссылка на таблицу расчета | G14: ufCrm31_1777547556213 | K14: raw
A16: Надо заполнить на основе документации | D16: Проверка | E16: Источник информации: | F16: Рекомендации
A17: 2 | B17: Место поставки товара | C17: Подольск | E17: 1. ТЗ РАЗДЕЛ X. ТРЕБОВАНИЯ К КОЛИЧЕСТВУ, МЕСТУ И СРОКУ (ПЕРИОДИЧНОСТИ) ПОСТАВКИ. 2. Извещение: раздел место исполнения договора или место поставки. 3. Договор: место поставки. 4. Спецификация | G17: ufCrm_69EA3A22B3191 | I17: Да | J17: Подольск | K17: raw
A18: 3 | B18: Срок поставки по договору, календарные дни или точная дата | C18: 30 | D18: =IF(IFERROR(C18/1,0)=0,"Должно быть или число или точная дата, Ошибка","ok") -> ok | E18: 1. ТЗ РАЗДЕЛ X. ТРЕБОВАНИЯ К КОЛИЧЕСТВУ, МЕСТУ И СРОКУ (ПЕРИОДИЧНОСТИ) ПОСТАВКИ. 2. Спецификация (при наличии). 3. Договор (при наличии): либо в разделе ПРЕДМЕТ ДОГОВОРА, либо СРОКИ ПОСТАВКИ, либо в СПЕЦИФИКАЦИИ к договору. 4. Иногда может быть указано в Извещении в разделе предмет договора. | F18: 1. Ищем "срок поставки" в проекте договора или в ТЗ/Спецификации. 2. Если указана конкретная дата ,то вводим ее. 3. Если указан диапазон дат то вводим берем максимальную дату 4. Если указан период : например в течение 40 дней или не более 20 дней с даты заключения договора ,то ставим просто число. 5. Из рабочих (Х) переводим в календарные (Y) с помощью формулы Х=Y/5*7. | G18: ufCrm_69EA3A22BCFF5 | I18: Да | J18: 30 | K18: raw
A19: 4 | B19: Срок доставки, календарные дни | D19: =IF(IFERROR(C19/1,0)=0,"Должно быть или число или точная дата, Ошибка","ok") -> Должно быть или число или точная дата, Ошибка | E19: Надо вычислить самостоятельно. | F19: Смотрим на сайте деловых линий сколько времени занимает доставка из Подольска до заказчика + прибавляем 7 дней | G19: ufCrm_69EA3A22C6588 | I19: Да | K19: raw
A20: 5 | B20: Срок приемки, календарные дни | C20: 7 | D20: =IF(IFERROR(C20/1,0)=0,"Должно быть или число или точная дата, Ошибка","ok") -> ok | E20: Договор раздел ПРИЕМКА ТОВАРА или ПОРЯДОК ПРИЕМКИ. | F20: 1. Изучаем договор или другую документацию по закупке ищем срок приемки товара. 2. Из рабочих (Х) переводим в календарные (Y) с помощью формулы Х=Y/5*7. 3. Если информация отсутствует, то ставим "30". | G20: ufCrm_69EA3A22CFA43 | I20: Да | J20: 7 | K20: raw
A21: 6 | B21: Срок оплаты, календарные дни | C21: 30 | D21: =IF(IFERROR(C21/1,0)=0,"Должно быть или число или точная дата, Ошибка","ok") -> ok | E21: 1. Извещение: Раздел условия оплаты. 2. Договор: раздел порядок оплаты. | F21: 1. Изучаем договор или другую документацию по закупке ищем срок оплаты. 2. Если указана конкретная дата ,то вводим ее. 3. Если указан диапазон дат то вводим берем максимальную дату 4. Если указан период : например в течение 40 дней или не более 20 дней с даты заключения договора ,то ставим просто число. 5. Из рабочих (Х) переводим в календарные (Y) с помощью формулы Х=Y/5*7. 6. Если информация отсутствует, то ставим "30". | G21: ufCrm_69EA3A22D8590 | I21: Да | J21: 30 | K21: raw
A22: 7 | B22: Аванс,% | E22: 1. Извещение: Раздел условия оплаты. 2. Договор: раздел порядок оплаты. | G22: ufCrm_69EA3A220488D | I22: Да | K22: raw
A23: 8 | B23: Аванс, руб | G23: ufCrm_69EA3A221B414 | I23: Да | K23: money
A24: 9 | B24: Неустойка за день просрочки,% | E24: 1. Договор Раздел Ответственность. | G24: ufCrm_69EA3A222390D | I24: Да | K24: raw
A25: 10 | B25: Ограничение неустойки за просрочку | E25: 1. Договор Раздел Ответственность. | G25: ufCrm_69EA3A222B5FD | I25: Да | K25: raw
A26: 11 | B26: Штраф за просрочку от стоимости Товара/договора, % | E26: 1. Договор Раздел Ответственность. | G26: ufCrm_69EA3A22398F7 | I26: Да | K26: enumeration
A27: 12 | B27: Штраф за поставку товара с недостатками от стоимости Товара/договора, % | E27: 1. Договор Раздел Ответственность. | G27: ufCrm_69EA3A2241A6C | I27: Да | K27: enumeration
A28: 13 | B28: Досрочная поставка товара по договору | G28: ufCrm_69EA3A2249278 | I28: Да | K28: enumeration
A29: 14 | B29: Частичная поставка товара по договору | E29: 1. Договор раздел Поставка товара, Условия поставки и т.п. | F29: Если не указано что продукция должна быть поставлена одной партией и в полном объеме то ставим "Да". | G29: ufCrm_69EA3A22507F4 | I29: Да | K29: enumeration
A30: 15 | B30: Частичная оплата товара по договору | E30: Договор. | F30: Если не указано что продукция будет оплачена по факту ПОЛНОЙ поставки то ставим "Да". | G30: ufCrm_69EA3A2257D9F | I30: Да | K30: enumeration
A31: 16 | B31: Поставка по заявке или частями | C31: Нет | G31: ufCrm_69EA3A2232300 | I31: Да | J31: 5329 | K31: enumeration
A32: 17 | B32: Обеспечения заявки, % | E32: Извещение. | G32: ufCrm_69EA3A225EFD0 | I32: Да | K32: raw
A33: 18 | B33: Обеспечения заявки, руб | E33: Извещение. | G33: ufCrm_69EA3A22644AD | I33: Да | K33: money
A34: 19 | B34: Обеспечение ИСПОЛНЕНИЯ договора, % | E34: Извещение./ Проект договора по поиску на слово "Обеспечение" далее искать Обеспечение Исполнения. | G34: ufCrm_69EA3A2269B8F | I34: Да | K34: raw
A35: 20 | B35: Обеспечение ИСПОЛНЕНИЯ договора, руб | E35: Извещение./ Проект договора по поиску на слово "Обеспечение" далее искать Обеспечение Исполнения. | G35: ufCrm_69EA3A226F3CC | I35: Да | K35: money
A36: 21 | B36: Правила приемки | E36: Договор раздел ПРИЕМКА ТОВАРА или ПОРЯДОК ПРИЕМКИ. | G36: ufCrm_69EA3A2274E59 | I36: Да | K36: enumeration
A37: 22 | B37: ЕОС-качество | E37: Договор раздел ПРИЕМКА ТОВАРА или ПОРЯДОК ПРИЕМКИ. | F37: 1. Ищем в договоре ЕОС-качество. 2. Если ЕОС-Качество упоминается, то ставим да,если нет, то нет. | G37: ufCrm_69EA3A227FF23 | I37: Да | K37: enumeration
A38: 23 | B38: Доля импорта | E38: Надо вычислить самостоятельно. | F38: Отношение импортной продукции к общему объему в закупочных ценах.
A39: 24 | B39: Категория поставляемых товаров | G39: ufCrm_69EA3A22E3E95 | I39: Да | K39: enumeration
A40: 25 | B40: НМЦ | D40: =IF(C40<>'1-1 Сбор КП'!K22,"Ошибка проверить попозиционное НМЦ","ok") -> ok | G40: opportunity | I40: Да | J40: 0 | K40: money
A41: 26 | B41: Валюта НМЦ | C41: RUB | D41: =IF(C41="","Необходимо выбрать валюту договора, ошибка","ok") -> ok | G41: currencyId | I41: Да | J41: RUB | K41: raw
A42: 27 | B42: Ставка НДС в договоре | C42: 0.22 | D42: =IF(C42="","Необходимо выбрать ставку НДС, ошибка","ok") -> ok | G42: ufCrm_69EA3A2289038 | I42: Да | J42: 5377 | K42: enumeration
A43: 28 | B43: Присутствует ли ТЗ в проекте договора на ЭТП | G43: ufCrm_69EA3A229088A | I43: Да | K43: enumeration
A44: 29 | B44: Экспортный контракт | G44: ufCrm_69EA3A22983AF | I44: Да | K44: enumeration
A45: 30 | B45: Постановление правительства №1875 | G45: ufCrm_69EA3A21DCA6B | I45: Да | K45: enumeration
A46: 31 | B46: Срок действия предложения (нет или конкретный срок) | G46: ufCrm_69EA3A21F3424 | I46: Да | K46: raw
A47: 32 | B47: Условия договора на которые нужно обратить ВНИМАНИЕ | G47: ufCrm_69EA3A22A19EE | I47: Да | K47: raw
A49: Данные из Битрикс
A50: =A47+1 -> 33 | B50: Текущая стадия СП | C50: Есть товары у которых нет цен | G50: stageId | I50: Да | J50: DT1076_41:UC_NFPPYY | K50: enumeration
A51: =A50+1 -> 34 | B51: Текущая стадия Сделки | C51: Расчет | G51: ufCrm31_1776958599 | I51: Да | J51: Расчет | K51: raw
A52: =A51+1 -> 35 | B52: Ответственный за сделку Менеджер | C52: Антон | G52: assignedById | I52: Да | J52: 1 | K52: staf
A53: =A52+1 -> 36 | B53: Ответственный за создание таблиц и сбор ИЦИ | C53: Артем Хафизов | G53: ufCrm31_1776958433 | I53: Да | J53: 659 | K53: staf
A54: =A53+1 -> 37 | B54: Ответственный за расчет и тех. часть | C54: Геннадий Грибовский | G54: ufCrm31_1781782219 | I54: Да | J54: 895 | K54: staf
A55: =A54+1 -> 38 | B55: Наблюдатели | C55: Антон Артем Хафизов Геннадий Грибовский | G55: observers | I55: Да | J55: 1 | K55: staf
A57: Заполняется автоматически с листа 3-3
A58: =A55+1 -> 39 | B58: Реальный срок поставки, календарных дней | C58: ='4-1 Расчет рентабельности КП'!B36 -> #REF! | E58: Заполняется автоматом на основе максимальных данных с листа 3-3 - проверить.
A59: =A58+1 -> 40 | B59: Планируемый срок проекта , календарные дни | C59: ='4-1 Расчет рентабельности КП'!B41 -> #REF!
A60: =A59+1 -> 41 | B60: Кол-во позиций, шт | C60: =IFERROR(COUNTIFS('3-3 Выбор поставщиков'!F2:F21,">0",'3-3 Выбор поставщиков'!A2:A21,"<>@"),0) -> 0
A61: =A60+1 -> 42 | B61: Кол-во поставщиков в проекте (на основе листа "3-3 выбор поставщиков"), шт | C61: {=COUNTA(UNIQUE('3-3 Выбор поставщиков'!K2:K21))} -> 1
A63: КОНТРАКТАЦИЯ
A64: =A61+1 -> 43 | B64: Наименование заказчика | E64: Заполняет ответственный за заключение договора
A65: =A64+1 -> 44 | B65: Контакты ЛПР | E65: Заполняет ответственный менеджер
A66: =A65+1 -> 45 | B66: Другие контакты заказчика. | E66: Заполняет ответственный менеджер, а затем ответственный за заключение договора
A67: =A66+1 -> 46 | B67: Дата публикации протокола | E67: Заполняет ответственный за заключение договора сразу после его опубликования
A68: =A67+1 -> 47 | B68: Общее количество дней, отведенное на заключения договора от даты публикации | E68: Заполняет ответственный за заключение договора сразу после опубликования протокола (информация берется из извещения)
A69: =A68+1 -> 48 | B69: Плановая дата заключения договора (расчетная) | C69: =IF(C67+C68>0,C67+C68,) | E69: рассчитывается автоматически (38+39)
A70: =A69+1 -> 49 | B70: Количество дней, отведенное заказчику на передачу проекта договора Победителю | E70: Заполняет ответственный за заключение договора сразу после опубликования протокола
A71: =A70+1 -> 50 | B71: Дата до которой Заказчик должен передать нам подписанный проект договора (расч) | E71: Заполняет ответственный за заключение договора сразу после опубликования протокола/Для КЗ рассчитывается исходя из информации прописанной в Извещении
A72: =A71+1 -> 51 | B72: Дата фактической передачи Заказчиком проекта договора нам | E72: Заполняет ответственный за заключение договора сразу после поступления к нам подписанного заказчиком проекта договора
A73: =A72+1 -> 52 | B73: Кол-во дней которые отведены нам на подписание договора | E73: Заполняет ответственный за заключение договора сразу после опубликования протокола/Для КЗ рассчитывается исходя из информации прописанной в Извещении
A74: =A73+1 -> 53 | B74: Дата когда МЫ должны направить подписанный нами договор. | E74: рассчитывается автоматически
A75: =A74+1 -> 54 | B75: Фактическая Дата подписания и направления договора нами | E75: Заполняет ответственный за заключение договора -дата должна соответствовать фактической дате отправления подписанного нами договора заказчику
A76: =A75+1 -> 55 | B76: Юр лицо победитель | E76: Заполняет ответственный за заключение договора
A77: =A76+1 -> 56 | B77: Цена Договора | D77: =IF(IFERROR(C77/1,-1)=-1,"Должно быть число, проверить пробелы Ошибка",) | E77: Заполняет ответственный за заключение договора
A78: =A77+1 -> 57 | B78: Номер договора | E78: Заполняет ответственный за заключение договора
A79: =A78+1 -> 58 | B79: Договор от (дата в шапке договора) | E79: Заполняет ответственный за заключение договора
A80: =A79+1 -> 59 | B80: Вид подписания договора | E80: Заполняет ответственный за заключение договора
A81: =A80+1 -> 60 | B81: Сумма обеспечения договора | E81: Заполняет ответственный за заключение договора
A82: =A81+1 -> 61 | B82: Дата направления заказчику Обеспечения Исполнения договора | E82: Заполняет ответственный за заключение договора
A83: =A82+1 -> 62 | B83: Кто контактирует с заказчиком по вопросу исполнения | E83: Заполняет ответственный за заключение договора
A84: =A83+1 -> 63 | B84: Комментарий
B86: Дата согласования запросов | C86: 46302.665 | G86: ufCrm31_1782799136 | I86: Да | J86: 2026-10-07T15:57:43+03:00 | K86: datetime
B87: Результат экспертизы | C87: В процессе | G87: ufCrm31_1781869533683 | I87: Да | J87: 5469 | K87: enumeration
B88: Состояние рассылки | C88: Всё отправлено | G88: ufCrm31_1781091023615 | I88: Да | J88: 5453 | K88: enumeration
B89: Наличие цен | C89: Есть товары без цен | G89: ufCrm31_1782134329446 | I89: Да | J89: 5495 | K89: enumeration
B90: Дата завершения экспертизы | I90: Да | K90: datetime
C91: 46308.604 | G91: date_from_bitrix
B92: Дата перехода в стадию 'Подготовка ТП' | G92: ufCrm31_1791195837 | I92: Да | K92: datetime
B93: Добавлено новое предложение | G93: ufCrm31_1791195853 | I93: Да | K93: raw
G94: opportunity_currency | J94: 0
C95: Успех | G95: bitrix_status

Sheet 1-0 Товары
C1: header_first
A2: err | B2: err2 | C2: key | D2: Номер | E2: Номенклатура | F2: Характеристики | G2: ЕдИзм | H2: Количевство | I2: НМЦ | J2: НазваниеТовараПоДоговору | K2: ИзготовительТовараПоДоговору | L2: Группа_1_2 | M2: Группа_5_2 | N2: СрокПоставкиПоДоговору
C3: formulaColl | D3: formulaColl | E3: formulaFree | F3: formulaFree | G3: formulaFree | H3: formulaFree | I3: formulaFree | J3: formulaColl | K3: formulaColl | L3: formulaColl | M3: formulaColl | N3: formulaColl
C4: var_key
C5: var_name
C6: var_value
C7: header_07
C8: header_08
C9: header_last
C10: =IFERROR(__xludf.DUMMYFUNCTION("{""ID_Товара""; LAMBDA( doFindRow, doFilter, theWordStart, theCStart, theWordEnd, theCEnd, theDataWord, theData, doFilter(doFindRow(theDataWord,theWordStart,theCStart),doFindRow(theDataWord,theWordEnd,theCEnd),theData) )( LAMBDA(theWords,theWord,theC"&" , VLOOKUP( theWord, BYROW(theWords,LAMBDA(theW,{theW , ROW(theW)})),2,FALSE ) +theC), LAMBDA(bodyStart,bodyEnd,theData, FILTER(theData,bodyStart <= BYROW(theData,lambda(d,ROW(d))) ,BYROW(theData,lambda(d,ROW(d)))<=bodyEnd )), ""№"",1,""@"",-1,'1-1 Сб"&"ор КП'!C1:C31 ,'1-1 Сбор КП'!Z1:Z31 )} "),"ID_Товара") -> ID_Товара | D10: =IFERROR(__xludf.DUMMYFUNCTION("{ {'1-1 Сбор КП'!C1:G1}; {LAMBDA( doFindRow, doFilter, theWordStart, theCStart, theWordEnd, theCEnd, theDataWord, theData, doFilter(doFindRow(theDataWord,theWordStart,theCStart),doFindRow(theDataWord,theWordEnd,theCEnd),theData) )( LAMBDA(theWords,t"&"heWord,theC , VLOOKUP( theWord, BYROW(theWords,LAMBDA(theW,{theW , ROW(theW)})),2,FALSE ) +theC), LAMBDA(bodyStart,bodyEnd,theData, FILTER(theData,bodyStart <= BYROW(theData,lambda(d,ROW(d))) ,BYROW(theData,lambda(d,ROW(d)))<=bodyEnd )), ""№"",1,""@"""&",-1,'1-1 Сбор КП'!C1:C31 ,'1-1 Сбор КП'!C1:G31 )} }"),"№") -> № | E10: =IFERROR(__xludf.DUMMYFUNCTION("""COMPUTED_VALUE"""),"Номенклатура") -> Номенклатура | F10: =IFERROR(__xludf.DUMMYFUNCTION("""COMPUTED_VALUE"""),"Характеристики") -> Характеристики | G10: =IFERROR(__xludf.DUMMYFUNCTION("""COMPUTED_VALUE"""),"Ед. Изм") -> Ед. Изм | H10: =IFERROR(__xludf.DUMMYFUNCTION("""COMPUTED_VALUE"""),"Кол-во") -> Кол-во | I10: =IFERROR(__xludf.DUMMYFUNCTION("{ {'1-1 Сбор КП'!K1}; {LAMBDA( doFindRow, doFilter, theWordStart, theCStart, theWordEnd, theCEnd, theDataWord, theData, doFilter(doFindRow(theDataWord,theWordStart,theCStart),doFindRow(theDataWord,theWordEnd,theCEnd),theData) )( LAMBDA(theWords,theW"&"ord,theC , VLOOKUP( theWord, BYROW(theWords,LAMBDA(theW,{theW , ROW(theW)})),2,FALSE ) +theC), LAMBDA(bodyStart,bodyEnd,theData, FILTER(theData,bodyStart <= BYROW(theData,lambda(d,ROW(d))) ,BYROW(theData,lambda(d,ROW(d)))<=bodyEnd )), ""№"",1,""@"",-1"&",'1-1 Сбор КП'!C1:C31 ,'1-1 Сбор КП'!K1:K31 )} }"),"НМЦ") -> НМЦ | J10: {=IF(E10:E313<>"",IFERROR(VLOOKUP(E10:E313,{'5-1 Сбор КП Закупки'!E10:E313,'5-1 Сбор КП Закупки'!F10:F313},2,FALSE) ,),)} -> Название товара по договору | K10: {=IF(E10:E313<>"",IFERROR(VLOOKUP(E10:E313,{'5-1 Сбор КП Закупки'!E10:E313,'5-1 Сбор КП Закупки'!G10:G313},2,FALSE) ,),)} -> Изготовитель товара по договору | L10: =IFERROR(__xludf.DUMMYFUNCTION("BYROW({ {'1-1 Сбор КП'!O1}; {LAMBDA( doFindRow, doFilter, theWordStart, theCStart, theWordEnd, theCEnd, theDataWord, theData, doFilter(doFindRow(theDataWord,theWordStart,theCStart),doFindRow(theDataWord,theWordEnd,theCEnd),theData) )( LAMBDA(theWord"&"s,theWord,theC , VLOOKUP( theWord, BYROW(theWords,LAMBDA(theW,{theW , ROW(theW)})),2,FALSE ) +theC), LAMBDA(bodyStart,bodyEnd,theData, FILTER(theData,bodyStart <= BYROW(theData,lambda(d,ROW(d))) ,BYROW(theData,lambda(d,ROW(d)))<=bodyEnd )), ""№"",1,"""&"@"",-1,'1-1 Сбор КП'!C1:C31 ,'1-1 Сбор КП'!O1:O31 )} },LAMBDA(theG,IFERROR(theG,)))"),"Группа") -> Группа | M10: {={"Группа";LAMBDA(doFind,theIds,theData, doFind(theIds,theData) )( LAMBDA(theIds,theData, BYROW(theIds,LAMBDA(ti,IF(ti<>"", IFERROR(VLOOKUP(ti,theData,2,0),),)))), '1-0 Товары'!C11:C313, {'5-2 Запросы КП Закупки'!C11:C313,'5-2 Запросы КП Закупки'!N11:N313} )}} -> Группа | N10: =IFERROR(__xludf.DUMMYFUNCTION("{ {'1-1 Сбор КП'!N1}; {LAMBDA( doFindRow, doFilter, theWordStart, theCStart, theWordEnd, theCEnd, theDataWord, theData, doFilter(doFindRow(theDataWord,theWordStart,theCStart),doFindRow(theDataWord,theWordEnd,theCEnd),theData) )( LAMBDA(theWords,theW"&"ord,theC , VLOOKUP( theWord, BYROW(theWords,LAMBDA(theW,{theW , ROW(theW)})),2,FALSE ) +theC), LAMBDA(bodyStart,bodyEnd,theData, FILTER(theData,bodyStart <= BYROW(theData,lambda(d,ROW(d))) ,BYROW(theData,lambda(d,ROW(d)))<=bodyEnd )), ""№"",1,""@"",-1"&",'1-1 Сбор КП'!C1:C31 ,'1-1 Сбор КП'!N1:N31 )} }"),"Срок поставки по договору") -> Срок поставки по договору | O10: =IFERROR(__xludf.DUMMYFUNCTION("{ {'1-1 Сбор КП'!L1}; {LAMBDA( doFindRow, doFilter, theWordStart, theCStart, theWordEnd, theCEnd, theDataWord, theData, doFilter(doFindRow(theDataWord,theWordStart,theCStart),doFindRow(theDataWord,theWordEnd,theCEnd),theData) )( LAMBDA(theWords,theW"&"ord,theC , VLOOKUP( theWord, BYROW(theWords,LAMBDA(theW,{theW , ROW(theW)})),2,FALSE ) +theC), LAMBDA(bodyStart,bodyEnd,theData, FILTER(theData,bodyStart <= BYROW(theData,lambda(d,ROW(d))) ,BYROW(theData,lambda(d,ROW(d)))<=bodyEnd )), ""№"",1,""@"",-1"&",'1-1 Сбор КП'!C1:C31 ,'1-1 Сбор КП'!L1:L31 )} }"),"Нац режим 1875") -> Нац режим 1875 | P10: =IFERROR(__xludf.DUMMYFUNCTION("{ {'1-1 Сбор КП'!M1}; {LAMBDA( doFindRow, doFilter, theWordStart, theCStart, theWordEnd, theCEnd, theDataWord, theData, doFilter(doFindRow(theDataWord,theWordStart,theCStart),doFindRow(theDataWord,theWordEnd,theCEnd),theData) )( LAMBDA(theWords,theW"&"ord,theC , VLOOKUP( theWord, BYROW(theWords,LAMBDA(theW,{theW , ROW(theW)})),2,FALSE ) +theC), LAMBDA(bodyStart,bodyEnd,theData, FILTER(theData,bodyStart <= BYROW(theData,lambda(d,ROW(d))) ,BYROW(theData,lambda(d,ROW(d)))<=bodyEnd )), ""№"",1,""@"",-1"&",'1-1 Сбор КП'!C1:C31 ,'1-1 Сбор КП'!M1:M31 )} }"),"Код ОКПД 2") -> Код ОКПД 2
C11: =IFERROR(__xludf.DUMMYFUNCTION("""COMPUTED_VALUE"""),"ID_T001") -> ID_T001 | D11: =IFERROR(__xludf.DUMMYFUNCTION("""COMPUTED_VALUE"""),"1") -> 1 | E11: =IFERROR(__xludf.DUMMYFUNCTION("""COMPUTED_VALUE"""),"Масляный фильтр - Артикул 89781969 ESG-315 зав.№ F010451") -> Масляный фильтр - Артикул 89781969 ESG-315 зав.№ F010451 | F11: =IFERROR(__xludf.DUMMYFUNCTION("""COMPUTED_VALUE""")," ESG-315 зав. № F01045") -> ESG-315 зав. № F01045 | G11: =IFERROR(__xludf.DUMMYFUNCTION("""COMPUTED_VALUE"""),"шт.") -> шт. | H11: =IFERROR(__xludf.DUMMYFUNCTION("""COMPUTED_VALUE"""),3.0) -> 3
C12: =IFERROR(__xludf.DUMMYFUNCTION("""COMPUTED_VALUE"""),"ID_T002") -> ID_T002 | D12: =IFERROR(__xludf.DUMMYFUNCTION("""COMPUTED_VALUE"""),"2") -> 2 | E12: =IFERROR(__xludf.DUMMYFUNCTION("""COMPUTED_VALUE"""),"Масляный фильтр - Артикул 85062259") -> Масляный фильтр - Артикул 85062259 | F12: =IFERROR(__xludf.DUMMYFUNCTION("""COMPUTED_VALUE"""),"ESG-315 зав.№ 17030008 VS-250; ESM-200") -> ESG-315 зав.№ 17030008 VS-250; ESM-200 | G12: =IFERROR(__xludf.DUMMYFUNCTION("""COMPUTED_VALUE"""),"шт.") -> шт. | H12: =IFERROR(__xludf.DUMMYFUNCTION("""COMPUTED_VALUE"""),6.0) -> 6
C13: =IFERROR(__xludf.DUMMYFUNCTION("""COMPUTED_VALUE"""),"ID_T003") -> ID_T003 | D13: =IFERROR(__xludf.DUMMYFUNCTION("""COMPUTED_VALUE"""),"3") -> 3 | E13: =IFERROR(__xludf.DUMMYFUNCTION("""COMPUTED_VALUE"""),"Воздушный фильтр - Артикул 85067179 ") -> Воздушный фильтр - Артикул 85067179 | F13: =IFERROR(__xludf.DUMMYFUNCTION("""COMPUTED_VALUE"""),"ESG-315 зав.№ F010451; ESG-315 зав.№ 17030008 VS-250; ESM-200; «Gardner Denver»") -> ESG-315 зав.№ F010451; ESG-315 зав.№ 17030008 VS-250; ESM-200; «Gardner Denver» | G13: =IFERROR(__xludf.DUMMYFUNCTION("""COMPUTED_VALUE"""),"шт.") -> шт. | H13: =IFERROR(__xludf.DUMMYFUNCTION("""COMPUTED_VALUE"""),16.0) -> 16
C14: =IFERROR(__xludf.DUMMYFUNCTION("""COMPUTED_VALUE"""),"ID_T004") -> ID_T004 | D14: =IFERROR(__xludf.DUMMYFUNCTION("""COMPUTED_VALUE"""),"4") -> 4 | E14: =IFERROR(__xludf.DUMMYFUNCTION("""COMPUTED_VALUE"""),"Термостат в сборе ESM-200; «Gardner Denver»") -> Термостат в сборе ESM-200; «Gardner Denver» | F14: =IFERROR(__xludf.DUMMYFUNCTION("""COMPUTED_VALUE"""),"ESM-200; «Gardner Denver»") -> ESM-200; «Gardner Denver» | G14: =IFERROR(__xludf.DUMMYFUNCTION("""COMPUTED_VALUE"""),"шт.") -> шт. | H14: =IFERROR(__xludf.DUMMYFUNCTION("""COMPUTED_VALUE"""),2.0) -> 2
C15: =IFERROR(__xludf.DUMMYFUNCTION("""COMPUTED_VALUE"""),"ID_T005") -> ID_T005 | D15: =IFERROR(__xludf.DUMMYFUNCTION("""COMPUTED_VALUE"""),"5") -> 5 | E15: =IFERROR(__xludf.DUMMYFUNCTION("""COMPUTED_VALUE"""),"Масляный сепаратор Артикул 03498328") -> Масляный сепаратор Артикул 03498328 | F15: =IFERROR(__xludf.DUMMYFUNCTION("""COMPUTED_VALUE""")," ESS-18 «Gardner Denver»") -> ESS-18 «Gardner Denver» | G15: =IFERROR(__xludf.DUMMYFUNCTION("""COMPUTED_VALUE"""),"шт.") -> шт. | H15: =IFERROR(__xludf.DUMMYFUNCTION("""COMPUTED_VALUE"""),3.0) -> 3
C16: =IFERROR(__xludf.DUMMYFUNCTION("""COMPUTED_VALUE"""),"ID_T006") -> ID_T006 | D16: =IFERROR(__xludf.DUMMYFUNCTION("""COMPUTED_VALUE"""),"6") -> 6 | E16: =IFERROR(__xludf.DUMMYFUNCTION("""COMPUTED_VALUE"""),"Масляный фильтр Артикул 89675429") -> Масляный фильтр Артикул 89675429 | F16: =IFERROR(__xludf.DUMMYFUNCTION("""COMPUTED_VALUE""")," ESS-18 «Gardner Denver»") -> ESS-18 «Gardner Denver» | G16: =IFERROR(__xludf.DUMMYFUNCTION("""COMPUTED_VALUE"""),"шт.") -> шт. | H16: =IFERROR(__xludf.DUMMYFUNCTION("""COMPUTED_VALUE"""),3.0) -> 3
C17: =IFERROR(__xludf.DUMMYFUNCTION("""COMPUTED_VALUE"""),"ID_T007") -> ID_T007 | D17: =IFERROR(__xludf.DUMMYFUNCTION("""COMPUTED_VALUE"""),"7") -> 7 | E17: =IFERROR(__xludf.DUMMYFUNCTION("""COMPUTED_VALUE"""),"Воздушный фильтр - Артикул 81166609") -> Воздушный фильтр - Артикул 81166609 | F17: =IFERROR(__xludf.DUMMYFUNCTION("""COMPUTED_VALUE""")," ESS-18 «Gardner Denver»") -> ESS-18 «Gardner Denver» | G17: =IFERROR(__xludf.DUMMYFUNCTION("""COMPUTED_VALUE"""),"шт.") -> шт. | H17: =IFERROR(__xludf.DUMMYFUNCTION("""COMPUTED_VALUE"""),3.0) -> 3
C18: =IFERROR(__xludf.DUMMYFUNCTION("""COMPUTED_VALUE"""),"ID_T008") -> ID_T008 | D18: =IFERROR(__xludf.DUMMYFUNCTION("""COMPUTED_VALUE"""),"8") -> 8 | E18: =IFERROR(__xludf.DUMMYFUNCTION("""COMPUTED_VALUE"""),"Сервисный набор арт. 2906020000 ") -> Сервисный набор арт. 2906020000 | F18: =IFERROR(__xludf.DUMMYFUNCTION("""COMPUTED_VALUE"""),"GA 200 зав. № APF133999; GA 250 зав. № APF133914; GA 250 зав. № APF 133915 «Atlas Copco»") -> GA 200 зав. № APF133999; GA 250 зав. № APF133914; GA 250 зав. № APF 133915 «Atlas Copco» | G18: =IFERROR(__xludf.DUMMYFUNCTION("""COMPUTED_VALUE"""),"шт.") -> шт. | H18: =IFERROR(__xludf.DUMMYFUNCTION("""COMPUTED_VALUE"""),3.0) -> 3
C19: =IFERROR(__xludf.DUMMYFUNCTION("""COMPUTED_VALUE"""),"ID_T009") -> ID_T009 | D19: =IFERROR(__xludf.DUMMYFUNCTION("""COMPUTED_VALUE"""),"9") -> 9 | E19: =IFERROR(__xludf.DUMMYFUNCTION("""COMPUTED_VALUE"""),"Сервисный набор 8000 ч. арт. 2906075700") -> Сервисный набор 8000 ч. арт. 2906075700 | F19: =IFERROR(__xludf.DUMMYFUNCTION("""COMPUTED_VALUE"""),"GA 200 зав. № APF133999; GA 250 зав. № APF133914; GA 250 зав. № APF 133915 «Atlas Copco»") -> GA 200 зав. № APF133999; GA 250 зав. № APF133914; GA 250 зав. № APF 133915 «Atlas Copco» | G19: =IFERROR(__xludf.DUMMYFUNCTION("""COMPUTED_VALUE"""),"шт.") -> шт. | H19: =IFERROR(__xludf.DUMMYFUNCTION("""COMPUTED_VALUE"""),3.0) -> 3
C20: =IFERROR(__xludf.DUMMYFUNCTION("""COMPUTED_VALUE"""),"ID_T010") -> ID_T010 | D20: =IFERROR(__xludf.DUMMYFUNCTION("""COMPUTED_VALUE"""),"10") -> 10 | E20: =IFERROR(__xludf.DUMMYFUNCTION("""COMPUTED_VALUE"""),"Масляный сепаратор ") -> Масляный сепаратор | F20: =IFERROR(__xludf.DUMMYFUNCTION("""COMPUTED_VALUE"""),"«Dalgakiran» Inversys +315 зав. №VD 4037, зав. № VD 6420.") -> «Dalgakiran» Inversys +315 зав. №VD 4037, зав. № VD 6420. | G20: =IFERROR(__xludf.DUMMYFUNCTION("""COMPUTED_VALUE"""),"шт.") -> шт. | H20: =IFERROR(__xludf.DUMMYFUNCTION("""COMPUTED_VALUE"""),3.0) -> 3
C21: =IFERROR(__xludf.DUMMYFUNCTION("""COMPUTED_VALUE"""),"ID_T011") -> ID_T011 | D21: =IFERROR(__xludf.DUMMYFUNCTION("""COMPUTED_VALUE"""),"11") -> 11 | E21: =IFERROR(__xludf.DUMMYFUNCTION("""COMPUTED_VALUE"""),"Воздушный фильтр") -> Воздушный фильтр | F21: =IFERROR(__xludf.DUMMYFUNCTION("""COMPUTED_VALUE"""),"«Dalgakiran» Inversys +315 зав. №VD 4037, зав. № VD 6420.") -> «Dalgakiran» Inversys +315 зав. №VD 4037, зав. № VD 6420. | G21: =IFERROR(__xludf.DUMMYFUNCTION("""COMPUTED_VALUE"""),"шт.") -> шт. | H21: =IFERROR(__xludf.DUMMYFUNCTION("""COMPUTED_VALUE"""),6.0) -> 6
C22: =IFERROR(__xludf.DUMMYFUNCTION("""COMPUTED_VALUE"""),"ID_T012") -> ID_T012 | D22: =IFERROR(__xludf.DUMMYFUNCTION("""COMPUTED_VALUE"""),"12") -> 12 | E22: =IFERROR(__xludf.DUMMYFUNCTION("""COMPUTED_VALUE"""),"Масляный фильтр") -> Масляный фильтр | F22: =IFERROR(__xludf.DUMMYFUNCTION("""COMPUTED_VALUE"""),"«Dalgakiran» Inversys +315 зав. №VD 4037, зав. № VD 6420.") -> «Dalgakiran» Inversys +315 зав. №VD 4037, зав. № VD 6420. | G22: =IFERROR(__xludf.DUMMYFUNCTION("""COMPUTED_VALUE"""),"шт.") -> шт. | H22: =IFERROR(__xludf.DUMMYFUNCTION("""COMPUTED_VALUE"""),6.0) -> 6
C23: =IFERROR(__xludf.DUMMYFUNCTION("""COMPUTED_VALUE"""),"ID_T013") -> ID_T013 | D23: =IFERROR(__xludf.DUMMYFUNCTION("""COMPUTED_VALUE"""),"13") -> 13 | E23: =IFERROR(__xludf.DUMMYFUNCTION("""COMPUTED_VALUE"""),"Масляный сепаратор DS 3084 ") -> Масляный сепаратор DS 3084 | F23: =IFERROR(__xludf.DUMMYFUNCTION("""COMPUTED_VALUE"""),"BB-50/8 ВУЗ АО «НПАО «ВНИИ компрессормаш»") -> BB-50/8 ВУЗ АО «НПАО «ВНИИ компрессормаш» | G23: =IFERROR(__xludf.DUMMYFUNCTION("""COMPUTED_VALUE"""),"шт.") -> шт. | H23: =IFERROR(__xludf.DUMMYFUNCTION("""COMPUTED_VALUE"""),2.0) -> 2
C24: =IFERROR(__xludf.DUMMYFUNCTION("""COMPUTED_VALUE"""),"ID_T014") -> ID_T014 | D24: =IFERROR(__xludf.DUMMYFUNCTION("""COMPUTED_VALUE"""),"14") -> 14 | E24: =IFERROR(__xludf.DUMMYFUNCTION("""COMPUTED_VALUE"""),"Воздушный фильтр ЛААЗ ЭФВ 721.1109560 (7405. 1109560)") -> Воздушный фильтр ЛААЗ ЭФВ 721.1109560 (7405. 1109560) | F24: =IFERROR(__xludf.DUMMYFUNCTION("""COMPUTED_VALUE"""),"BB-50/8 ВУЗ АО «НПАО «ВНИИ компрессормаш»") -> BB-50/8 ВУЗ АО «НПАО «ВНИИ компрессормаш» | G24: =IFERROR(__xludf.DUMMYFUNCTION("""COMPUTED_VALUE"""),"шт.") -> шт. | H24: =IFERROR(__xludf.DUMMYFUNCTION("""COMPUTED_VALUE"""),4.0) -> 4
C25: =IFERROR(__xludf.DUMMYFUNCTION("""COMPUTED_VALUE"""),"ID_T015") -> ID_T015 | D25: =IFERROR(__xludf.DUMMYFUNCTION("""COMPUTED_VALUE"""),"15") -> 15 | E25: =IFERROR(__xludf.DUMMYFUNCTION("""COMPUTED_VALUE"""),"Масляный фильтр W13145/3") -> Масляный фильтр W13145/3 | F25: =IFERROR(__xludf.DUMMYFUNCTION("""COMPUTED_VALUE"""),"BB-50/8 ВУЗ АО «НПАО «ВНИИ компрессормаш»") -> BB-50/8 ВУЗ АО «НПАО «ВНИИ компрессормаш» | G25: =IFERROR(__xludf.DUMMYFUNCTION("""COMPUTED_VALUE"""),"шт.") -> шт. | H25: =IFERROR(__xludf.DUMMYFUNCTION("""COMPUTED_VALUE"""),4.0) -> 4
C26: =IFERROR(__xludf.DUMMYFUNCTION("""COMPUTED_VALUE"""),"ID_T016") -> ID_T016 | D26: =IFERROR(__xludf.DUMMYFUNCTION("""COMPUTED_VALUE"""),"16") -> 16
C27: =IFERROR(__xludf.DUMMYFUNCTION("""COMPUTED_VALUE"""),"ID_T017") -> ID_T017 | D27: =IFERROR(__xludf.DUMMYFUNCTION("""COMPUTED_VALUE"""),"17") -> 17
C28: =IFERROR(__xludf.DUMMYFUNCTION("""COMPUTED_VALUE"""),"ID_T018") -> ID_T018 | D28: =IFERROR(__xludf.DUMMYFUNCTION("""COMPUTED_VALUE"""),"18") -> 18
C29: =IFERROR(__xludf.DUMMYFUNCTION("""COMPUTED_VALUE"""),"ID_T019") -> ID_T019 | D29: =IFERROR(__xludf.DUMMYFUNCTION("""COMPUTED_VALUE"""),"19") -> 19
C30: =IFERROR(__xludf.DUMMYFUNCTION("""COMPUTED_VALUE"""),"ID_T020") -> ID_T020 | D30: =IFERROR(__xludf.DUMMYFUNCTION("""COMPUTED_VALUE"""),"20") -> 20

Sheet 1-1 Сбор КП
C1: № | D1: Номенклатура | E1: Характеристики | F1: Ед. Изм | G1: Кол-во | H1: Цена | I1: Итого | J1: Предложений | K1: НМЦ | L1: Нац режим 1875 | M1: Код ОКПД 2 | N1: Срок поставки по договору | O1: {={"Группа";LAMBDA(theNames,theData,BYROW(theNames,LAMBDA(tn,IFERROR(VLOOKUP(tn,theData,2,0),))))(C2:C21,{'1-2 Запросы по товарным группам'!D:D,'1-2 Запросы по товарным группам'!O:O})}} -> Группа | P1: =IFERROR(__xludf.DUMMYFUNCTION("{{""Доля ответов"",""Предложение"",""Писем""};let( _t_em_map , let( _t_gr, '1-2 Запросы по товарным группам'!$O11:$O311, _t_nm, '1-2 Запросы по товарным группам'!$P11:$P311, _t_em, '1-2 Запросы по товарным группам'!$AA11:JI$311, do_sm, LAMBDA"&"(em_mp, BYROW(em_mp,LAMBDA(e_ar,COUNTA(e_ar)))), QUERY( {{""Группа"" , ""Кол-во""};{Map(_t_gr,_t_nm,do_sm(_t_em),LAMBDA(g,n,s,IF(n=2,{g,s},{"""",""""})) )}},""Select * Where Col1 is not null"") ), _t_ot_mp , BYROW('1-1 Сбор КП'!$AA2:$HS30, LAMBDA(r,"&" IFERROR(COUNTA( FILTER(r,MOD( COLUMN(r),3)=0 ) ),) )), _t_mp_stat_tov, MAP('1-1 Сбор КП'!$Z2:$Z30,'1-1 Сбор КП'!$D2:$D30,_t_ot_mp,'1-1 Сбор КП'!$O2:$O30, LAMBDA(z,t,r,g, {z,IF(t<>"""",IFERROR( r/VLOOKUP(g,_t_em_map,2,FALSE) ,),),IF(t<>"""",r,),IFERROR( V"&"LOOKUP(g,_t_em_map,2,FALSE) ,)})), _t_mp_stat_itog, LAMBDA(_t, let ( _t_dolya, LAMBDA(_a,SUM(_a)/COUNT(_a))(INDEX( _t,,2)) ,_t_predl, LAMBDA(_a,SUM(_a))(INDEX( _t,,3)) , {""@"",_t_dolya , _t_predl , "" ""}))(_t_mp_stat_tov), _t_raw_rez,{_t_mp_stat_tov;_t_"&"mp_stat_itog}, _t_ord, LET( _t_nrs, '1-1 Сбор КП'!$C$1:$C30, _t_ids, '1-1 Сбор КП'!$Z$1:$Z30, _t_fr, MATCH(""№"", _t_nrs, 0) + 1, _t_to, MATCH(""@"", _t_nrs, 0) - 1, {INDEX(_t_ids, _t_fr,1):INDEX(_t_ids, _t_to,1); ""@""}), rez,Byrow(_t_ord,LAMB"&"DA(o, ARRAYFORMULA( IFERROR(VLOOKUP(o,_t_raw_rez,{2,3,4},FALSE) , ) ))), rez )}"),"Доля ответов") -> Доля ответов | Q1: =IFERROR(__xludf.DUMMYFUNCTION("""COMPUTED_VALUE"""),"Предложение") -> Предложение | R1: =IFERROR(__xludf.DUMMYFUNCTION("""COMPUTED_VALUE"""),"Писем") -> Писем | S1: свободные | T1: свободные | U1: свободные | V1: свободные | W1: свободные | X1: свободные | Y1: свободные | Z1: Цены Начало | AA1: amkomplekt@mail.ru | AD1: sales@noemi-parts.ru | AG1: aa@kentek.ru | AJ1: dg@air-part.ru | AM1: 104@pnevmotek.com | AP1: vkorolev@rutector.ru | AS1: bmd@melcom-ural.ru | AV1: utkm@mail.ru | AY1: engelsfilter@mail.ru | BB1: rt@air-part.ru | BE1: order@techfil.ru | BH1: ca@air-part.ru (1) | BK1: ca@air-part.ru (2) | BN1: m.rulev@a-ac.ru | BQ1: zap-premium@mail.ru | BT1: otgruzka@proftool.ru | BW1: kononov@indust-group.ru | BZ1: r.staroverov@evlart.ru | CC1: e.omelyusik@evlart.ru | CF1: sale@dlv-rnd.ru | CI1: davidov@pressair.ru | HS1: Цены Конец | HT1: 1 цена | HU1: поставщик | HV1: 2 цена | HW1: поставщик | HX1: 3 цена | HY1: поставщик | ID1: Комментарий | IE1: Лучшие цены | IF1: CommentBlokStart | IL1: CommentBlokEnd | IQ1: КомментарийЭксперта | IR1: ТопЭксперта | IS1: CommentExpertBlokStart | JF1: CommentExpertBlokEnd
A2: Доллар | B2: ='4-1 Расчет рентабельности КП'!AJ43 -> #REF! | C2: 1 | D2: Масляный фильтр - Артикул 89781969 ESG-315 зав.№ F010451 | E2: ESG-315 зав. № F01045 | F2: шт. | G2: 3 | H2: 5 450,00 6 433,68 | I2: 16 350,00 19 301,04 | J2: 7, из них аналог 4 | Q2: =IFERROR(__xludf.DUMMYFUNCTION("""COMPUTED_VALUE"""),7.0) -> 7 | Z2: ID_T001 | BE2: 6900 | BF2: 5 рд | BG2: Масляный фильтр 89781969 [ Аналог SH/O8186 ] | BH2: 19500 | BI2: 18 нед | BJ2: Масляный фильтр - Артикул 89781969 (оригинал) | BK2: 8600 | BL2: нал | BM2: Масляный фильтр - Артикул 89781969 (аналог) | BQ2: 6250 | BR2: 7 рд | BS2: Фильтр масляный 89781969 аналог | BZ2: 6433.68 | CA2: нал | CB2: Масляный фильтр - Артикул 89781969 ESG-315 — Аналог | CF2: =814.69*B3 -> #REF! | CG2: 5 д | CH2: Масляный фильтр (арт. 85062259) | CI2: 5450 | CJ2: 5 рд | CK2: Масляный фильтр 89781969 = SH8186 | HT2: =IFERROR(SMALL($R2:$HS2,VALUE(LEFT(HT$1,1))),"") | HU2: =IFERROR(OFFSET($AA$1,0,MATCH(HT2,$AA2:$HS2,0)),"") | HV2: =IFERROR(SMALL($AA2:$HS2,VALUE(LEFT(HV$1,1))),"") | HW2: =IFERROR(OFFSET($A$1,0,MATCH(HV2,$AA2:$HS2,0)),"") | HX2: =IFERROR(SMALL($AA2:$HS2,VALUE(LEFT(HX$1,1))),"") | HY2: =IFERROR(OFFSET($AA$1,0,MATCH(HX2,$AA2:$HS2,0)),"") | ID2: =IFERROR(__xludf.DUMMYFUNCTION(" IFERROR( TEXTJOIN(""|||"",FALSE , ARRAY_CONSTRAIN( SORT( ARRAYFORMULA(Split(TRANSPOSE (Split(TEXTJOIN(""|||"",TRUE,'1-1 Сбор КП'!$IF2:$IL2),""|||"",FALSE,FALSE) ),""|"",FALSE,FALSE)),3,FALSE ),100,2) ) ,)"),"") | IE2: =IFERROR(__xludf.DUMMYFUNCTION("LAMBDA(cc,тело,комент, комЭкс, порядок,показ, BYROW(тело, LAMBDA(r, TEXTJOIN(""|||"",FALSE,ARRAY_CONSTRAIN( Query( TRANSPOSE( { {ARRAYFORMULA( FILTER( ADDRESS(ROW(r), COLUMN(r) ), MOD(COLUMN(r)-cc,3)=0))}; {ARRAYFORMULA( FILTER( ADDRESS(1, COLUMN(r) ), MO"&"D(COLUMN(r)-cc,3)=0))}; {ARRAYFORMULA( IFERROR(VLOOKUP( FILTER( ADDRESS(1, COLUMN(r) ), MOD(COLUMN(r)-cc,3)=0), { TRANSPOSE (FILTER( {SPLIT(INDEX(комент,1,0),""|||"",FALSE,FALSE)}, ARRAYFORMULA( ISODD({SEQUENCE(1, COLUMNS(SPLIT(INDEX(комент,1,0),""|||"&""",FALSE,FALSE) ), 1, 1)})))) , TRANSPOSE (FILTER( {SPLIT(INDEX(комент,1,0),""|||"",FALSE,FALSE)}, ARRAYFORMULA( ISEVEN({SEQUENCE(1, COLUMNS( SPLIT(INDEX(комент,1,0),""|||"",FALSE,FALSE) ), 1, 1)}))))} ,2,0 ),""""))}; {ARRAYFORMULA( FILTER( ADDRESS(RO"&"W(r), COLUMN(r) ), MOD(COLUMN(r)-cc,3)=1))}; {ARRAYFORMULA( Lambda(f,m,""Подходит: ""& IFERROR( VLOOKUP( f, комЭкс, 4,0 ),""-?"")&"", ""& m&"" ""&IFERROR(VLOOKUP( f, комЭкс, 2,0 ),)&"" ""&IFERROR(VLOOKUP( f, комЭкс, 3,0 ),) ) ( FILTER( ADDRESS(1, COLUM"&"N(r) ), MOD(COLUMN(r)-cc,3)=0), FILTER( r, MOD(COLUMN(r)-cc,3)=2) ) ) }; {ARRAYFORMULA( FILTER( r, MOD(COLUMN(r)-cc,3)=0))}; BYCOL({ARRAYFORMULA( FILTER( ""'1-1 Сбор КП'!""&""R1C""&COLUMN(r) , MOD(COLUMN(r)-cc,3)=0))},LAMBDA(aa, LAMBDA(a,ifs ( IFERR"&"OR(FIND(""(♠)"",a),0)<>0,IFERROR( VLOOKUP(""♠"",порядок,2,FALSE),5), IFERROR(FIND(""(♦️)"",a),0)<>0,IFERROR( VLOOKUP(""♦️"",порядок,2,FALSE),5), IFERROR(FIND(""(♣️)"",a),0)<>0,IFERROR( VLOOKUP(""♣️"",порядок,2,FALSE),5), IFERROR(FIND(""(♥️)"",a),0)<>0,IFE"&"RROR( VLOOKUP(""♥️"",порядок,2,FALSE),5), TRUE,IFERROR( VLOOKUP(""-"",порядок,2,FALSE),5) ))(INDIRECT( aa,FALSE) ) )); BYCOL({ARRAYFORMULA( FILTER( ""'1-1 Сбор КП'!""&""R1C""&COLUMN(r) , MOD(COLUMN(r)-cc,3)=0))},LAMBDA(aa, LAMBDA(a,ifs ( IFERROR(FIND"&"(""(♠)"",a),0)<>0,IFERROR( VLOOKUP(""♠"",показ,2,FALSE),TRUE), IFERROR(FIND(""(♦️)"",a),0)<>0,IFERROR( VLOOKUP(""♦️"",показ,2,FALSE),TRUE), IFERROR(FIND(""(♣️)"",a),0)<>0,IFERROR( VLOOKUP(""♣️"",показ,2,FALSE),TRUE), IFERROR(FIND(""(♥️)"",a),0)<>0,IFERROR"&"( VLOOKUP(""♥️"",показ,2,FALSE),TRUE), TRUE,IFERROR( VLOOKUP(""-"",показ,2,FALSE),TRUE) ))(INDIRECT( aa,FALSE) ) )) }),""Select * Where Col6 is not null and Col8=true Order by Col7, Col6"",0),7,5)) ) ) ) ( COLUMN('1-1 Сбор КП'!$AA2), '1-1 Сбор КП'!$A"&"A2:$HS2, '1-1 Сбор КП'!$ID2, BYROW( TRANSPOSE(Split('1-1 Сбор КП'!$IQ2,""|||"",FALSE)),LAMBDA(rc,Split(rc,""📎"",FALSE,FALSE))), {'3-3 Выбор поставщиков'!$AB$24:$AB$28 , '3-3 Выбор поставщиков'!$AF$24:$AF$28}, {'3-3 Выбор поставщиков'!$AB$24:$AB$28 ,"&" '3-3 Выбор поставщиков'!$AD$24:$AD$28} )"),"$CI$2|||$CI$1||||||$CJ$2|||Подходит: Осн поставщик, Масляный фильтр 89781969 = SH8186 |||$BQ$2|||$BQ$1||||||$BR$2|||Подходит: Да, Фильтр масляный 89781969 аналог |||$BZ$2|||$BZ$1||||||$CA$2|||Подходит: -?, Масляный фильтр - Артикул 89781969 ESG-315 — "&"Аналог |||$BE$2|||$BE$1||||||$BF$2|||Подходит: Да, Масляный фильтр 89781969 [ Аналог SH/O8186 ] |||$BK$2|||$BK$1||||||$BL$2|||Подходит: -?, Масляный фильтр - Артикул 89781969 (аналог) |||$BH$2|||$BH$1||||||$BI$2|||Подходит: -?, Масляный фильтр - Артик"&"ул 89781969 (оригинал) ") -> $CI$2|||$CI$1||||||$CJ$2|||Подходит: Осн поставщик, Масляный фильтр 89781969 = SH8186 |||$BQ$2|||$BQ$1||||||$BR$2|||Подходит: Да, Фильтр масляный 89781969 аналог |||$BZ$2|||$BZ$1||||||$CA$2|||Подходит: -?, Масляный фильтр - Артикул 89781969 ESG-315 — Аналог |||$BE$2|||$BE$1||||||$BF$2|||Подходит: Да, Масляный фильтр 89781969 [ Аналог SH/O8186 ] |||$BK$2|||$BK$1||||||$BL$2|||Подходит: -?, Масляный фильтр - Артикул 89781969 (аналог) |||$BH$2|||$BH$1||||||$BI$2|||Подходит: -?, Масляный фильтр - Артикул 89781969 (оригинал) | IQ2: =IFERROR(__xludf.DUMMYFUNCTION(" IFERROR( TEXTJOIN(""|||"",true , BYROW( ARRAY_CONSTRAIN( SORT( ARRAYFORMULA( Split( TRANSPOSE ( Split(TEXTJOIN(""|||"", TRUE, '1-1 Сбор КП'!$IS2:$JF2) ,""|||"",FALSE,FALSE) ),""📎"",FALSE,FALSE"&")),5,FALSE ),100,4) ,LAMBDA(r,TEXTJOIN(""📎"",FALSE ,r)) ) ,))"),"$BQ$1📎📎📎Да|||$CI$1📎📎📎Осн поставщик|||$CI$1📎📎📎Осн поставщик|||$BE$1📎📎📎Да|||$BE$1📎📎📎Да|||$BQ$1📎📎📎Осн поставщик") -> $BQ$1📎📎📎Да|||$CI$1📎📎📎Осн поставщик|||$CI$1📎📎📎Осн поставщик|||$BE$1📎📎📎Да|||$BE$1📎📎📎Да|||$BQ$1📎📎📎Осн поставщик | IR2: =IFERROR(__xludf.DUMMYFUNCTION(" LAMBDA(cc,тело,комент,комЭкс,BYROW(тело,LAMBDA(r, TEXTJOIN(""|||"",FALSE, ARRAY_CONSTRAIN( Query( TRANSPOSE( { { ARRAYFORMULA( FILTER( ADDRESS(ROW(r), COLUMN(r) ), MOD(COLUMN(r)-cc,3)=0)) }; { ARRAYFORMULA( FILTER( ADDRESS(1, COLUMN(r) ), MOD(COL"&"UMN(r)-cc,3)=0)) }; { ARRAYFORMULA( FILTER( ADDRESS(ROW(r), COLUMN(r) ), MOD(COLUMN(r)-cc,3)=1)) }; { ARRAYFORMULA( FILTER( ADDRESS(ROW(r), COLUMN(r)+1 ), MOD(COLUMN(r)-cc,3)=1)) }; { ARRAYFORMULA( IFERROR(VLOOKUP( FILTER( ADDRESS(1,"&" COLUMN(r) ), MOD(COLUMN(r)-cc,3)=0),комЭкс,2,0 ),"""")) }; { ARRAYFORMULA( IFERROR(VLOOKUP( FILTER( ADDRESS(1, COLUMN(r) ), MOD(COLUMN(r)-cc,3)=0),комЭкс,3,0 ),"""")) }; { ARRAYFORMULA( IFERROR(VLOOKUP( FILTER( ADDRESS(1, COLUMN(r) ), MOD(COLUMN("&"r)-cc,3)=0),комЭкс,4,0 ),"""")) }; { ARRAYFORMULA( IFERROR(VLOOKUP( FILTER( ADDRESS(1, COLUMN(r) ), MOD(COLUMN(r)-cc,3)=0), { TRANSPOSE (FILTER( {SPLIT(INDEX(комент,1,0),""|||"",FALSE,FALSE)}, ARRAYFORMULA( ISODD({SEQUENCE(1, COLUMNS(SPLIT(INDEX(ком"&"ент,1,0),""|||"",FALSE,FALSE) ), 1, 1)})))) , TRANSPOSE (FILTER( {SPLIT(INDEX(комент,1,0),""|||"",FALSE,FALSE)}, ARRAYFORMULA( ISEVEN({SEQUENCE(1, COLUMNS( SPLIT(INDEX(комент,1,0),""|||"",FALSE,FALSE) ), 1, 1)}))))} ,2,0 ),"""")) }; { ARRAYFORMULA( FIL"&"TER( r, MOD(COLUMN(r)-cc,3)=0)) } } ),""Select * Where Col9 is not null Order by Col9"",0),14,8))) )) ( COLUMN('1-1 Сбор КП'!$AA2), '1-1 Сбор КП'!$AA2:$HS2, '1-1 Сбор КП'!$ID2, BYROW( TRANSPOSE(Split('1-1 Сбор КП'!$IQ2,""|||"",FALSE)),LAMBDA(rc,Sp"&"lit(rc,""📎"",FALSE,FALSE))) ) "),"$CI$2|||$CI$1|||$CJ$2|||$CK$2|||||||||Осн поставщик||||||$BQ$2|||$BQ$1|||$BR$2|||$BS$2|||||||||Да||||||$BZ$2|||$BZ$1|||$CA$2|||$CB$2|||||||||||||||$BE$2|||$BE$1|||$BF$2|||$BG$2|||||||||Да||||||$BK$2|||$BK$1|||$BL$2|||$BM$2|||||||||||||||$BH$2|||$BH$1|||$B"&"I$2|||$BJ$2||||||||||||") -> $CI$2|||$CI$1|||$CJ$2|||$CK$2|||||||||Осн поставщик||||||$BQ$2|||$BQ$1|||$BR$2|||$BS$2|||||||||Да||||||$BZ$2|||$BZ$1|||$CA$2|||$CB$2|||||||||||||||$BE$2|||$BE$1|||$BF$2|||$BG$2|||||||||Да||||||$BK$2|||$BK$1|||$BL$2|||$BM$2|||||||||||||||$BH$2|||$BH$1|||$BI$2|||$BJ$2|||||||||||| | IS2: $BQ$1📎📎📎Осн поставщик📎1791373921834|||$BE$1📎📎📎Да📎1791375018979|||$CI$1📎📎📎Осн поставщик📎1791880838684 | IT2: $BQ$1📎📎📎Да📎1791880954777|||$BE$1📎📎📎Да📎1791375018979|||$CI$1📎📎📎Осн поставщик📎1791880838684
A3: Евро | B3: ='4-1 Расчет рентабельности КП'!AJ44 -> #REF! | C3: 2 | D3: Масляный фильтр - Артикул 85062259 | E3: ESG-315 зав.№ 17030008 VS-250; ESM-200 | F3: шт. | G3: 6 | H3: 5 450,00 11 956,00 | I3: 32 700,00 71 736,00 | J3: 7, из них аналог 4 | Q3: =IFERROR(__xludf.DUMMYFUNCTION("""COMPUTED_VALUE"""),7.0) -> 7 | Z3: ID_T002 | BE3: 6900 | BF3: 5 рд | BG3: Масляный фильтр 85062259 [ Аналог SH/O8186 ] | BH3: 17700 | BI3: 18 нед | BJ3: Масляный фильтр - Артикул 85062259 (оригинал) | BK3: 8600 | BL3: нал | BM3: Масляный фильтр - Артикул 85062259 (аналог) | BQ3: 6400 | BR3: 7 рд | BS3: Фильтр масляный 85062259 аналог | BT3: =528.14*1.22*B3 -> #REF! | BU3: нал | BV3: 85062259 Масляный фильтр | BZ3: 11956 | CA3: нал | CB3: Масляный фильтр - Артикул 85062259 | CI3: 5450 | CJ3: 5 рд | CK3: Масляный фильтр 85062259 = SH8186 | HT3: =IFERROR(SMALL($R3:$HS3,VALUE(LEFT(HT$1,1))),"") | HU3: =IFERROR(OFFSET($AA$1,0,MATCH(HT3,$AA3:$HS3,0)),"") | HV3: =IFERROR(SMALL($AA3:$HS3,VALUE(LEFT(HV$1,1))),"") | HW3: =IFERROR(OFFSET($A$1,0,MATCH(HV3,$AA3:$HS3,0)),"") | HX3: =IFERROR(SMALL($AA3:$HS3,VALUE(LEFT(HX$1,1))),"") | HY3: =IFERROR(OFFSET($AA$1,0,MATCH(HX3,$AA3:$HS3,0)),"") | ID3: =IFERROR(__xludf.DUMMYFUNCTION(" IFERROR( TEXTJOIN(""|||"",FALSE , ARRAY_CONSTRAIN( SORT( ARRAYFORMULA(Split(TRANSPOSE (Split(TEXTJOIN(""|||"",TRUE,'1-1 Сбор КП'!$IF3:$IL3),""|||"",FALSE,FALSE) ),""|"",FALSE,FALSE)),3,FALSE ),100,2) ) ,)"),"") | IE3: =IFERROR(__xludf.DUMMYFUNCTION("LAMBDA(cc,тело,комент, комЭкс, порядок,показ, BYROW(тело, LAMBDA(r, TEXTJOIN(""|||"",FALSE,ARRAY_CONSTRAIN( Query( TRANSPOSE( { {ARRAYFORMULA( FILTER( ADDRESS(ROW(r), COLUMN(r) ), MOD(COLUMN(r)-cc,3)=0))}; {ARRAYFORMULA( FILTER( ADDRESS(1, COLUMN(r) ), MO"&"D(COLUMN(r)-cc,3)=0))}; {ARRAYFORMULA( IFERROR(VLOOKUP( FILTER( ADDRESS(1, COLUMN(r) ), MOD(COLUMN(r)-cc,3)=0), { TRANSPOSE (FILTER( {SPLIT(INDEX(комент,1,0),""|||"",FALSE,FALSE)}, ARRAYFORMULA( ISODD({SEQUENCE(1, COLUMNS(SPLIT(INDEX(комент,1,0),""|||"&""",FALSE,FALSE) ), 1, 1)})))) , TRANSPOSE (FILTER( {SPLIT(INDEX(комент,1,0),""|||"",FALSE,FALSE)}, ARRAYFORMULA( ISEVEN({SEQUENCE(1, COLUMNS( SPLIT(INDEX(комент,1,0),""|||"",FALSE,FALSE) ), 1, 1)}))))} ,2,0 ),""""))}; {ARRAYFORMULA( FILTER( ADDRESS(RO"&"W(r), COLUMN(r) ), MOD(COLUMN(r)-cc,3)=1))}; {ARRAYFORMULA( Lambda(f,m,""Подходит: ""& IFERROR( VLOOKUP( f, комЭкс, 4,0 ),""-?"")&"", ""& m&"" ""&IFERROR(VLOOKUP( f, комЭкс, 2,0 ),)&"" ""&IFERROR(VLOOKUP( f, комЭкс, 3,0 ),) ) ( FILTER( ADDRESS(1, COLUM"&"N(r) ), MOD(COLUMN(r)-cc,3)=0), FILTER( r, MOD(COLUMN(r)-cc,3)=2) ) ) }; {ARRAYFORMULA( FILTER( r, MOD(COLUMN(r)-cc,3)=0))}; BYCOL({ARRAYFORMULA( FILTER( ""'1-1 Сбор КП'!""&""R1C""&COLUMN(r) , MOD(COLUMN(r)-cc,3)=0))},LAMBDA(aa, LAMBDA(a,ifs ( IFERR"&"OR(FIND(""(♠)"",a),0)<>0,IFERROR( VLOOKUP(""♠"",порядок,2,FALSE),5), IFERROR(FIND(""(♦️)"",a),0)<>0,IFERROR( VLOOKUP(""♦️"",порядок,2,FALSE),5), IFERROR(FIND(""(♣️)"",a),0)<>0,IFERROR( VLOOKUP(""♣️"",порядок,2,FALSE),5), IFERROR(FIND(""(♥️)"",a),0)<>0,IFE"&"RROR( VLOOKUP(""♥️"",порядок,2,FALSE),5), TRUE,IFERROR( VLOOKUP(""-"",порядок,2,FALSE),5) ))(INDIRECT( aa,FALSE) ) )); BYCOL({ARRAYFORMULA( FILTER( ""'1-1 Сбор КП'!""&""R1C""&COLUMN(r) , MOD(COLUMN(r)-cc,3)=0))},LAMBDA(aa, LAMBDA(a,ifs ( IFERROR(FIND"&"(""(♠)"",a),0)<>0,IFERROR( VLOOKUP(""♠"",показ,2,FALSE),TRUE), IFERROR(FIND(""(♦️)"",a),0)<>0,IFERROR( VLOOKUP(""♦️"",показ,2,FALSE),TRUE), IFERROR(FIND(""(♣️)"",a),0)<>0,IFERROR( VLOOKUP(""♣️"",показ,2,FALSE),TRUE), IFERROR(FIND(""(♥️)"",a),0)<>0,IFERROR"&"( VLOOKUP(""♥️"",показ,2,FALSE),TRUE), TRUE,IFERROR( VLOOKUP(""-"",показ,2,FALSE),TRUE) ))(INDIRECT( aa,FALSE) ) )) }),""Select * Where Col6 is not null and Col8=true Order by Col7, Col6"",0),7,5)) ) ) ) ( COLUMN('1-1 Сбор КП'!$AA3), '1-1 Сбор КП'!$A"&"A3:$HS3, '1-1 Сбор КП'!$ID3, BYROW( TRANSPOSE(Split('1-1 Сбор КП'!$IQ3,""|||"",FALSE)),LAMBDA(rc,Split(rc,""📎"",FALSE,FALSE))), {'3-3 Выбор поставщиков'!$AB$24:$AB$28 , '3-3 Выбор поставщиков'!$AF$24:$AF$28}, {'3-3 Выбор поставщиков'!$AB$24:$AB$28 ,"&" '3-3 Выбор поставщиков'!$AD$24:$AD$28} )"),"$CI$3|||$CI$1||||||$CJ$3|||Подходит: Осн поставщик, Масляный фильтр 85062259 = SH8186 |||$BQ$3|||$BQ$1||||||$BR$3|||Подходит: Да, Фильтр масляный 85062259 аналог |||$BE$3|||$BE$1||||||$BF$3|||Подходит: Да, Масляный фильтр 85062259 [ Аналог SH/O8186 ] "&"|||$BK$3|||$BK$1||||||$BL$3|||Подходит: -?, Масляный фильтр - Артикул 85062259 (аналог) |||$BZ$3|||$BZ$1||||||$CA$3|||Подходит: -?, Масляный фильтр - Артикул 85062259 |||$BH$3|||$BH$1||||||$BI$3|||Подходит: -?, Масляный фильтр - Артикул 85062259 (ориги"&"нал) ") -> $CI$3|||$CI$1||||||$CJ$3|||Подходит: Осн поставщик, Масляный фильтр 85062259 = SH8186 |||$BQ$3|||$BQ$1||||||$BR$3|||Подходит: Да, Фильтр масляный 85062259 аналог |||$BE$3|||$BE$1||||||$BF$3|||Подходит: Да, Масляный фильтр 85062259 [ Аналог SH/O8186 ] |||$BK$3|||$BK$1||||||$BL$3|||Подходит: -?, Масляный фильтр - Артикул 85062259 (аналог) |||$BZ$3|||$BZ$1||||||$CA$3|||Подходит: -?, Масляный фильтр - Артикул 85062259 |||$BH$3|||$BH$1||||||$BI$3|||Подходит: -?, Масляный фильтр - Артикул 85062259 (оригинал) | IQ3: =IFERROR(__xludf.DUMMYFUNCTION(" IFERROR( TEXTJOIN(""|||"",true , BYROW( ARRAY_CONSTRAIN( SORT( ARRAYFORMULA( Split( TRANSPOSE ( Split(TEXTJOIN(""|||"", TRUE, '1-1 Сбор КП'!$IS3:$JF3) ,""|||"",FALSE,FALSE) ),""📎"",FALSE,FALSE"&")),5,FALSE ),100,4) ,LAMBDA(r,TEXTJOIN(""📎"",FALSE ,r)) ) ,))"),"$BQ$1📎📎📎Да|||$CI$1📎📎📎Осн поставщик|||$CI$1📎📎📎Осн поставщик|||$BE$1📎📎📎Да|||$BE$1📎📎📎Да|||$BQ$1📎📎📎Осн поставщик") -> $BQ$1📎📎📎Да|||$CI$1📎📎📎Осн поставщик|||$CI$1📎📎📎Осн поставщик|||$BE$1📎📎📎Да|||$BE$1📎📎📎Да|||$BQ$1📎📎📎Осн поставщик | IR3: =IFERROR(__xludf.DUMMYFUNCTION(" LAMBDA(cc,тело,комент,комЭкс,BYROW(тело,LAMBDA(r, TEXTJOIN(""|||"",FALSE, ARRAY_CONSTRAIN( Query( TRANSPOSE( { { ARRAYFORMULA( FILTER( ADDRESS(ROW(r), COLUMN(r) ), MOD(COLUMN(r)-cc,3)=0)) }; { ARRAYFORMULA( FILTER( ADDRESS(1, COLUMN(r) ), MOD(COL"&"UMN(r)-cc,3)=0)) }; { ARRAYFORMULA( FILTER( ADDRESS(ROW(r), COLUMN(r) ), MOD(COLUMN(r)-cc,3)=1)) }; { ARRAYFORMULA( FILTER( ADDRESS(ROW(r), COLUMN(r)+1 ), MOD(COLUMN(r)-cc,3)=1)) }; { ARRAYFORMULA( IFERROR(VLOOKUP( FILTER( ADDRESS(1,"&" COLUMN(r) ), MOD(COLUMN(r)-cc,3)=0),комЭкс,2,0 ),"""")) }; { ARRAYFORMULA( IFERROR(VLOOKUP( FILTER( ADDRESS(1, COLUMN(r) ), MOD(COLUMN(r)-cc,3)=0),комЭкс,3,0 ),"""")) }; { ARRAYFORMULA( IFERROR(VLOOKUP( FILTER( ADDRESS(1, COLUMN(r) ), MOD(COLUMN("&"r)-cc,3)=0),комЭкс,4,0 ),"""")) }; { ARRAYFORMULA( IFERROR(VLOOKUP( FILTER( ADDRESS(1, COLUMN(r) ), MOD(COLUMN(r)-cc,3)=0), { TRANSPOSE (FILTER( {SPLIT(INDEX(комент,1,0),""|||"",FALSE,FALSE)}, ARRAYFORMULA( ISODD({SEQUENCE(1, COLUMNS(SPLIT(INDEX(ком"&"ент,1,0),""|||"",FALSE,FALSE) ), 1, 1)})))) , TRANSPOSE (FILTER( {SPLIT(INDEX(комент,1,0),""|||"",FALSE,FALSE)}, ARRAYFORMULA( ISEVEN({SEQUENCE(1, COLUMNS( SPLIT(INDEX(комент,1,0),""|||"",FALSE,FALSE) ), 1, 1)}))))} ,2,0 ),"""")) }; { ARRAYFORMULA( FIL"&"TER( r, MOD(COLUMN(r)-cc,3)=0)) } } ),""Select * Where Col9 is not null Order by Col9"",0),14,8))) )) ( COLUMN('1-1 Сбор КП'!$AA3), '1-1 Сбор КП'!$AA3:$HS3, '1-1 Сбор КП'!$ID3, BYROW( TRANSPOSE(Split('1-1 Сбор КП'!$IQ3,""|||"",FALSE)),LAMBDA(rc,Sp"&"lit(rc,""📎"",FALSE,FALSE))) ) "),"$CI$3|||$CI$1|||$CJ$3|||$CK$3|||||||||Осн поставщик||||||$BQ$3|||$BQ$1|||$BR$3|||$BS$3|||||||||Да||||||$BE$3|||$BE$1|||$BF$3|||$BG$3|||||||||Да||||||$BK$3|||$BK$1|||$BL$3|||$BM$3|||||||||||||||$BZ$3|||$BZ$1|||$CA$3|||$CB$3|||||||||||||||$BH$3|||$BH$1|||$B"&"I$3|||$BJ$3||||||||||||") -> $CI$3|||$CI$1|||$CJ$3|||$CK$3|||||||||Осн поставщик||||||$BQ$3|||$BQ$1|||$BR$3|||$BS$3|||||||||Да||||||$BE$3|||$BE$1|||$BF$3|||$BG$3|||||||||Да||||||$BK$3|||$BK$1|||$BL$3|||$BM$3|||||||||||||||$BZ$3|||$BZ$1|||$CA$3|||$CB$3|||||||||||||||$BH$3|||$BH$1|||$BI$3|||$BJ$3|||||||||||| | IS3: $BQ$1📎📎📎Осн поставщик📎1791373995630|||$BE$1📎📎📎Да📎1791375565363|||$CI$1📎📎📎Осн поставщик📎1791880880186 | IT3: $BQ$1📎📎📎Да📎1791880963114|||$BE$1📎📎📎Да📎1791375565363|||$CI$1📎📎📎Осн поставщик📎1791880880186
A4: CNY | B4: ='4-1 Расчет рентабельности КП'!AJ45 -> #REF! | C4: 3 | D4: Воздушный фильтр - Артикул 85067179 | E4: ESG-315 зав.№ F010451; ESG-315 зав.№ 17030008 VS-250; ESM-200; «Gardner Denver» | F4: шт. | G4: 16 | H4: 4 700,00 4 902,00 | I4: 75 200,00 78 432,00 | J4: 8, из них аналог 4 | Q4: =IFERROR(__xludf.DUMMYFUNCTION("""COMPUTED_VALUE"""),8.0) -> 8 | Z4: ID_T003 | BE4: 6400 | BF4: 5 рд | BG4: Воздушный фильтр 85067179 [ Аналог A0584/AG0378 ] | BH4: 19800 | BI4: 18 нед | BJ4: Воздушный фильтр - Артикул 85067179 (оригинал) | BK4: 6500 | BL4: нал | BM4: Воздушный фильтр - Артикул 85067179 (аналог) | BQ4: 4700 | BR4: 7 рд | BS4: Фильтр воздушный 85067179 аналог | BT4: =415.05*1.22*B3 -> #REF! | BU4: нал | BV4: 85067179 Воздушный фильтр | BZ4: 4902 | CA4: нал | CB4: Воздушный фильтр - Артикул 85067179 Аналог | CF4: =639.82*B3 -> #REF! | CG4: 5 д | CH4: Воздушный фильтр (арт. 85067179) | CI4: 5000 | CJ4: 5 рд | CK4: Воздушный фильтр 85067179 = AG0378 | HT4: =IFERROR(SMALL($R4:$HS4,VALUE(LEFT(HT$1,1))),"") | HU4: =IFERROR(OFFSET($AA$1,0,MATCH(HT4,$AA4:$HS4,0)),"") | HV4: =IFERROR(SMALL($AA4:$HS4,VALUE(LEFT(HV$1,1))),"") | HW4: =IFERROR(OFFSET($A$1,0,MATCH(HV4,$AA4:$HS4,0)),"") | HX4: =IFERROR(SMALL($AA4:$HS4,VALUE(LEFT(HX$1,1))),"") | HY4: =IFERROR(OFFSET($AA$1,0,MATCH(HX4,$AA4:$HS4,0)),"") | ID4: =IFERROR(__xludf.DUMMYFUNCTION(" IFERROR( TEXTJOIN(""|||"",FALSE , ARRAY_CONSTRAIN( SORT( ARRAYFORMULA(Split(TRANSPOSE (Split(TEXTJOIN(""|||"",TRUE,'1-1 Сбор КП'!$IF4:$IL4),""|||"",FALSE,FALSE) ),""|"",FALSE,FALSE)),3,FALSE ),100,2) ) ,)"),"") | IE4: =IFERROR(__xludf.DUMMYFUNCTION("LAMBDA(cc,тело,комент, комЭкс, порядок,показ, BYROW(тело, LAMBDA(r, TEXTJOIN(""|||"",FALSE,ARRAY_CONSTRAIN( Query( TRANSPOSE( { {ARRAYFORMULA( FILTER( ADDRESS(ROW(r), COLUMN(r) ), MOD(COLUMN(r)-cc,3)=0))}; {ARRAYFORMULA( FILTER( ADDRESS(1, COLUMN(r) ), MO"&"D(COLUMN(r)-cc,3)=0))}; {ARRAYFORMULA( IFERROR(VLOOKUP( FILTER( ADDRESS(1, COLUMN(r) ), MOD(COLUMN(r)-cc,3)=0), { TRANSPOSE (FILTER( {SPLIT(INDEX(комент,1,0),""|||"",FALSE,FALSE)}, ARRAYFORMULA( ISODD({SEQUENCE(1, COLUMNS(SPLIT(INDEX(комент,1,0),""|||"&""",FALSE,FALSE) ), 1, 1)})))) , TRANSPOSE (FILTER( {SPLIT(INDEX(комент,1,0),""|||"",FALSE,FALSE)}, ARRAYFORMULA( ISEVEN({SEQUENCE(1, COLUMNS( SPLIT(INDEX(комент,1,0),""|||"",FALSE,FALSE) ), 1, 1)}))))} ,2,0 ),""""))}; {ARRAYFORMULA( FILTER( ADDRESS(RO"&"W(r), COLUMN(r) ), MOD(COLUMN(r)-cc,3)=1))}; {ARRAYFORMULA( Lambda(f,m,""Подходит: ""& IFERROR( VLOOKUP( f, комЭкс, 4,0 ),""-?"")&"", ""& m&"" ""&IFERROR(VLOOKUP( f, комЭкс, 2,0 ),)&"" ""&IFERROR(VLOOKUP( f, комЭкс, 3,0 ),) ) ( FILTER( ADDRESS(1, COLUM"&"N(r) ), MOD(COLUMN(r)-cc,3)=0), FILTER( r, MOD(COLUMN(r)-cc,3)=2) ) ) }; {ARRAYFORMULA( FILTER( r, MOD(COLUMN(r)-cc,3)=0))}; BYCOL({ARRAYFORMULA( FILTER( ""'1-1 Сбор КП'!""&""R1C""&COLUMN(r) , MOD(COLUMN(r)-cc,3)=0))},LAMBDA(aa, LAMBDA(a,ifs ( IFERR"&"OR(FIND(""(♠)"",a),0)<>0,IFERROR( VLOOKUP(""♠"",порядок,2,FALSE),5), IFERROR(FIND(""(♦️)"",a),0)<>0,IFERROR( VLOOKUP(""♦️"",порядок,2,FALSE),5), IFERROR(FIND(""(♣️)"",a),0)<>0,IFERROR( VLOOKUP(""♣️"",порядок,2,FALSE),5), IFERROR(FIND(""(♥️)"",a),0)<>0,IFE"&"RROR( VLOOKUP(""♥️"",порядок,2,FALSE),5), TRUE,IFERROR( VLOOKUP(""-"",порядок,2,FALSE),5) ))(INDIRECT( aa,FALSE) ) )); BYCOL({ARRAYFORMULA( FILTER( ""'1-1 Сбор КП'!""&""R1C""&COLUMN(r) , MOD(COLUMN(r)-cc,3)=0))},LAMBDA(aa, LAMBDA(a,ifs ( IFERROR(FIND"&"(""(♠)"",a),0)<>0,IFERROR( VLOOKUP(""♠"",показ,2,FALSE),TRUE), IFERROR(FIND(""(♦️)"",a),0)<>0,IFERROR( VLOOKUP(""♦️"",показ,2,FALSE),TRUE), IFERROR(FIND(""(♣️)"",a),0)<>0,IFERROR( VLOOKUP(""♣️"",показ,2,FALSE),TRUE), IFERROR(FIND(""(♥️)"",a),0)<>0,IFERROR"&"( VLOOKUP(""♥️"",показ,2,FALSE),TRUE), TRUE,IFERROR( VLOOKUP(""-"",показ,2,FALSE),TRUE) ))(INDIRECT( aa,FALSE) ) )) }),""Select * Where Col6 is not null and Col8=true Order by Col7, Col6"",0),7,5)) ) ) ) ( COLUMN('1-1 Сбор КП'!$AA4), '1-1 Сбор КП'!$A"&"A4:$HS4, '1-1 Сбор КП'!$ID4, BYROW( TRANSPOSE(Split('1-1 Сбор КП'!$IQ4,""|||"",FALSE)),LAMBDA(rc,Split(rc,""📎"",FALSE,FALSE))), {'3-3 Выбор поставщиков'!$AB$24:$AB$28 , '3-3 Выбор поставщиков'!$AF$24:$AF$28}, {'3-3 Выбор поставщиков'!$AB$24:$AB$28 ,"&" '3-3 Выбор поставщиков'!$AD$24:$AD$28} )"),"$BQ$4|||$BQ$1||||||$BR$4|||Подходит: Осн поставщик, Фильтр воздушный 85067179 аналог |||$BZ$4|||$BZ$1||||||$CA$4|||Подходит: -?, Воздушный фильтр - Артикул 85067179 Аналог |||$CI$4|||$CI$1||||||$CJ$4|||Подходит: -?, Воздушный фильтр 85067179 = AG0378 "&" |||$BE$4|||$BE$1||||||$BF$4|||Подходит: Да, Воздушный фильтр 85067179 [ Аналог A0584/AG0378 ] |||$BK$4|||$BK$1||||||$BL$4|||Подходит: -?, Воздушный фильтр - Артикул 85067179 (аналог) |||$BH$4|||$BH$1||||||$BI$4|||Подходит: -?, Воздушный фильтр - Артику"&"л 85067179 (оригинал) ") -> $BQ$4|||$BQ$1||||||$BR$4|||Подходит: Осн поставщик, Фильтр воздушный 85067179 аналог |||$BZ$4|||$BZ$1||||||$CA$4|||Подходит: -?, Воздушный фильтр - Артикул 85067179 Аналог |||$CI$4|||$CI$1||||||$CJ$4|||Подходит: -?, Воздушный фильтр 85067179 = AG0378 |||$BE$4|||$BE$1||||||$BF$4|||Подходит: Да, Воздушный фильтр 85067179 [ Аналог A0584/AG0378 ] |||$BK$4|||$BK$1||||||$BL$4|||Подходит: -?, Воздушный фильтр - Артикул 85067179 (аналог) |||$BH$4|||$BH$1||||||$BI$4|||Подходит: -?, Воздушный фильтр - Артикул 85067179 (оригинал) | IQ4: =IFERROR(__xludf.DUMMYFUNCTION(" IFERROR( TEXTJOIN(""|||"",true , BYROW( ARRAY_CONSTRAIN( SORT( ARRAYFORMULA( Split( TRANSPOSE ( Split(TEXTJOIN(""|||"", TRUE, '1-1 Сбор КП'!$IS4:$JF4) ,""|||"",FALSE,FALSE) ),""📎"",FALSE,FALSE"&")),5,FALSE ),100,4) ,LAMBDA(r,TEXTJOIN(""📎"",FALSE ,r)) ) ,))"),"$BE$1📎📎📎Да|||$BQ$1📎📎📎Осн поставщик|||$BQ$1📎📎📎Осн поставщик") -> $BE$1📎📎📎Да|||$BQ$1📎📎📎Осн поставщик|||$BQ$1📎📎📎Осн поставщик | IR4: =IFERROR(__xludf.DUMMYFUNCTION(" LAMBDA(cc,тело,комент,комЭкс,BYROW(тело,LAMBDA(r, TEXTJOIN(""|||"",FALSE, ARRAY_CONSTRAIN( Query( TRANSPOSE( { { ARRAYFORMULA( FILTER( ADDRESS(ROW(r), COLUMN(r) ), MOD(COLUMN(r)-cc,3)=0)) }; { ARRAYFORMULA( FILTER( ADDRESS(1, COLUMN(r) ), MOD(COL"&"UMN(r)-cc,3)=0)) }; { ARRAYFORMULA( FILTER( ADDRESS(ROW(r), COLUMN(r) ), MOD(COLUMN(r)-cc,3)=1)) }; { ARRAYFORMULA( FILTER( ADDRESS(ROW(r), COLUMN(r)+1 ), MOD(COLUMN(r)-cc,3)=1)) }; { ARRAYFORMULA( IFERROR(VLOOKUP( FILTER( ADDRESS(1,"&" COLUMN(r) ), MOD(COLUMN(r)-cc,3)=0),комЭкс,2,0 ),"""")) }; { ARRAYFORMULA( IFERROR(VLOOKUP( FILTER( ADDRESS(1, COLUMN(r) ), MOD(COLUMN(r)-cc,3)=0),комЭкс,3,0 ),"""")) }; { ARRAYFORMULA( IFERROR(VLOOKUP( FILTER( ADDRESS(1, COLUMN(r) ), MOD(COLUMN("&"r)-cc,3)=0),комЭкс,4,0 ),"""")) }; { ARRAYFORMULA( IFERROR(VLOOKUP( FILTER( ADDRESS(1, COLUMN(r) ), MOD(COLUMN(r)-cc,3)=0), { TRANSPOSE (FILTER( {SPLIT(INDEX(комент,1,0),""|||"",FALSE,FALSE)}, ARRAYFORMULA( ISODD({SEQUENCE(1, COLUMNS(SPLIT(INDEX(ком"&"ент,1,0),""|||"",FALSE,FALSE) ), 1, 1)})))) , TRANSPOSE (FILTER( {SPLIT(INDEX(комент,1,0),""|||"",FALSE,FALSE)}, ARRAYFORMULA( ISEVEN({SEQUENCE(1, COLUMNS( SPLIT(INDEX(комент,1,0),""|||"",FALSE,FALSE) ), 1, 1)}))))} ,2,0 ),"""")) }; { ARRAYFORMULA( FIL"&"TER( r, MOD(COLUMN(r)-cc,3)=0)) } } ),""Select * Where Col9 is not null Order by Col9"",0),14,8))) )) ( COLUMN('1-1 Сбор КП'!$AA4), '1-1 Сбор КП'!$AA4:$HS4, '1-1 Сбор КП'!$ID4, BYROW( TRANSPOSE(Split('1-1 Сбор КП'!$IQ4,""|||"",FALSE)),LAMBDA(rc,Sp"&"lit(rc,""📎"",FALSE,FALSE))) ) "),"$BQ$4|||$BQ$1|||$BR$4|||$BS$4|||||||||Осн поставщик||||||$BZ$4|||$BZ$1|||$CA$4|||$CB$4|||||||||||||||$CI$4|||$CI$1|||$CJ$4|||$CK$4|||||||||||||||$BE$4|||$BE$1|||$BF$4|||$BG$4|||||||||Да||||||$BK$4|||$BK$1|||$BL$4|||$BM$4|||||||||||||||$BH$4|||$BH$1|||$BI$"&"4|||$BJ$4||||||||||||") -> $BQ$4|||$BQ$1|||$BR$4|||$BS$4|||||||||Осн поставщик||||||$BZ$4|||$BZ$1|||$CA$4|||$CB$4|||||||||||||||$CI$4|||$CI$1|||$CJ$4|||$CK$4|||||||||||||||$BE$4|||$BE$1|||$BF$4|||$BG$4|||||||||Да||||||$BK$4|||$BK$1|||$BL$4|||$BM$4|||||||||||||||$BH$4|||$BH$1|||$BI$4|||$BJ$4|||||||||||| | IS4: $BQ$1📎📎📎Осн поставщик📎1791374014362 | IT4: $BQ$1📎📎📎Осн поставщик📎1791374014362|||$BE$1📎📎📎Да📎1791375584506
C5: 4 | D5: Термостат в сборе ESM-200; «Gardner Denver» | E5: ESM-200; «Gardner Denver» | F5: шт. | G5: 2 | H5: 0,00 0,00 | I5: 0,00 0,00 | J5: Мало, всего 0 | Q5: =IFERROR(__xludf.DUMMYFUNCTION("""COMPUTED_VALUE"""),0.0) -> 0 | Z5: ID_T004 | HT5: =IFERROR(SMALL($R5:$HS5,VALUE(LEFT(HT$1,1))),"") | HU5: =IFERROR(OFFSET($AA$1,0,MATCH(HT5,$AA5:$HS5,0)),"") | HV5: =IFERROR(SMALL($AA5:$HS5,VALUE(LEFT(HV$1,1))),"") | HW5: =IFERROR(OFFSET($A$1,0,MATCH(HV5,$AA5:$HS5,0)),"") | HX5: =IFERROR(SMALL($AA5:$HS5,VALUE(LEFT(HX$1,1))),"") | HY5: =IFERROR(OFFSET($AA$1,0,MATCH(HX5,$AA5:$HS5,0)),"") | ID5: =IFERROR(__xludf.DUMMYFUNCTION(" IFERROR( TEXTJOIN(""|||"",FALSE , ARRAY_CONSTRAIN( SORT( ARRAYFORMULA(Split(TRANSPOSE (Split(TEXTJOIN(""|||"",TRUE,'1-1 Сбор КП'!$IF5:$IL5),""|||"",FALSE,FALSE) ),""|"",FALSE,FALSE)),3,FALSE ),100,2) ) ,)"),"") | IE5: =IFERROR(__xludf.DUMMYFUNCTION("LAMBDA(cc,тело,комент, комЭкс, порядок,показ, BYROW(тело, LAMBDA(r, TEXTJOIN(""|||"",FALSE,ARRAY_CONSTRAIN( Query( TRANSPOSE( { {ARRAYFORMULA( FILTER( ADDRESS(ROW(r), COLUMN(r) ), MOD(COLUMN(r)-cc,3)=0))}; {ARRAYFORMULA( FILTER( ADDRESS(1, COLUMN(r) ), MO"&"D(COLUMN(r)-cc,3)=0))}; {ARRAYFORMULA( IFERROR(VLOOKUP( FILTER( ADDRESS(1, COLUMN(r) ), MOD(COLUMN(r)-cc,3)=0), { TRANSPOSE (FILTER( {SPLIT(INDEX(комент,1,0),""|||"",FALSE,FALSE)}, ARRAYFORMULA( ISODD({SEQUENCE(1, COLUMNS(SPLIT(INDEX(комент,1,0),""|||"&""",FALSE,FALSE) ), 1, 1)})))) , TRANSPOSE (FILTER( {SPLIT(INDEX(комент,1,0),""|||"",FALSE,FALSE)}, ARRAYFORMULA( ISEVEN({SEQUENCE(1, COLUMNS( SPLIT(INDEX(комент,1,0),""|||"",FALSE,FALSE) ), 1, 1)}))))} ,2,0 ),""""))}; {ARRAYFORMULA( FILTER( ADDRESS(RO"&"W(r), COLUMN(r) ), MOD(COLUMN(r)-cc,3)=1))}; {ARRAYFORMULA( Lambda(f,m,""Подходит: ""& IFERROR( VLOOKUP( f, комЭкс, 4,0 ),""-?"")&"", ""& m&"" ""&IFERROR(VLOOKUP( f, комЭкс, 2,0 ),)&"" ""&IFERROR(VLOOKUP( f, комЭкс, 3,0 ),) ) ( FILTER( ADDRESS(1, COLUM"&"N(r) ), MOD(COLUMN(r)-cc,3)=0), FILTER( r, MOD(COLUMN(r)-cc,3)=2) ) ) }; {ARRAYFORMULA( FILTER( r, MOD(COLUMN(r)-cc,3)=0))}; BYCOL({ARRAYFORMULA( FILTER( ""'1-1 Сбор КП'!""&""R1C""&COLUMN(r) , MOD(COLUMN(r)-cc,3)=0))},LAMBDA(aa, LAMBDA(a,ifs ( IFERR"&"OR(FIND(""(♠)"",a),0)<>0,IFERROR( VLOOKUP(""♠"",порядок,2,FALSE),5), IFERROR(FIND(""(♦️)"",a),0)<>0,IFERROR( VLOOKUP(""♦️"",порядок,2,FALSE),5), IFERROR(FIND(""(♣️)"",a),0)<>0,IFERROR( VLOOKUP(""♣️"",порядок,2,FALSE),5), IFERROR(FIND(""(♥️)"",a),0)<>0,IFE"&"RROR( VLOOKUP(""♥️"",порядок,2,FALSE),5), TRUE,IFERROR( VLOOKUP(""-"",порядок,2,FALSE),5) ))(INDIRECT( aa,FALSE) ) )); BYCOL({ARRAYFORMULA( FILTER( ""'1-1 Сбор КП'!""&""R1C""&COLUMN(r) , MOD(COLUMN(r)-cc,3)=0))},LAMBDA(aa, LAMBDA(a,ifs ( IFERROR(FIND"&"(""(♠)"",a),0)<>0,IFERROR( VLOOKUP(""♠"",показ,2,FALSE),TRUE), IFERROR(FIND(""(♦️)"",a),0)<>0,IFERROR( VLOOKUP(""♦️"",показ,2,FALSE),TRUE), IFERROR(FIND(""(♣️)"",a),0)<>0,IFERROR( VLOOKUP(""♣️"",показ,2,FALSE),TRUE), IFERROR(FIND(""(♥️)"",a),0)<>0,IFERROR"&"( VLOOKUP(""♥️"",показ,2,FALSE),TRUE), TRUE,IFERROR( VLOOKUP(""-"",показ,2,FALSE),TRUE) ))(INDIRECT( aa,FALSE) ) )) }),""Select * Where Col6 is not null and Col8=true Order by Col7, Col6"",0),7,5)) ) ) ) ( COLUMN('1-1 Сбор КП'!$AA5), '1-1 Сбор КП'!$A"&"A5:$HS5, '1-1 Сбор КП'!$ID5, BYROW( TRANSPOSE(Split('1-1 Сбор КП'!$IQ5,""|||"",FALSE)),LAMBDA(rc,Split(rc,""📎"",FALSE,FALSE))), {'3-3 Выбор поставщиков'!$AB$24:$AB$28 , '3-3 Выбор поставщиков'!$AF$24:$AF$28}, {'3-3 Выбор поставщиков'!$AB$24:$AB$28 ,"&" '3-3 Выбор поставщиков'!$AD$24:$AD$28} )"),"#N/A") -> #N/A | IQ5: =IFERROR(__xludf.DUMMYFUNCTION(" IFERROR( TEXTJOIN(""|||"",true , BYROW( ARRAY_CONSTRAIN( SORT( ARRAYFORMULA( Split( TRANSPOSE ( Split(TEXTJOIN(""|||"", TRUE, '1-1 Сбор КП'!$IS5:$JF5) ,""|||"",FALSE,FALSE) ),""📎"",FALSE,FALSE"&")),5,FALSE ),100,4) ,LAMBDA(r,TEXTJOIN(""📎"",FALSE ,r)) ) ,))"),"") | IR5: =IFERROR(__xludf.DUMMYFUNCTION(" LAMBDA(cc,тело,комент,комЭкс,BYROW(тело,LAMBDA(r, TEXTJOIN(""|||"",FALSE, ARRAY_CONSTRAIN( Query( TRANSPOSE( { { ARRAYFORMULA( FILTER( ADDRESS(ROW(r), COLUMN(r) ), MOD(COLUMN(r)-cc,3)=0)) }; { ARRAYFORMULA( FILTER( ADDRESS(1, COLUMN(r) ), MOD(COL"&"UMN(r)-cc,3)=0)) }; { ARRAYFORMULA( FILTER( ADDRESS(ROW(r), COLUMN(r) ), MOD(COLUMN(r)-cc,3)=1)) }; { ARRAYFORMULA( FILTER( ADDRESS(ROW(r), COLUMN(r)+1 ), MOD(COLUMN(r)-cc,3)=1)) }; { ARRAYFORMULA( IFERROR(VLOOKUP( FILTER( ADDRESS(1,"&" COLUMN(r) ), MOD(COLUMN(r)-cc,3)=0),комЭкс,2,0 ),"""")) }; { ARRAYFORMULA( IFERROR(VLOOKUP( FILTER( ADDRESS(1, COLUMN(r) ), MOD(COLUMN(r)-cc,3)=0),комЭкс,3,0 ),"""")) }; { ARRAYFORMULA( IFERROR(VLOOKUP( FILTER( ADDRESS(1, COLUMN(r) ), MOD(COLUMN("&"r)-cc,3)=0),комЭкс,4,0 ),"""")) }; { ARRAYFORMULA( IFERROR(VLOOKUP( FILTER( ADDRESS(1, COLUMN(r) ), MOD(COLUMN(r)-cc,3)=0), { TRANSPOSE (FILTER( {SPLIT(INDEX(комент,1,0),""|||"",FALSE,FALSE)}, ARRAYFORMULA( ISODD({SEQUENCE(1, COLUMNS(SPLIT(INDEX(ком"&"ент,1,0),""|||"",FALSE,FALSE) ), 1, 1)})))) , TRANSPOSE (FILTER( {SPLIT(INDEX(комент,1,0),""|||"",FALSE,FALSE)}, ARRAYFORMULA( ISEVEN({SEQUENCE(1, COLUMNS( SPLIT(INDEX(комент,1,0),""|||"",FALSE,FALSE) ), 1, 1)}))))} ,2,0 ),"""")) }; { ARRAYFORMULA( FIL"&"TER( r, MOD(COLUMN(r)-cc,3)=0)) } } ),""Select * Where Col9 is not null Order by Col9"",0),14,8))) )) ( COLUMN('1-1 Сбор КП'!$AA5), '1-1 Сбор КП'!$AA5:$HS5, '1-1 Сбор КП'!$ID5, BYROW( TRANSPOSE(Split('1-1 Сбор КП'!$IQ5,""|||"",FALSE)),LAMBDA(rc,Sp"&"lit(rc,""📎"",FALSE,FALSE))) ) "),"#N/A") -> #N/A
A6: откл от ср | B6: 0.5 | C6: 5 | D6: Масляный сепаратор Артикул 03498328 | E6: ESS-18 «Gardner Denver» | F6: шт. | G6: 3 | H6: 9 900,00 11 956,00 | I6: 29 700,00 35 868,00 | J6: 8, из них аналог 4 | Q6: =IFERROR(__xludf.DUMMYFUNCTION("""COMPUTED_VALUE"""),8.0) -> 8 | Z6: ID_T005 | BE6: 12800 | BF6: 5 рд | BG6: Cепаратор 03498328 [ Аналог DA1118 ] | BH6: 16600 | BI6: 18 нед | BJ6: Масляный сепаратор Артикул 03498328 (оригинал) | BK6: 12900 | BL6: нал | BM6: Масляный сепаратор Артикул 03498328 (аналог) | BQ6: 12000 | BR6: 7 рд | BS6: Сепаратор 03498328 аналог | BT6: =564.63*1.22*B3 -> #REF! | BU6: 2 шт нал | BV6: CC1140542 Масляный сепаратор | BZ6: 11956 | CA6: 12 нед | CB6: Масляный сепаратор Артикул 03498328 | CF6: =871.29*B3 -> #REF! | CG6: 5 д | CH6: Сепаратор (арт. 03498328) | CI6: 9900 | CJ6: 5 рд | CK6: Масляный сепаратор 03498328 = DA1118 | HT6: =IFERROR(SMALL($R6:$HS6,VALUE(LEFT(HT$1,1))),"") | HU6: =IFERROR(OFFSET($AA$1,0,MATCH(HT6,$AA6:$HS6,0)),"") | HV6: =IFERROR(SMALL($AA6:$HS6,VALUE(LEFT(HV$1,1))),"") | HW6: =IFERROR(OFFSET($A$1,0,MATCH(HV6,$AA6:$HS6,0)),"") | HX6: =IFERROR(SMALL($AA6:$HS6,VALUE(LEFT(HX$1,1))),"") | HY6: =IFERROR(OFFSET($AA$1,0,MATCH(HX6,$AA6:$HS6,0)),"") | ID6: =IFERROR(__xludf.DUMMYFUNCTION(" IFERROR( TEXTJOIN(""|||"",FALSE , ARRAY_CONSTRAIN( SORT( ARRAYFORMULA(Split(TRANSPOSE (Split(TEXTJOIN(""|||"",TRUE,'1-1 Сбор КП'!$IF6:$IL6),""|||"",FALSE,FALSE) ),""|"",FALSE,FALSE)),3,FALSE ),100,2) ) ,)"),"") | IE6: =IFERROR(__xludf.DUMMYFUNCTION("LAMBDA(cc,тело,комент, комЭкс, порядок,показ, BYROW(тело, LAMBDA(r, TEXTJOIN(""|||"",FALSE,ARRAY_CONSTRAIN( Query( TRANSPOSE( { {ARRAYFORMULA( FILTER( ADDRESS(ROW(r), COLUMN(r) ), MOD(COLUMN(r)-cc,3)=0))}; {ARRAYFORMULA( FILTER( ADDRESS(1, COLUMN(r) ), MO"&"D(COLUMN(r)-cc,3)=0))}; {ARRAYFORMULA( IFERROR(VLOOKUP( FILTER( ADDRESS(1, COLUMN(r) ), MOD(COLUMN(r)-cc,3)=0), { TRANSPOSE (FILTER( {SPLIT(INDEX(комент,1,0),""|||"",FALSE,FALSE)}, ARRAYFORMULA( ISODD({SEQUENCE(1, COLUMNS(SPLIT(INDEX(комент,1,0),""|||"&""",FALSE,FALSE) ), 1, 1)})))) , TRANSPOSE (FILTER( {SPLIT(INDEX(комент,1,0),""|||"",FALSE,FALSE)}, ARRAYFORMULA( ISEVEN({SEQUENCE(1, COLUMNS( SPLIT(INDEX(комент,1,0),""|||"",FALSE,FALSE) ), 1, 1)}))))} ,2,0 ),""""))}; {ARRAYFORMULA( FILTER( ADDRESS(RO"&"W(r), COLUMN(r) ), MOD(COLUMN(r)-cc,3)=1))}; {ARRAYFORMULA( Lambda(f,m,""Подходит: ""& IFERROR( VLOOKUP( f, комЭкс, 4,0 ),""-?"")&"", ""& m&"" ""&IFERROR(VLOOKUP( f, комЭкс, 2,0 ),)&"" ""&IFERROR(VLOOKUP( f, комЭкс, 3,0 ),) ) ( FILTER( ADDRESS(1, COLUM"&"N(r) ), MOD(COLUMN(r)-cc,3)=0), FILTER( r, MOD(COLUMN(r)-cc,3)=2) ) ) }; {ARRAYFORMULA( FILTER( r, MOD(COLUMN(r)-cc,3)=0))}; BYCOL({ARRAYFORMULA( FILTER( ""'1-1 Сбор КП'!""&""R1C""&COLUMN(r) , MOD(COLUMN(r)-cc,3)=0))},LAMBDA(aa, LAMBDA(a,ifs ( IFERR"&"OR(FIND(""(♠)"",a),0)<>0,IFERROR( VLOOKUP(""♠"",порядок,2,FALSE),5), IFERROR(FIND(""(♦️)"",a),0)<>0,IFERROR( VLOOKUP(""♦️"",порядок,2,FALSE),5), IFERROR(FIND(""(♣️)"",a),0)<>0,IFERROR( VLOOKUP(""♣️"",порядок,2,FALSE),5), IFERROR(FIND(""(♥️)"",a),0)<>0,IFE"&"RROR( VLOOKUP(""♥️"",порядок,2,FALSE),5), TRUE,IFERROR( VLOOKUP(""-"",порядок,2,FALSE),5) ))(INDIRECT( aa,FALSE) ) )); BYCOL({ARRAYFORMULA( FILTER( ""'1-1 Сбор КП'!""&""R1C""&COLUMN(r) , MOD(COLUMN(r)-cc,3)=0))},LAMBDA(aa, LAMBDA(a,ifs ( IFERROR(FIND"&"(""(♠)"",a),0)<>0,IFERROR( VLOOKUP(""♠"",показ,2,FALSE),TRUE), IFERROR(FIND(""(♦️)"",a),0)<>0,IFERROR( VLOOKUP(""♦️"",показ,2,FALSE),TRUE), IFERROR(FIND(""(♣️)"",a),0)<>0,IFERROR( VLOOKUP(""♣️"",показ,2,FALSE),TRUE), IFERROR(FIND(""(♥️)"",a),0)<>0,IFERROR"&"( VLOOKUP(""♥️"",показ,2,FALSE),TRUE), TRUE,IFERROR( VLOOKUP(""-"",показ,2,FALSE),TRUE) ))(INDIRECT( aa,FALSE) ) )) }),""Select * Where Col6 is not null and Col8=true Order by Col7, Col6"",0),7,5)) ) ) ) ( COLUMN('1-1 Сбор КП'!$AA6), '1-1 Сбор КП'!$A"&"A6:$HS6, '1-1 Сбор КП'!$ID6, BYROW( TRANSPOSE(Split('1-1 Сбор КП'!$IQ6,""|||"",FALSE)),LAMBDA(rc,Split(rc,""📎"",FALSE,FALSE))), {'3-3 Выбор поставщиков'!$AB$24:$AB$28 , '3-3 Выбор поставщиков'!$AF$24:$AF$28}, {'3-3 Выбор поставщиков'!$AB$24:$AB$28 ,"&" '3-3 Выбор поставщиков'!$AD$24:$AD$28} )"),"$CI$6|||$CI$1||||||$CJ$6|||Подходит: Осн поставщик, Масляный сепаратор 03498328 = DA1118 |||$BZ$6|||$BZ$1||||||$CA$6|||Подходит: Да, Масляный сепаратор Артикул 03498328 |||$BQ$6|||$BQ$1||||||$BR$6|||Подходит: Да, Сепаратор 03498328 аналог |||$BE$6|||$B"&"E$1||||||$BF$6|||Подходит: Да, Cепаратор 03498328 [ Аналог DA1118 ] |||$BK$6|||$BK$1||||||$BL$6|||Подходит: -?, Масляный сепаратор Артикул 03498328 (аналог) |||$BH$6|||$BH$1||||||$BI$6|||Подходит: -?, Масляный сепаратор Артикул 03498328 (оригинал) ") -> $CI$6|||$CI$1||||||$CJ$6|||Подходит: Осн поставщик, Масляный сепаратор 03498328 = DA1118 |||$BZ$6|||$BZ$1||||||$CA$6|||Подходит: Да, Масляный сепаратор Артикул 03498328 |||$BQ$6|||$BQ$1||||||$BR$6|||Подходит: Да, Сепаратор 03498328 аналог |||$BE$6|||$BE$1||||||$BF$6|||Подходит: Да, Cепаратор 03498328 [ Аналог DA1118 ] |||$BK$6|||$BK$1||||||$BL$6|||Подходит: -?, Масляный сепаратор Артикул 03498328 (аналог) |||$BH$6|||$BH$1||||||$BI$6|||Подходит: -?, Масляный сепаратор Артикул 03498328 (оригинал) | IQ6: =IFERROR(__xludf.DUMMYFUNCTION(" IFERROR( TEXTJOIN(""|||"",true , BYROW( ARRAY_CONSTRAIN( SORT( ARRAYFORMULA( Split( TRANSPOSE ( Split(TEXTJOIN(""|||"", TRUE, '1-1 Сбор КП'!$IS6:$JF6) ,""|||"",FALSE,FALSE) ),""📎"",FALSE,FALSE"&")),5,FALSE ),100,4) ,LAMBDA(r,TEXTJOIN(""📎"",FALSE ,r)) ) ,))"),"$BZ$1📎📎📎Да|||$BQ$1📎📎📎Да|||$BQ$1📎📎📎Да|||$CI$1📎📎📎Осн поставщик|||$CI$1📎📎📎Осн поставщик|||$CI$1📎📎📎Осн поставщик|||$BE$1📎📎📎Да|||$BE$1📎📎📎Да|||$BE$1📎📎📎Да|||$BQ$1📎📎📎Осн поставщик") -> $BZ$1📎📎📎Да|||$BQ$1📎📎📎Да|||$BQ$1📎📎📎Да|||$CI$1📎📎📎Осн поставщик|||$CI$1📎📎📎Осн поставщик|||$CI$1📎📎📎Осн поставщик|||$BE$1📎📎📎Да|||$BE$1📎📎📎Да|||$BE$1📎📎📎Да|||$BQ$1📎📎📎Осн поставщик | IR6: =IFERROR(__xludf.DUMMYFUNCTION(" LAMBDA(cc,тело,комент,комЭкс,BYROW(тело,LAMBDA(r, TEXTJOIN(""|||"",FALSE, ARRAY_CONSTRAIN( Query( TRANSPOSE( { { ARRAYFORMULA( FILTER( ADDRESS(ROW(r), COLUMN(r) ), MOD(COLUMN(r)-cc,3)=0)) }; { ARRAYFORMULA( FILTER( ADDRESS(1, COLUMN(r) ), MOD(COL"&"UMN(r)-cc,3)=0)) }; { ARRAYFORMULA( FILTER( ADDRESS(ROW(r), COLUMN(r) ), MOD(COLUMN(r)-cc,3)=1)) }; { ARRAYFORMULA( FILTER( ADDRESS(ROW(r), COLUMN(r)+1 ), MOD(COLUMN(r)-cc,3)=1)) }; { ARRAYFORMULA( IFERROR(VLOOKUP( FILTER( ADDRESS(1,"&" COLUMN(r) ), MOD(COLUMN(r)-cc,3)=0),комЭкс,2,0 ),"""")) }; { ARRAYFORMULA( IFERROR(VLOOKUP( FILTER( ADDRESS(1, COLUMN(r) ), MOD(COLUMN(r)-cc,3)=0),комЭкс,3,0 ),"""")) }; { ARRAYFORMULA( IFERROR(VLOOKUP( FILTER( ADDRESS(1, COLUMN(r) ), MOD(COLUMN("&"r)-cc,3)=0),комЭкс,4,0 ),"""")) }; { ARRAYFORMULA( IFERROR(VLOOKUP( FILTER( ADDRESS(1, COLUMN(r) ), MOD(COLUMN(r)-cc,3)=0), { TRANSPOSE (FILTER( {SPLIT(INDEX(комент,1,0),""|||"",FALSE,FALSE)}, ARRAYFORMULA( ISODD({SEQUENCE(1, COLUMNS(SPLIT(INDEX(ком"&"ент,1,0),""|||"",FALSE,FALSE) ), 1, 1)})))) , TRANSPOSE (FILTER( {SPLIT(INDEX(комент,1,0),""|||"",FALSE,FALSE)}, ARRAYFORMULA( ISEVEN({SEQUENCE(1, COLUMNS( SPLIT(INDEX(комент,1,0),""|||"",FALSE,FALSE) ), 1, 1)}))))} ,2,0 ),"""")) }; { ARRAYFORMULA( FIL"&"TER( r, MOD(COLUMN(r)-cc,3)=0)) } } ),""Select * Where Col9 is not null Order by Col9"",0),14,8))) )) ( COLUMN('1-1 Сбор КП'!$AA6), '1-1 Сбор КП'!$AA6:$HS6, '1-1 Сбор КП'!$ID6, BYROW( TRANSPOSE(Split('1-1 Сбор КП'!$IQ6,""|||"",FALSE)),LAMBDA(rc,Sp"&"lit(rc,""📎"",FALSE,FALSE))) ) "),"$CI$6|||$CI$1|||$CJ$6|||$CK$6|||||||||Осн поставщик||||||$BZ$6|||$BZ$1|||$CA$6|||$CB$6|||||||||Да||||||$BQ$6|||$BQ$1|||$BR$6|||$BS$6|||||||||Да||||||$BE$6|||$BE$1|||$BF$6|||$BG$6|||||||||Да||||||$BK$6|||$BK$1|||$BL$6|||$BM$6|||||||||||||||$BH$6|||$BH$1|||"&"$BI$6|||$BJ$6||||||||||||") -> $CI$6|||$CI$1|||$CJ$6|||$CK$6|||||||||Осн поставщик||||||$BZ$6|||$BZ$1|||$CA$6|||$CB$6|||||||||Да||||||$BQ$6|||$BQ$1|||$BR$6|||$BS$6|||||||||Да||||||$BE$6|||$BE$1|||$BF$6|||$BG$6|||||||||Да||||||$BK$6|||$BK$1|||$BL$6|||$BM$6|||||||||||||||$BH$6|||$BH$1|||$BI$6|||$BJ$6|||||||||||| | IS6: $BQ$1📎📎📎Осн поставщик📎1791374087506|||$BE$1📎📎📎Да📎1791375710997|||$CI$1📎📎📎Осн поставщик📎1791880887101 | IT6: $BQ$1📎📎📎Да📎1791880995892|||$BE$1📎📎📎Да📎1791375710997|||$CI$1📎📎📎Осн поставщик📎1791880887101|||$BZ$1📎📎📎Да📎1791881141260 | IU6: $BQ$1📎📎📎Да📎1791880995892|||$BE$1📎📎📎Да📎1791375710997|||$CI$1📎📎📎Осн поставщик📎1791880887101
A7: Первые мин знач | C7: 6 | D7: Масляный фильтр Артикул 89675429 | E7: ESS-18 «Gardner Denver» | F7: шт. | G7: 3 | H7: 950,00 2 547,36 | I7: 2 850,00 7 642,08 | J7: 8, из них аналог 4 | Q7: =IFERROR(__xludf.DUMMYFUNCTION("""COMPUTED_VALUE"""),8.0) -> 8 | Z7: ID_T006 | BE7: 2750 | BF7: 5 рд | BG7: Масляный фильтр 89675429 [ Аналог SH8130 ] | BH7: 9800 | BI7: 18 нед | BJ7: Масляный фильтр Артикул 89675429 (оригинал) | BK7: 3900 | BL7: нал | BM7: Масляный фильтр Артикул 89675429 (аналог) | BQ7: 950 | BR7: 7 рд | BS7: Фильтр масляный 89675429 аналог | BT7: =109.68*1.22*B3 -> #REF! | BU7: 1 шт нал | BV7: 89675429 Масляный фильтр | BZ7: 2547.36 | CA7: 12 нед | CB7: Масляный фильтр Артикул 89675429 | CF7: =169.81*B3 -> #REF! | CG7: 5 д | CH7: Масляный фильтр (арт. 89675429) | CI7: 3650 | CJ7: 5 рд | CK7: Масляный фильтр 89675429 = SH8229 | HT7: =IFERROR(SMALL($R7:$HS7,VALUE(LEFT(HT$1,1))),"") | HU7: =IFERROR(OFFSET($AA$1,0,MATCH(HT7,$AA7:$HS7,0)),"") | HV7: =IFERROR(SMALL($AA7:$HS7,VALUE(LEFT(HV$1,1))),"") | HW7: =IFERROR(OFFSET($A$1,0,MATCH(HV7,$AA7:$HS7,0)),"") | HX7: =IFERROR(SMALL($AA7:$HS7,VALUE(LEFT(HX$1,1))),"") | HY7: =IFERROR(OFFSET($AA$1,0,MATCH(HX7,$AA7:$HS7,0)),"") | ID7: =IFERROR(__xludf.DUMMYFUNCTION(" IFERROR( TEXTJOIN(""|||"",FALSE , ARRAY_CONSTRAIN( SORT( ARRAYFORMULA(Split(TRANSPOSE (Split(TEXTJOIN(""|||"",TRUE,'1-1 Сбор КП'!$IF7:$IL7),""|||"",FALSE,FALSE) ),""|"",FALSE,FALSE)),3,FALSE ),100,2) ) ,)"),"") | IE7: =IFERROR(__xludf.DUMMYFUNCTION("LAMBDA(cc,тело,комент, комЭкс, порядок,показ, BYROW(тело, LAMBDA(r, TEXTJOIN(""|||"",FALSE,ARRAY_CONSTRAIN( Query( TRANSPOSE( { {ARRAYFORMULA( FILTER( ADDRESS(ROW(r), COLUMN(r) ), MOD(COLUMN(r)-cc,3)=0))}; {ARRAYFORMULA( FILTER( ADDRESS(1, COLUMN(r) ), MO"&"D(COLUMN(r)-cc,3)=0))}; {ARRAYFORMULA( IFERROR(VLOOKUP( FILTER( ADDRESS(1, COLUMN(r) ), MOD(COLUMN(r)-cc,3)=0), { TRANSPOSE (FILTER( {SPLIT(INDEX(комент,1,0),""|||"",FALSE,FALSE)}, ARRAYFORMULA( ISODD({SEQUENCE(1, COLUMNS(SPLIT(INDEX(комент,1,0),""|||"&""",FALSE,FALSE) ), 1, 1)})))) , TRANSPOSE (FILTER( {SPLIT(INDEX(комент,1,0),""|||"",FALSE,FALSE)}, ARRAYFORMULA( ISEVEN({SEQUENCE(1, COLUMNS( SPLIT(INDEX(комент,1,0),""|||"",FALSE,FALSE) ), 1, 1)}))))} ,2,0 ),""""))}; {ARRAYFORMULA( FILTER( ADDRESS(RO"&"W(r), COLUMN(r) ), MOD(COLUMN(r)-cc,3)=1))}; {ARRAYFORMULA( Lambda(f,m,""Подходит: ""& IFERROR( VLOOKUP( f, комЭкс, 4,0 ),""-?"")&"", ""& m&"" ""&IFERROR(VLOOKUP( f, комЭкс, 2,0 ),)&"" ""&IFERROR(VLOOKUP( f, комЭкс, 3,0 ),) ) ( FILTER( ADDRESS(1, COLUM"&"N(r) ), MOD(COLUMN(r)-cc,3)=0), FILTER( r, MOD(COLUMN(r)-cc,3)=2) ) ) }; {ARRAYFORMULA( FILTER( r, MOD(COLUMN(r)-cc,3)=0))}; BYCOL({ARRAYFORMULA( FILTER( ""'1-1 Сбор КП'!""&""R1C""&COLUMN(r) , MOD(COLUMN(r)-cc,3)=0))},LAMBDA(aa, LAMBDA(a,ifs ( IFERR"&"OR(FIND(""(♠)"",a),0)<>0,IFERROR( VLOOKUP(""♠"",порядок,2,FALSE),5), IFERROR(FIND(""(♦️)"",a),0)<>0,IFERROR( VLOOKUP(""♦️"",порядок,2,FALSE),5), IFERROR(FIND(""(♣️)"",a),0)<>0,IFERROR( VLOOKUP(""♣️"",порядок,2,FALSE),5), IFERROR(FIND(""(♥️)"",a),0)<>0,IFE"&"RROR( VLOOKUP(""♥️"",порядок,2,FALSE),5), TRUE,IFERROR( VLOOKUP(""-"",порядок,2,FALSE),5) ))(INDIRECT( aa,FALSE) ) )); BYCOL({ARRAYFORMULA( FILTER( ""'1-1 Сбор КП'!""&""R1C""&COLUMN(r) , MOD(COLUMN(r)-cc,3)=0))},LAMBDA(aa, LAMBDA(a,ifs ( IFERROR(FIND"&"(""(♠)"",a),0)<>0,IFERROR( VLOOKUP(""♠"",показ,2,FALSE),TRUE), IFERROR(FIND(""(♦️)"",a),0)<>0,IFERROR( VLOOKUP(""♦️"",показ,2,FALSE),TRUE), IFERROR(FIND(""(♣️)"",a),0)<>0,IFERROR( VLOOKUP(""♣️"",показ,2,FALSE),TRUE), IFERROR(FIND(""(♥️)"",a),0)<>0,IFERROR"&"( VLOOKUP(""♥️"",показ,2,FALSE),TRUE), TRUE,IFERROR( VLOOKUP(""-"",показ,2,FALSE),TRUE) ))(INDIRECT( aa,FALSE) ) )) }),""Select * Where Col6 is not null and Col8=true Order by Col7, Col6"",0),7,5)) ) ) ) ( COLUMN('1-1 Сбор КП'!$AA7), '1-1 Сбор КП'!$A"&"A7:$HS7, '1-1 Сбор КП'!$ID7, BYROW( TRANSPOSE(Split('1-1 Сбор КП'!$IQ7,""|||"",FALSE)),LAMBDA(rc,Split(rc,""📎"",FALSE,FALSE))), {'3-3 Выбор поставщиков'!$AB$24:$AB$28 , '3-3 Выбор поставщиков'!$AF$24:$AF$28}, {'3-3 Выбор поставщиков'!$AB$24:$AB$28 ,"&" '3-3 Выбор поставщиков'!$AD$24:$AD$28} )"),"$BQ$7|||$BQ$1||||||$BR$7|||Подходит: Осн поставщик, Фильтр масляный 89675429 аналог |||$BZ$7|||$BZ$1||||||$CA$7|||Подходит: Да, Масляный фильтр Артикул 89675429 |||$BE$7|||$BE$1||||||$BF$7|||Подходит: Да, Масляный фильтр 89675429 [ Аналог SH8130 ] |||"&"$CI$7|||$CI$1||||||$CJ$7|||Подходит: -?, Масляный фильтр 89675429 = SH8229 |||$BK$7|||$BK$1||||||$BL$7|||Подходит: -?, Масляный фильтр Артикул 89675429 (аналог) |||$BH$7|||$BH$1||||||$BI$7|||Подходит: -?, Масляный фильтр Артикул 89675429 (оригинал) ") -> $BQ$7|||$BQ$1||||||$BR$7|||Подходит: Осн поставщик, Фильтр масляный 89675429 аналог |||$BZ$7|||$BZ$1||||||$CA$7|||Подходит: Да, Масляный фильтр Артикул 89675429 |||$BE$7|||$BE$1||||||$BF$7|||Подходит: Да, Масляный фильтр 89675429 [ Аналог SH8130 ] |||$CI$7|||$CI$1||||||$CJ$7|||Подходит: -?, Масляный фильтр 89675429 = SH8229 |||$BK$7|||$BK$1||||||$BL$7|||Подходит: -?, Масляный фильтр Артикул 89675429 (аналог) |||$BH$7|||$BH$1||||||$BI$7|||Подходит: -?, Масляный фильтр Артикул 89675429 (оригинал) | IQ7: =IFERROR(__xludf.DUMMYFUNCTION(" IFERROR( TEXTJOIN(""|||"",true , BYROW( ARRAY_CONSTRAIN( SORT( ARRAYFORMULA( Split( TRANSPOSE ( Split(TEXTJOIN(""|||"", TRUE, '1-1 Сбор КП'!$IS7:$JF7) ,""|||"",FALSE,FALSE) ),""📎"",FALSE,FALSE"&")),5,FALSE ),100,4) ,LAMBDA(r,TEXTJOIN(""📎"",FALSE ,r)) ) ,))"),"$BZ$1📎📎📎Да|||$BE$1📎📎📎Да|||$BQ$1📎📎📎Осн поставщик|||$BQ$1📎📎📎Осн поставщик") -> $BZ$1📎📎📎Да|||$BE$1📎📎📎Да|||$BQ$1📎📎📎Осн поставщик|||$BQ$1📎📎📎Осн поставщик | IR7: =IFERROR(__xludf.DUMMYFUNCTION(" LAMBDA(cc,тело,комент,комЭкс,BYROW(тело,LAMBDA(r, TEXTJOIN(""|||"",FALSE, ARRAY_CONSTRAIN( Query( TRANSPOSE( { { ARRAYFORMULA( FILTER( ADDRESS(ROW(r), COLUMN(r) ), MOD(COLUMN(r)-cc,3)=0)) }; { ARRAYFORMULA( FILTER( ADDRESS(1, COLUMN(r) ), MOD(COL"&"UMN(r)-cc,3)=0)) }; { ARRAYFORMULA( FILTER( ADDRESS(ROW(r), COLUMN(r) ), MOD(COLUMN(r)-cc,3)=1)) }; { ARRAYFORMULA( FILTER( ADDRESS(ROW(r), COLUMN(r)+1 ), MOD(COLUMN(r)-cc,3)=1)) }; { ARRAYFORMULA( IFERROR(VLOOKUP( FILTER( ADDRESS(1,"&" COLUMN(r) ), MOD(COLUMN(r)-cc,3)=0),комЭкс,2,0 ),"""")) }; { ARRAYFORMULA( IFERROR(VLOOKUP( FILTER( ADDRESS(1, COLUMN(r) ), MOD(COLUMN(r)-cc,3)=0),комЭкс,3,0 ),"""")) }; { ARRAYFORMULA( IFERROR(VLOOKUP( FILTER( ADDRESS(1, COLUMN(r) ), MOD(COLUMN("&"r)-cc,3)=0),комЭкс,4,0 ),"""")) }; { ARRAYFORMULA( IFERROR(VLOOKUP( FILTER( ADDRESS(1, COLUMN(r) ), MOD(COLUMN(r)-cc,3)=0), { TRANSPOSE (FILTER( {SPLIT(INDEX(комент,1,0),""|||"",FALSE,FALSE)}, ARRAYFORMULA( ISODD({SEQUENCE(1, COLUMNS(SPLIT(INDEX(ком"&"ент,1,0),""|||"",FALSE,FALSE) ), 1, 1)})))) , TRANSPOSE (FILTER( {SPLIT(INDEX(комент,1,0),""|||"",FALSE,FALSE)}, ARRAYFORMULA( ISEVEN({SEQUENCE(1, COLUMNS( SPLIT(INDEX(комент,1,0),""|||"",FALSE,FALSE) ), 1, 1)}))))} ,2,0 ),"""")) }; { ARRAYFORMULA( FIL"&"TER( r, MOD(COLUMN(r)-cc,3)=0)) } } ),""Select * Where Col9 is not null Order by Col9"",0),14,8))) )) ( COLUMN('1-1 Сбор КП'!$AA7), '1-1 Сбор КП'!$AA7:$HS7, '1-1 Сбор КП'!$ID7, BYROW( TRANSPOSE(Split('1-1 Сбор КП'!$IQ7,""|||"",FALSE)),LAMBDA(rc,Sp"&"lit(rc,""📎"",FALSE,FALSE))) ) "),"$BQ$7|||$BQ$1|||$BR$7|||$BS$7|||||||||Осн поставщик||||||$BZ$7|||$BZ$1|||$CA$7|||$CB$7|||||||||Да||||||$BE$7|||$BE$1|||$BF$7|||$BG$7|||||||||Да||||||$CI$7|||$CI$1|||$CJ$7|||$CK$7|||||||||||||||$BK$7|||$BK$1|||$BL$7|||$BM$7|||||||||||||||$BH$7|||$BH$1|||$B"&"I$7|||$BJ$7||||||||||||") -> $BQ$7|||$BQ$1|||$BR$7|||$BS$7|||||||||Осн поставщик||||||$BZ$7|||$BZ$1|||$CA$7|||$CB$7|||||||||Да||||||$BE$7|||$BE$1|||$BF$7|||$BG$7|||||||||Да||||||$CI$7|||$CI$1|||$CJ$7|||$CK$7|||||||||||||||$BK$7|||$BK$1|||$BL$7|||$BM$7|||||||||||||||$BH$7|||$BH$1|||$BI$7|||$BJ$7|||||||||||| | IS7: $BQ$1📎📎📎Осн поставщик📎1791374620598 | IT7: $BQ$1📎📎📎Осн поставщик📎1791374620598|||$BE$1📎📎📎Да📎1791375880894|||$BZ$1📎📎📎Да📎1791881178358
A8: Мало ответов | B8: 3 | C8: 7 | D8: Воздушный фильтр - Артикул 81166609 | E8: ESS-18 «Gardner Denver» | F8: шт. | G8: 3 | H8: 1 600,00 2 275,00 | I8: 4 800,00 6 825,00 | J8: 8, из них аналог 4 | Q8: =IFERROR(__xludf.DUMMYFUNCTION("""COMPUTED_VALUE"""),8.0) -> 8 | Z8: ID_T007 | BE8: 1850 | BF8: 5 рд | BG8: Воздушный фильтр 81166609 [ Аналог SA6007 ] | BH8: 9500 | BI8: 18 нед | BJ8: Воздушный фильтр - Артикул 81166609 (оригинал) | BK8: 4400 | BL8: нал | BM8: Воздушный фильтр - Артикул 81166609 (аналог) | BQ8: 1900 | BR8: 7 рд | BS8: Фильтр воздушный 81166609 аналог | BT8: =64.59*1.22*B3 -> #REF! | BU8: нал | BV8: 81166609 Воздушный фильтр | BZ8: 2275 | CA8: 12 нед | CB8: Воздушный фильтр - Артикул 81166609 | CF8: =100.07*B3 -> #REF! | CG8: 5 д | CH8: Воздушный фильтр (арт. 81166609) | CI8: 1600 | CJ8: 5 рд | CK8: Воздушный фильтр 81166609 = SA6007 | HT8: =IFERROR(SMALL($R8:$HS8,VALUE(LEFT(HT$1,1))),"") | HU8: =IFERROR(OFFSET($AA$1,0,MATCH(HT8,$AA8:$HS8,0)),"") | HV8: =IFERROR(SMALL($AA8:$HS8,VALUE(LEFT(HV$1,1))),"") | HW8: =IFERROR(OFFSET($A$1,0,MATCH(HV8,$AA8:$HS8,0)),"") | HX8: =IFERROR(SMALL($AA8:$HS8,VALUE(LEFT(HX$1,1))),"") | HY8: =IFERROR(OFFSET($AA$1,0,MATCH(HX8,$AA8:$HS8,0)),"") | ID8: =IFERROR(__xludf.DUMMYFUNCTION(" IFERROR( TEXTJOIN(""|||"",FALSE , ARRAY_CONSTRAIN( SORT( ARRAYFORMULA(Split(TRANSPOSE (Split(TEXTJOIN(""|||"",TRUE,'1-1 Сбор КП'!$IF8:$IL8),""|||"",FALSE,FALSE) ),""|"",FALSE,FALSE)),3,FALSE ),100,2) ) ,)"),"") | IE8: =IFERROR(__xludf.DUMMYFUNCTION("LAMBDA(cc,тело,комент, комЭкс, порядок,показ, BYROW(тело, LAMBDA(r, TEXTJOIN(""|||"",FALSE,ARRAY_CONSTRAIN( Query( TRANSPOSE( { {ARRAYFORMULA( FILTER( ADDRESS(ROW(r), COLUMN(r) ), MOD(COLUMN(r)-cc,3)=0))}; {ARRAYFORMULA( FILTER( ADDRESS(1, COLUMN(r) ), MO"&"D(COLUMN(r)-cc,3)=0))}; {ARRAYFORMULA( IFERROR(VLOOKUP( FILTER( ADDRESS(1, COLUMN(r) ), MOD(COLUMN(r)-cc,3)=0), { TRANSPOSE (FILTER( {SPLIT(INDEX(комент,1,0),""|||"",FALSE,FALSE)}, ARRAYFORMULA( ISODD({SEQUENCE(1, COLUMNS(SPLIT(INDEX(комент,1,0),""|||"&""",FALSE,FALSE) ), 1, 1)})))) , TRANSPOSE (FILTER( {SPLIT(INDEX(комент,1,0),""|||"",FALSE,FALSE)}, ARRAYFORMULA( ISEVEN({SEQUENCE(1, COLUMNS( SPLIT(INDEX(комент,1,0),""|||"",FALSE,FALSE) ), 1, 1)}))))} ,2,0 ),""""))}; {ARRAYFORMULA( FILTER( ADDRESS(RO"&"W(r), COLUMN(r) ), MOD(COLUMN(r)-cc,3)=1))}; {ARRAYFORMULA( Lambda(f,m,""Подходит: ""& IFERROR( VLOOKUP( f, комЭкс, 4,0 ),""-?"")&"", ""& m&"" ""&IFERROR(VLOOKUP( f, комЭкс, 2,0 ),)&"" ""&IFERROR(VLOOKUP( f, комЭкс, 3,0 ),) ) ( FILTER( ADDRESS(1, COLUM"&"N(r) ), MOD(COLUMN(r)-cc,3)=0), FILTER( r, MOD(COLUMN(r)-cc,3)=2) ) ) }; {ARRAYFORMULA( FILTER( r, MOD(COLUMN(r)-cc,3)=0))}; BYCOL({ARRAYFORMULA( FILTER( ""'1-1 Сбор КП'!""&""R1C""&COLUMN(r) , MOD(COLUMN(r)-cc,3)=0))},LAMBDA(aa, LAMBDA(a,ifs ( IFERR"&"OR(FIND(""(♠)"",a),0)<>0,IFERROR( VLOOKUP(""♠"",порядок,2,FALSE),5), IFERROR(FIND(""(♦️)"",a),0)<>0,IFERROR( VLOOKUP(""♦️"",порядок,2,FALSE),5), IFERROR(FIND(""(♣️)"",a),0)<>0,IFERROR( VLOOKUP(""♣️"",порядок,2,FALSE),5), IFERROR(FIND(""(♥️)"",a),0)<>0,IFE"&"RROR( VLOOKUP(""♥️"",порядок,2,FALSE),5), TRUE,IFERROR( VLOOKUP(""-"",порядок,2,FALSE),5) ))(INDIRECT( aa,FALSE) ) )); BYCOL({ARRAYFORMULA( FILTER( ""'1-1 Сбор КП'!""&""R1C""&COLUMN(r) , MOD(COLUMN(r)-cc,3)=0))},LAMBDA(aa, LAMBDA(a,ifs ( IFERROR(FIND"&"(""(♠)"",a),0)<>0,IFERROR( VLOOKUP(""♠"",показ,2,FALSE),TRUE), IFERROR(FIND(""(♦️)"",a),0)<>0,IFERROR( VLOOKUP(""♦️"",показ,2,FALSE),TRUE), IFERROR(FIND(""(♣️)"",a),0)<>0,IFERROR( VLOOKUP(""♣️"",показ,2,FALSE),TRUE), IFERROR(FIND(""(♥️)"",a),0)<>0,IFERROR"&"( VLOOKUP(""♥️"",показ,2,FALSE),TRUE), TRUE,IFERROR( VLOOKUP(""-"",показ,2,FALSE),TRUE) ))(INDIRECT( aa,FALSE) ) )) }),""Select * Where Col6 is not null and Col8=true Order by Col7, Col6"",0),7,5)) ) ) ) ( COLUMN('1-1 Сбор КП'!$AA8), '1-1 Сбор КП'!$A"&"A8:$HS8, '1-1 Сбор КП'!$ID8, BYROW( TRANSPOSE(Split('1-1 Сбор КП'!$IQ8,""|||"",FALSE)),LAMBDA(rc,Split(rc,""📎"",FALSE,FALSE))), {'3-3 Выбор поставщиков'!$AB$24:$AB$28 , '3-3 Выбор поставщиков'!$AF$24:$AF$28}, {'3-3 Выбор поставщиков'!$AB$24:$AB$28 ,"&" '3-3 Выбор поставщиков'!$AD$24:$AD$28} )"),"$CI$8|||$CI$1||||||$CJ$8|||Подходит: Осн поставщик, Воздушный фильтр 81166609 = SA6007 |||$BE$8|||$BE$1||||||$BF$8|||Подходит: Да, Воздушный фильтр 81166609 [ Аналог SA6007 ] |||$BQ$8|||$BQ$1||||||$BR$8|||Подходит: Да, Фильтр воздушный 81166609 аналог "&"|||$BZ$8|||$BZ$1||||||$CA$8|||Подходит: -?, Воздушный фильтр - Артикул 81166609 |||$BK$8|||$BK$1||||||$BL$8|||Подходит: -?, Воздушный фильтр - Артикул 81166609 (аналог) |||$BH$8|||$BH$1||||||$BI$8|||Подходит: -?, Воздушный фильтр - Артикул 81166609 (ор"&"игинал) ") -> $CI$8|||$CI$1||||||$CJ$8|||Подходит: Осн поставщик, Воздушный фильтр 81166609 = SA6007 |||$BE$8|||$BE$1||||||$BF$8|||Подходит: Да, Воздушный фильтр 81166609 [ Аналог SA6007 ] |||$BQ$8|||$BQ$1||||||$BR$8|||Подходит: Да, Фильтр воздушный 81166609 аналог |||$BZ$8|||$BZ$1||||||$CA$8|||Подходит: -?, Воздушный фильтр - Артикул 81166609 |||$BK$8|||$BK$1||||||$BL$8|||Подходит: -?, Воздушный фильтр - Артикул 81166609 (аналог) |||$BH$8|||$BH$1||||||$BI$8|||Подходит: -?, Воздушный фильтр - Артикул 81166609 (оригинал) | IQ8: =IFERROR(__xludf.DUMMYFUNCTION(" IFERROR( TEXTJOIN(""|||"",true , BYROW( ARRAY_CONSTRAIN( SORT( ARRAYFORMULA( Split( TRANSPOSE ( Split(TEXTJOIN(""|||"", TRUE, '1-1 Сбор КП'!$IS8:$JF8) ,""|||"",FALSE,FALSE) ),""📎"",FALSE,FALSE"&")),5,FALSE ),100,4) ,LAMBDA(r,TEXTJOIN(""📎"",FALSE ,r)) ) ,))"),"$BQ$1📎📎📎Да|||$CI$1📎📎📎Осн поставщик|||$CI$1📎📎📎Осн поставщик|||$BQ$1📎📎📎Осн поставщик|||$BQ$1📎📎📎Осн поставщик|||$BE$1📎📎📎Да|||$BE$1📎📎📎Да|||$BE$1📎📎📎Да") -> $BQ$1📎📎📎Да|||$CI$1📎📎📎Осн поставщик|||$CI$1📎📎📎Осн поставщик|||$BQ$1📎📎📎Осн поставщик|||$BQ$1📎📎📎Осн поставщик|||$BE$1📎📎📎Да|||$BE$1📎📎📎Да|||$BE$1📎📎📎Да | IR8: =IFERROR(__xludf.DUMMYFUNCTION(" LAMBDA(cc,тело,комент,комЭкс,BYROW(тело,LAMBDA(r, TEXTJOIN(""|||"",FALSE, ARRAY_CONSTRAIN( Query( TRANSPOSE( { { ARRAYFORMULA( FILTER( ADDRESS(ROW(r), COLUMN(r) ), MOD(COLUMN(r)-cc,3)=0)) }; { ARRAYFORMULA( FILTER( ADDRESS(1, COLUMN(r) ), MOD(COL"&"UMN(r)-cc,3)=0)) }; { ARRAYFORMULA( FILTER( ADDRESS(ROW(r), COLUMN(r) ), MOD(COLUMN(r)-cc,3)=1)) }; { ARRAYFORMULA( FILTER( ADDRESS(ROW(r), COLUMN(r)+1 ), MOD(COLUMN(r)-cc,3)=1)) }; { ARRAYFORMULA( IFERROR(VLOOKUP( FILTER( ADDRESS(1,"&" COLUMN(r) ), MOD(COLUMN(r)-cc,3)=0),комЭкс,2,0 ),"""")) }; { ARRAYFORMULA( IFERROR(VLOOKUP( FILTER( ADDRESS(1, COLUMN(r) ), MOD(COLUMN(r)-cc,3)=0),комЭкс,3,0 ),"""")) }; { ARRAYFORMULA( IFERROR(VLOOKUP( FILTER( ADDRESS(1, COLUMN(r) ), MOD(COLUMN("&"r)-cc,3)=0),комЭкс,4,0 ),"""")) }; { ARRAYFORMULA( IFERROR(VLOOKUP( FILTER( ADDRESS(1, COLUMN(r) ), MOD(COLUMN(r)-cc,3)=0), { TRANSPOSE (FILTER( {SPLIT(INDEX(комент,1,0),""|||"",FALSE,FALSE)}, ARRAYFORMULA( ISODD({SEQUENCE(1, COLUMNS(SPLIT(INDEX(ком"&"ент,1,0),""|||"",FALSE,FALSE) ), 1, 1)})))) , TRANSPOSE (FILTER( {SPLIT(INDEX(комент,1,0),""|||"",FALSE,FALSE)}, ARRAYFORMULA( ISEVEN({SEQUENCE(1, COLUMNS( SPLIT(INDEX(комент,1,0),""|||"",FALSE,FALSE) ), 1, 1)}))))} ,2,0 ),"""")) }; { ARRAYFORMULA( FIL"&"TER( r, MOD(COLUMN(r)-cc,3)=0)) } } ),""Select * Where Col9 is not null Order by Col9"",0),14,8))) )) ( COLUMN('1-1 Сбор КП'!$AA8), '1-1 Сбор КП'!$AA8:$HS8, '1-1 Сбор КП'!$ID8, BYROW( TRANSPOSE(Split('1-1 Сбор КП'!$IQ8,""|||"",FALSE)),LAMBDA(rc,Sp"&"lit(rc,""📎"",FALSE,FALSE))) ) "),"$CI$8|||$CI$1|||$CJ$8|||$CK$8|||||||||Осн поставщик||||||$BE$8|||$BE$1|||$BF$8|||$BG$8|||||||||Да||||||$BQ$8|||$BQ$1|||$BR$8|||$BS$8|||||||||Да||||||$BZ$8|||$BZ$1|||$CA$8|||$CB$8|||||||||||||||$BK$8|||$BK$1|||$BL$8|||$BM$8|||||||||||||||$BH$8|||$BH$1|||$B"&"I$8|||$BJ$8||||||||||||") -> $CI$8|||$CI$1|||$CJ$8|||$CK$8|||||||||Осн поставщик||||||$BE$8|||$BE$1|||$BF$8|||$BG$8|||||||||Да||||||$BQ$8|||$BQ$1|||$BR$8|||$BS$8|||||||||Да||||||$BZ$8|||$BZ$1|||$CA$8|||$CB$8|||||||||||||||$BK$8|||$BK$1|||$BL$8|||$BM$8|||||||||||||||$BH$8|||$BH$1|||$BI$8|||$BJ$8|||||||||||| | IS8: $BE$1📎📎📎Да📎1791374693136|||$BQ$1📎📎📎Осн поставщик📎1791375981105|||$CI$1📎📎📎Осн поставщик📎1791881119851 | IT8: $BE$1📎📎📎Да📎1791374693136|||$BQ$1📎📎📎Осн поставщик📎1791375981105 | IU8: $BE$1📎📎📎Да📎1791374693136|||$BQ$1📎📎📎Да📎1791881191803|||$CI$1📎📎📎Осн поставщик📎1791881119851
A9: Инструкция | C9: 8 | D9: Сервисный набор арт. 2906020000 | E9: GA 200 зав. № APF133999; GA 250 зав. № APF133914; GA 250 зав. № APF 133915 «Atlas Copco» | F9: шт. | G9: 3 | H9: 156 500,00 42 883,00 | I9: 469 500,00 128 649,00 | J9: 5, из них аналог 1 | Q9: =IFERROR(__xludf.DUMMYFUNCTION("""COMPUTED_VALUE"""),5.0) -> 5 | Z9: ID_T008 | AM9: 156500 | AN9: 12 нед | AO9: Сервисный набор арт. 2906020000 GA 200 1 шт | AP9: 104000 | AQ9: 12 нед | AR9: 2906020000 AIR/OIL FILTER KIT | BB9: 417300 | BC9: 14 нед | BD9: 2906020000. | BW9: =1153.18*1.22*B3 -> #REF! | BX9: 17 нед | BY9: Набор фильтров арт. 2906020000 | CC9: =35150*1.22 -> 42883 | CD9: 15 нед | CE9: Сервисный набор Atlas Copco 2906020000 | HT9: =IFERROR(SMALL($R9:$HS9,VALUE(LEFT(HT$1,1))),"") | HU9: =IFERROR(OFFSET($AA$1,0,MATCH(HT9,$AA9:$HS9,0)),"") | HV9: =IFERROR(SMALL($AA9:$HS9,VALUE(LEFT(HV$1,1))),"") | HW9: =IFERROR(OFFSET($A$1,0,MATCH(HV9,$AA9:$HS9,0)),"") | HX9: =IFERROR(SMALL($AA9:$HS9,VALUE(LEFT(HX$1,1))),"") | HY9: =IFERROR(OFFSET($AA$1,0,MATCH(HX9,$AA9:$HS9,0)),"") | ID9: =IFERROR(__xludf.DUMMYFUNCTION(" IFERROR( TEXTJOIN(""|||"",FALSE , ARRAY_CONSTRAIN( SORT( ARRAYFORMULA(Split(TRANSPOSE (Split(TEXTJOIN(""|||"",TRUE,'1-1 Сбор КП'!$IF9:$IL9),""|||"",FALSE,FALSE) ),""|"",FALSE,FALSE)),3,FALSE ),100,2) ) ,)"),"") | IE9: =IFERROR(__xludf.DUMMYFUNCTION("LAMBDA(cc,тело,комент, комЭкс, порядок,показ, BYROW(тело, LAMBDA(r, TEXTJOIN(""|||"",FALSE,ARRAY_CONSTRAIN( Query( TRANSPOSE( { {ARRAYFORMULA( FILTER( ADDRESS(ROW(r), COLUMN(r) ), MOD(COLUMN(r)-cc,3)=0))}; {ARRAYFORMULA( FILTER( ADDRESS(1, COLUMN(r) ), MO"&"D(COLUMN(r)-cc,3)=0))}; {ARRAYFORMULA( IFERROR(VLOOKUP( FILTER( ADDRESS(1, COLUMN(r) ), MOD(COLUMN(r)-cc,3)=0), { TRANSPOSE (FILTER( {SPLIT(INDEX(комент,1,0),""|||"",FALSE,FALSE)}, ARRAYFORMULA( ISODD({SEQUENCE(1, COLUMNS(SPLIT(INDEX(комент,1,0),""|||"&""",FALSE,FALSE) ), 1, 1)})))) , TRANSPOSE (FILTER( {SPLIT(INDEX(комент,1,0),""|||"",FALSE,FALSE)}, ARRAYFORMULA( ISEVEN({SEQUENCE(1, COLUMNS( SPLIT(INDEX(комент,1,0),""|||"",FALSE,FALSE) ), 1, 1)}))))} ,2,0 ),""""))}; {ARRAYFORMULA( FILTER( ADDRESS(RO"&"W(r), COLUMN(r) ), MOD(COLUMN(r)-cc,3)=1))}; {ARRAYFORMULA( Lambda(f,m,""Подходит: ""& IFERROR( VLOOKUP( f, комЭкс, 4,0 ),""-?"")&"", ""& m&"" ""&IFERROR(VLOOKUP( f, комЭкс, 2,0 ),)&"" ""&IFERROR(VLOOKUP( f, комЭкс, 3,0 ),) ) ( FILTER( ADDRESS(1, COLUM"&"N(r) ), MOD(COLUMN(r)-cc,3)=0), FILTER( r, MOD(COLUMN(r)-cc,3)=2) ) ) }; {ARRAYFORMULA( FILTER( r, MOD(COLUMN(r)-cc,3)=0))}; BYCOL({ARRAYFORMULA( FILTER( ""'1-1 Сбор КП'!""&""R1C""&COLUMN(r) , MOD(COLUMN(r)-cc,3)=0))},LAMBDA(aa, LAMBDA(a,ifs ( IFERR"&"OR(FIND(""(♠)"",a),0)<>0,IFERROR( VLOOKUP(""♠"",порядок,2,FALSE),5), IFERROR(FIND(""(♦️)"",a),0)<>0,IFERROR( VLOOKUP(""♦️"",порядок,2,FALSE),5), IFERROR(FIND(""(♣️)"",a),0)<>0,IFERROR( VLOOKUP(""♣️"",порядок,2,FALSE),5), IFERROR(FIND(""(♥️)"",a),0)<>0,IFE"&"RROR( VLOOKUP(""♥️"",порядок,2,FALSE),5), TRUE,IFERROR( VLOOKUP(""-"",порядок,2,FALSE),5) ))(INDIRECT( aa,FALSE) ) )); BYCOL({ARRAYFORMULA( FILTER( ""'1-1 Сбор КП'!""&""R1C""&COLUMN(r) , MOD(COLUMN(r)-cc,3)=0))},LAMBDA(aa, LAMBDA(a,ifs ( IFERROR(FIND"&"(""(♠)"",a),0)<>0,IFERROR( VLOOKUP(""♠"",показ,2,FALSE),TRUE), IFERROR(FIND(""(♦️)"",a),0)<>0,IFERROR( VLOOKUP(""♦️"",показ,2,FALSE),TRUE), IFERROR(FIND(""(♣️)"",a),0)<>0,IFERROR( VLOOKUP(""♣️"",показ,2,FALSE),TRUE), IFERROR(FIND(""(♥️)"",a),0)<>0,IFERROR"&"( VLOOKUP(""♥️"",показ,2,FALSE),TRUE), TRUE,IFERROR( VLOOKUP(""-"",показ,2,FALSE),TRUE) ))(INDIRECT( aa,FALSE) ) )) }),""Select * Where Col6 is not null and Col8=true Order by Col7, Col6"",0),7,5)) ) ) ) ( COLUMN('1-1 Сбор КП'!$AA9), '1-1 Сбор КП'!$A"&"A9:$HS9, '1-1 Сбор КП'!$ID9, BYROW( TRANSPOSE(Split('1-1 Сбор КП'!$IQ9,""|||"",FALSE)),LAMBDA(rc,Split(rc,""📎"",FALSE,FALSE))), {'3-3 Выбор поставщиков'!$AB$24:$AB$28 , '3-3 Выбор поставщиков'!$AF$24:$AF$28}, {'3-3 Выбор поставщиков'!$AB$24:$AB$28 ,"&" '3-3 Выбор поставщиков'!$AD$24:$AD$28} )"),"$CC$9|||$CC$1||||||$CD$9|||Подходит: Осн поставщик, Сервисный набор Atlas Copco 2906020000 |||$AP$9|||$AP$1||||||$AQ$9|||Подходит: Да, 2906020000 AIR/OIL FILTER KIT |||$AM$9|||$AM$1||||||$AN$9|||Подходит: Уточнить параметры, Сервисный набор арт. 290602"&"0000 GA 200 1 шт непонятный аналог, 1 шт|||$BB$9|||$BB$1||||||$BC$9|||Подходит: -?, 2906020000. ") -> $CC$9|||$CC$1||||||$CD$9|||Подходит: Осн поставщик, Сервисный набор Atlas Copco 2906020000 |||$AP$9|||$AP$1||||||$AQ$9|||Подходит: Да, 2906020000 AIR/OIL FILTER KIT |||$AM$9|||$AM$1||||||$AN$9|||Подходит: Уточнить параметры, Сервисный набор арт. 2906020000 GA 200 1 шт непонятный аналог, 1 шт|||$BB$9|||$BB$1||||||$BC$9|||Подходит: -?, 2906020000. | IQ9: =IFERROR(__xludf.DUMMYFUNCTION(" IFERROR( TEXTJOIN(""|||"",true , BYROW( ARRAY_CONSTRAIN( SORT( ARRAYFORMULA( Split( TRANSPOSE ( Split(TEXTJOIN(""|||"", TRUE, '1-1 Сбор КП'!$IS9:$JF9) ,""|||"",FALSE,FALSE) ),""📎"",FALSE,FALSE"&")),5,FALSE ),100,4) ,LAMBDA(r,TEXTJOIN(""📎"",FALSE ,r)) ) ,))"),"$AP$1📎📎📎Да|||$CC$1📎📎📎Осн поставщик|||$CC$1📎📎📎Осн поставщик|||$AM$1📎📎непонятный аналог, 1 шт📎Уточнить параметры|||$AM$1📎📎непонятный аналог, 1 шт📎Уточнить параметры|||$AP$1📎📎📎Осн поставщик") -> $AP$1📎📎📎Да|||$CC$1📎📎📎Осн поставщик|||$CC$1📎📎📎Осн поставщик|||$AM$1📎📎непонятный аналог, 1 шт📎Уточнить параметры|||$AM$1📎📎непонятный аналог, 1 шт📎Уточнить параметры|||$AP$1📎📎📎Осн поставщик | IR9: =IFERROR(__xludf.DUMMYFUNCTION(" LAMBDA(cc,тело,комент,комЭкс,BYROW(тело,LAMBDA(r, TEXTJOIN(""|||"",FALSE, ARRAY_CONSTRAIN( Query( TRANSPOSE( { { ARRAYFORMULA( FILTER( ADDRESS(ROW(r), COLUMN(r) ), MOD(COLUMN(r)-cc,3)=0)) }; { ARRAYFORMULA( FILTER( ADDRESS(1, COLUMN(r) ), MOD(COL"&"UMN(r)-cc,3)=0)) }; { ARRAYFORMULA( FILTER( ADDRESS(ROW(r), COLUMN(r) ), MOD(COLUMN(r)-cc,3)=1)) }; { ARRAYFORMULA( FILTER( ADDRESS(ROW(r), COLUMN(r)+1 ), MOD(COLUMN(r)-cc,3)=1)) }; { ARRAYFORMULA( IFERROR(VLOOKUP( FILTER( ADDRESS(1,"&" COLUMN(r) ), MOD(COLUMN(r)-cc,3)=0),комЭкс,2,0 ),"""")) }; { ARRAYFORMULA( IFERROR(VLOOKUP( FILTER( ADDRESS(1, COLUMN(r) ), MOD(COLUMN(r)-cc,3)=0),комЭкс,3,0 ),"""")) }; { ARRAYFORMULA( IFERROR(VLOOKUP( FILTER( ADDRESS(1, COLUMN(r) ), MOD(COLUMN("&"r)-cc,3)=0),комЭкс,4,0 ),"""")) }; { ARRAYFORMULA( IFERROR(VLOOKUP( FILTER( ADDRESS(1, COLUMN(r) ), MOD(COLUMN(r)-cc,3)=0), { TRANSPOSE (FILTER( {SPLIT(INDEX(комент,1,0),""|||"",FALSE,FALSE)}, ARRAYFORMULA( ISODD({SEQUENCE(1, COLUMNS(SPLIT(INDEX(ком"&"ент,1,0),""|||"",FALSE,FALSE) ), 1, 1)})))) , TRANSPOSE (FILTER( {SPLIT(INDEX(комент,1,0),""|||"",FALSE,FALSE)}, ARRAYFORMULA( ISEVEN({SEQUENCE(1, COLUMNS( SPLIT(INDEX(комент,1,0),""|||"",FALSE,FALSE) ), 1, 1)}))))} ,2,0 ),"""")) }; { ARRAYFORMULA( FIL"&"TER( r, MOD(COLUMN(r)-cc,3)=0)) } } ),""Select * Where Col9 is not null Order by Col9"",0),14,8))) )) ( COLUMN('1-1 Сбор КП'!$AA9), '1-1 Сбор КП'!$AA9:$HS9, '1-1 Сбор КП'!$ID9, BYROW( TRANSPOSE(Split('1-1 Сбор КП'!$IQ9,""|||"",FALSE)),LAMBDA(rc,Sp"&"lit(rc,""📎"",FALSE,FALSE))) ) "),"$CC$9|||$CC$1|||$CD$9|||$CE$9|||||||||Осн поставщик||||||$AP$9|||$AP$1|||$AQ$9|||$AR$9|||||||||Да||||||$AM$9|||$AM$1|||$AN$9|||$AO$9||||||непонятный аналог, 1 шт|||Уточнить параметры||||||$BB$9|||$BB$1|||$BC$9|||$BD$9||||||||||||") -> $CC$9|||$CC$1|||$CD$9|||$CE$9|||||||||Осн поставщик||||||$AP$9|||$AP$1|||$AQ$9|||$AR$9|||||||||Да||||||$AM$9|||$AM$1|||$AN$9|||$AO$9||||||непонятный аналог, 1 шт|||Уточнить параметры||||||$BB$9|||$BB$1|||$BC$9|||$BD$9|||||||||||| | IS9: $AP$1📎📎📎Осн поставщик📎1791374782957|||$AM$1📎📎непонятный аналог, 1 шт📎Уточнить параметры📎1791376063459|||$CC$1📎📎📎Осн поставщик📎1791881126121 | IT9: $AP$1📎📎📎Да📎1791881185359|||$AM$1📎📎непонятный аналог, 1 шт📎Уточнить параметры📎1791376063459|||$CC$1📎📎📎Осн поставщик📎1791881126121
C10: 9 | D10: Сервисный набор 8000 ч. арт. 2906075700 | E10: GA 200 зав. № APF133999; GA 250 зав. № APF133914; GA 250 зав. № APF 133915 «Atlas Copco» | F10: шт. | G10: 3 | H10: 599 500,00 183 976,00 | I10: 1 798 500,00 551 928,00 | J10: 5, из них аналог 1 | Q10: =IFERROR(__xludf.DUMMYFUNCTION("""COMPUTED_VALUE"""),5.0) -> 5 | Z10: ID_T009 | AM10: 599500 | AN10: 12 нед | AO10: Сервисный набор 8000 1 шт | AP10: 1057940 | AQ10: 12 нед | AR10: 2906075700 8000H MAINT KIT | BB10: 1615440 | BC10: 14 нед | BD10: 2906075700 . | BW10: =11064.9*1.22*B3 -> #REF! | BX10: 17 нед | BY10: Комплект арт. 2906075700 | CC10: =150800*1.22 -> 183976 | CD10: 15 нед | CE10: Сервисный набор Atlas Copco 2906075700 | HT10: =IFERROR(SMALL($R10:$HS10,VALUE(LEFT(HT$1,1))),"") | HU10: =IFERROR(OFFSET($AA$1,0,MATCH(HT10,$AA10:$HS10,0)),"") | HV10: =IFERROR(SMALL($AA10:$HS10,VALUE(LEFT(HV$1,1))),"") | HW10: =IFERROR(OFFSET($A$1,0,MATCH(HV10,$AA10:$HS10,0)),"") | HX10: =IFERROR(SMALL($AA10:$HS10,VALUE(LEFT(HX$1,1))),"") | HY10: =IFERROR(OFFSET($AA$1,0,MATCH(HX10,$AA10:$HS10,0)),"") | ID10: =IFERROR(__xludf.DUMMYFUNCTION(" IFERROR( TEXTJOIN(""|||"",FALSE , ARRAY_CONSTRAIN( SORT( ARRAYFORMULA(Split(TRANSPOSE (Split(TEXTJOIN(""|||"",TRUE,'1-1 Сбор КП'!$IF10:$IL10),""|||"",FALSE,FALSE) ),""|"",FALSE,FALSE)),3,FALSE ),100,2) ) "&",)"),"") | IE10: =IFERROR(__xludf.DUMMYFUNCTION("LAMBDA(cc,тело,комент, комЭкс, порядок,показ, BYROW(тело, LAMBDA(r, TEXTJOIN(""|||"",FALSE,ARRAY_CONSTRAIN( Query( TRANSPOSE( { {ARRAYFORMULA( FILTER( ADDRESS(ROW(r), COLUMN(r) ), MOD(COLUMN(r)-cc,3)=0))}; {ARRAYFORMULA( FILTER( ADDRESS(1, COLUMN(r) ), MO"&"D(COLUMN(r)-cc,3)=0))}; {ARRAYFORMULA( IFERROR(VLOOKUP( FILTER( ADDRESS(1, COLUMN(r) ), MOD(COLUMN(r)-cc,3)=0), { TRANSPOSE (FILTER( {SPLIT(INDEX(комент,1,0),""|||"",FALSE,FALSE)}, ARRAYFORMULA( ISODD({SEQUENCE(1, COLUMNS(SPLIT(INDEX(комент,1,0),""|||"&""",FALSE,FALSE) ), 1, 1)})))) , TRANSPOSE (FILTER( {SPLIT(INDEX(комент,1,0),""|||"",FALSE,FALSE)}, ARRAYFORMULA( ISEVEN({SEQUENCE(1, COLUMNS( SPLIT(INDEX(комент,1,0),""|||"",FALSE,FALSE) ), 1, 1)}))))} ,2,0 ),""""))}; {ARRAYFORMULA( FILTER( ADDRESS(RO"&"W(r), COLUMN(r) ), MOD(COLUMN(r)-cc,3)=1))}; {ARRAYFORMULA( Lambda(f,m,""Подходит: ""& IFERROR( VLOOKUP( f, комЭкс, 4,0 ),""-?"")&"", ""& m&"" ""&IFERROR(VLOOKUP( f, комЭкс, 2,0 ),)&"" ""&IFERROR(VLOOKUP( f, комЭкс, 3,0 ),) ) ( FILTER( ADDRESS(1, COLUM"&"N(r) ), MOD(COLUMN(r)-cc,3)=0), FILTER( r, MOD(COLUMN(r)-cc,3)=2) ) ) }; {ARRAYFORMULA( FILTER( r, MOD(COLUMN(r)-cc,3)=0))}; BYCOL({ARRAYFORMULA( FILTER( ""'1-1 Сбор КП'!""&""R1C""&COLUMN(r) , MOD(COLUMN(r)-cc,3)=0))},LAMBDA(aa, LAMBDA(a,ifs ( IFERR"&"OR(FIND(""(♠)"",a),0)<>0,IFERROR( VLOOKUP(""♠"",порядок,2,FALSE),5), IFERROR(FIND(""(♦️)"",a),0)<>0,IFERROR( VLOOKUP(""♦️"",порядок,2,FALSE),5), IFERROR(FIND(""(♣️)"",a),0)<>0,IFERROR( VLOOKUP(""♣️"",порядок,2,FALSE),5), IFERROR(FIND(""(♥️)"",a),0)<>0,IFE"&"RROR( VLOOKUP(""♥️"",порядок,2,FALSE),5), TRUE,IFERROR( VLOOKUP(""-"",порядок,2,FALSE),5) ))(INDIRECT( aa,FALSE) ) )); BYCOL({ARRAYFORMULA( FILTER( ""'1-1 Сбор КП'!""&""R1C""&COLUMN(r) , MOD(COLUMN(r)-cc,3)=0))},LAMBDA(aa, LAMBDA(a,ifs ( IFERROR(FIND"&"(""(♠)"",a),0)<>0,IFERROR( VLOOKUP(""♠"",показ,2,FALSE),TRUE), IFERROR(FIND(""(♦️)"",a),0)<>0,IFERROR( VLOOKUP(""♦️"",показ,2,FALSE),TRUE), IFERROR(FIND(""(♣️)"",a),0)<>0,IFERROR( VLOOKUP(""♣️"",показ,2,FALSE),TRUE), IFERROR(FIND(""(♥️)"",a),0)<>0,IFERROR"&"( VLOOKUP(""♥️"",показ,2,FALSE),TRUE), TRUE,IFERROR( VLOOKUP(""-"",показ,2,FALSE),TRUE) ))(INDIRECT( aa,FALSE) ) )) }),""Select * Where Col6 is not null and Col8=true Order by Col7, Col6"",0),7,5)) ) ) ) ( COLUMN('1-1 Сбор КП'!$AA10), '1-1 Сбор КП'!$"&"AA10:$HS10, '1-1 Сбор КП'!$ID10, BYROW( TRANSPOSE(Split('1-1 Сбор КП'!$IQ10,""|||"",FALSE)),LAMBDA(rc,Split(rc,""📎"",FALSE,FALSE))), {'3-3 Выбор поставщиков'!$AB$24:$AB$28 , '3-3 Выбор поставщиков'!$AF$24:$AF$28}, {'3-3 Выбор поставщиков'!$AB$24:$AB"&"$28 , '3-3 Выбор поставщиков'!$AD$24:$AD$28} )"),"$CC$10|||$CC$1||||||$CD$10|||Подходит: Осн поставщик, Сервисный набор Atlas Copco 2906075700 |||$AM$10|||$AM$1||||||$AN$10|||Подходит: Уточнить параметры, Сервисный набор 8000 1 шт непонятный аналог, 1 шт|||$AP$10|||$AP$1||||||$AQ$10|||Подходит: Да, 29"&"06075700 8000H MAINT KIT |||$BB$10|||$BB$1||||||$BC$10|||Подходит: -?, 2906075700 . ") -> $CC$10|||$CC$1||||||$CD$10|||Подходит: Осн поставщик, Сервисный набор Atlas Copco 2906075700 |||$AM$10|||$AM$1||||||$AN$10|||Подходит: Уточнить параметры, Сервисный набор 8000 1 шт непонятный аналог, 1 шт|||$AP$10|||$AP$1||||||$AQ$10|||Подходит: Да, 2906075700 8000H MAINT KIT |||$BB$10|||$BB$1||||||$BC$10|||Подходит: -?, 2906075700 . | IQ10: =IFERROR(__xludf.DUMMYFUNCTION(" IFERROR( TEXTJOIN(""|||"",true , BYROW( ARRAY_CONSTRAIN( SORT( ARRAYFORMULA( Split( TRANSPOSE ( Split(TEXTJOIN(""|||"", TRUE, '1-1 Сбор КП'!$IS10:$JF10) ,""|||"",FALSE,FALSE) ),""📎"",FALSE,FAL"&"SE)),5,FALSE ),100,4) ,LAMBDA(r,TEXTJOIN(""📎"",FALSE ,r)) ) ,))"),"$AP$1📎📎📎Да|||$CC$1📎📎📎Осн поставщик|||$CC$1📎📎📎Осн поставщик|||$AP$1📎📎📎Осн поставщик|||$AP$1📎📎📎Осн поставщик|||$AM$1📎📎непонятный аналог, 1 шт📎Уточнить параметры|||$AM$1📎📎непонятный аналог, 1 шт📎Уточнить параметры|||$AM$1📎📎непонятный а"&"налог, 1 шт📎Уточнить параметры") -> $AP$1📎📎📎Да|||$CC$1📎📎📎Осн поставщик|||$CC$1📎📎📎Осн поставщик|||$AP$1📎📎📎Осн поставщик|||$AP$1📎📎📎Осн поставщик|||$AM$1📎📎непонятный аналог, 1 шт📎Уточнить параметры|||$AM$1📎📎непонятный аналог, 1 шт📎Уточнить параметры|||$AM$1📎📎непонятный аналог, 1 шт📎Уточнить параметры | IR10: =IFERROR(__xludf.DUMMYFUNCTION(" LAMBDA(cc,тело,комент,комЭкс,BYROW(тело,LAMBDA(r, TEXTJOIN(""|||"",FALSE, ARRAY_CONSTRAIN( Query( TRANSPOSE( { { ARRAYFORMULA( FILTER( ADDRESS(ROW(r), COLUMN(r) ), MOD(COLUMN(r)-cc,3)=0)) }; { ARRAYFORMULA( FILTER( ADDRESS(1, COLUMN(r) ), MOD(COL"&"UMN(r)-cc,3)=0)) }; { ARRAYFORMULA( FILTER( ADDRESS(ROW(r), COLUMN(r) ), MOD(COLUMN(r)-cc,3)=1)) }; { ARRAYFORMULA( FILTER( ADDRESS(ROW(r), COLUMN(r)+1 ), MOD(COLUMN(r)-cc,3)=1)) }; { ARRAYFORMULA( IFERROR(VLOOKUP( FILTER( ADDRESS(1,"&" COLUMN(r) ), MOD(COLUMN(r)-cc,3)=0),комЭкс,2,0 ),"""")) }; { ARRAYFORMULA( IFERROR(VLOOKUP( FILTER( ADDRESS(1, COLUMN(r) ), MOD(COLUMN(r)-cc,3)=0),комЭкс,3,0 ),"""")) }; { ARRAYFORMULA( IFERROR(VLOOKUP( FILTER( ADDRESS(1, COLUMN(r) ), MOD(COLUMN("&"r)-cc,3)=0),комЭкс,4,0 ),"""")) }; { ARRAYFORMULA( IFERROR(VLOOKUP( FILTER( ADDRESS(1, COLUMN(r) ), MOD(COLUMN(r)-cc,3)=0), { TRANSPOSE (FILTER( {SPLIT(INDEX(комент,1,0),""|||"",FALSE,FALSE)}, ARRAYFORMULA( ISODD({SEQUENCE(1, COLUMNS(SPLIT(INDEX(ком"&"ент,1,0),""|||"",FALSE,FALSE) ), 1, 1)})))) , TRANSPOSE (FILTER( {SPLIT(INDEX(комент,1,0),""|||"",FALSE,FALSE)}, ARRAYFORMULA( ISEVEN({SEQUENCE(1, COLUMNS( SPLIT(INDEX(комент,1,0),""|||"",FALSE,FALSE) ), 1, 1)}))))} ,2,0 ),"""")) }; { ARRAYFORMULA( FIL"&"TER( r, MOD(COLUMN(r)-cc,3)=0)) } } ),""Select * Where Col9 is not null Order by Col9"",0),14,8))) )) ( COLUMN('1-1 Сбор КП'!$AA10), '1-1 Сбор КП'!$AA10:$HS10, '1-1 Сбор КП'!$ID10, BYROW( TRANSPOSE(Split('1-1 Сбор КП'!$IQ10,""|||"",FALSE)),LAMBDA("&"rc,Split(rc,""📎"",FALSE,FALSE))) ) "),"$CC$10|||$CC$1|||$CD$10|||$CE$10|||||||||Осн поставщик||||||$AM$10|||$AM$1|||$AN$10|||$AO$10||||||непонятный аналог, 1 шт|||Уточнить параметры||||||$AP$10|||$AP$1|||$AQ$10|||$AR$10|||||||||Да||||||$BB$10|||$BB$1|||$BC$10|||$BD$10||||||||||||") -> $CC$10|||$CC$1|||$CD$10|||$CE$10|||||||||Осн поставщик||||||$AM$10|||$AM$1|||$AN$10|||$AO$10||||||непонятный аналог, 1 шт|||Уточнить параметры||||||$AP$10|||$AP$1|||$AQ$10|||$AR$10|||||||||Да||||||$BB$10|||$BB$1|||$BC$10|||$BD$10|||||||||||| | IS10: $AM$1📎📎непонятный аналог, 1 шт📎Уточнить параметры📎1791374849447|||$AP$1📎📎📎Осн поставщик📎1791376195153|||$CC$1📎📎📎Осн поставщик📎1791881132286 | IT10: $AM$1📎📎непонятный аналог, 1 шт📎Уточнить параметры📎1791374849447|||$AP$1📎📎📎Осн поставщик📎1791376195153 | IU10: $AM$1📎📎непонятный аналог, 1 шт📎Уточнить параметры📎1791374849447|||$AP$1📎📎📎Да📎1791881197216|||$CC$1📎📎📎Осн поставщик📎1791881132286
C11: 10 | D11: Масляный сепаратор | E11: «Dalgakiran» Inversys +315 зав. №VD 4037, зав. № VD 6420. | F11: шт. | G11: 3 | H11: 0,00 59 800,00 | I11: 0,00 179 400,00 | J11: Мало, всего 1 | Q11: =IFERROR(__xludf.DUMMYFUNCTION("""COMPUTED_VALUE"""),1.0) -> 1 | Z11: ID_T010 | AJ11: 59800 | AK11: 5 рд | AL11: Масляный сепаратор | HT11: =IFERROR(SMALL($R11:$HS11,VALUE(LEFT(HT$1,1))),"") -> 59800 | HU11: =IFERROR(OFFSET($AA$1,0,MATCH(HT11,$AA11:$HS11,0)),"") | HV11: =IFERROR(SMALL($AA11:$HS11,VALUE(LEFT(HV$1,1))),"") | HW11: =IFERROR(OFFSET($A$1,0,MATCH(HV11,$AA11:$HS11,0)),"") | HX11: =IFERROR(SMALL($AA11:$HS11,VALUE(LEFT(HX$1,1))),"") | HY11: =IFERROR(OFFSET($AA$1,0,MATCH(HX11,$AA11:$HS11,0)),"") | ID11: =IFERROR(__xludf.DUMMYFUNCTION(" IFERROR( TEXTJOIN(""|||"",FALSE , ARRAY_CONSTRAIN( SORT( ARRAYFORMULA(Split(TRANSPOSE (Split(TEXTJOIN(""|||"",TRUE,'1-1 Сбор КП'!$IF11:$IL11),""|||"",FALSE,FALSE) ),""|"",FALSE,FALSE)),3,FALSE ),100,2) ) "&",)"),"") | IE11: =IFERROR(__xludf.DUMMYFUNCTION("LAMBDA(cc,тело,комент, комЭкс, порядок,показ, BYROW(тело, LAMBDA(r, TEXTJOIN(""|||"",FALSE,ARRAY_CONSTRAIN( Query( TRANSPOSE( { {ARRAYFORMULA( FILTER( ADDRESS(ROW(r), COLUMN(r) ), MOD(COLUMN(r)-cc,3)=0))}; {ARRAYFORMULA( FILTER( ADDRESS(1, COLUMN(r) ), MO"&"D(COLUMN(r)-cc,3)=0))}; {ARRAYFORMULA( IFERROR(VLOOKUP( FILTER( ADDRESS(1, COLUMN(r) ), MOD(COLUMN(r)-cc,3)=0), { TRANSPOSE (FILTER( {SPLIT(INDEX(комент,1,0),""|||"",FALSE,FALSE)}, ARRAYFORMULA( ISODD({SEQUENCE(1, COLUMNS(SPLIT(INDEX(комент,1,0),""|||"&""",FALSE,FALSE) ), 1, 1)})))) , TRANSPOSE (FILTER( {SPLIT(INDEX(комент,1,0),""|||"",FALSE,FALSE)}, ARRAYFORMULA( ISEVEN({SEQUENCE(1, COLUMNS( SPLIT(INDEX(комент,1,0),""|||"",FALSE,FALSE) ), 1, 1)}))))} ,2,0 ),""""))}; {ARRAYFORMULA( FILTER( ADDRESS(RO"&"W(r), COLUMN(r) ), MOD(COLUMN(r)-cc,3)=1))}; {ARRAYFORMULA( Lambda(f,m,""Подходит: ""& IFERROR( VLOOKUP( f, комЭкс, 4,0 ),""-?"")&"", ""& m&"" ""&IFERROR(VLOOKUP( f, комЭкс, 2,0 ),)&"" ""&IFERROR(VLOOKUP( f, комЭкс, 3,0 ),) ) ( FILTER( ADDRESS(1, COLUM"&"N(r) ), MOD(COLUMN(r)-cc,3)=0), FILTER( r, MOD(COLUMN(r)-cc,3)=2) ) ) }; {ARRAYFORMULA( FILTER( r, MOD(COLUMN(r)-cc,3)=0))}; BYCOL({ARRAYFORMULA( FILTER( ""'1-1 Сбор КП'!""&""R1C""&COLUMN(r) , MOD(COLUMN(r)-cc,3)=0))},LAMBDA(aa, LAMBDA(a,ifs ( IFERR"&"OR(FIND(""(♠)"",a),0)<>0,IFERROR( VLOOKUP(""♠"",порядок,2,FALSE),5), IFERROR(FIND(""(♦️)"",a),0)<>0,IFERROR( VLOOKUP(""♦️"",порядок,2,FALSE),5), IFERROR(FIND(""(♣️)"",a),0)<>0,IFERROR( VLOOKUP(""♣️"",порядок,2,FALSE),5), IFERROR(FIND(""(♥️)"",a),0)<>0,IFE"&"RROR( VLOOKUP(""♥️"",порядок,2,FALSE),5), TRUE,IFERROR( VLOOKUP(""-"",порядок,2,FALSE),5) ))(INDIRECT( aa,FALSE) ) )); BYCOL({ARRAYFORMULA( FILTER( ""'1-1 Сбор КП'!""&""R1C""&COLUMN(r) , MOD(COLUMN(r)-cc,3)=0))},LAMBDA(aa, LAMBDA(a,ifs ( IFERROR(FIND"&"(""(♠)"",a),0)<>0,IFERROR( VLOOKUP(""♠"",показ,2,FALSE),TRUE), IFERROR(FIND(""(♦️)"",a),0)<>0,IFERROR( VLOOKUP(""♦️"",показ,2,FALSE),TRUE), IFERROR(FIND(""(♣️)"",a),0)<>0,IFERROR( VLOOKUP(""♣️"",показ,2,FALSE),TRUE), IFERROR(FIND(""(♥️)"",a),0)<>0,IFERROR"&"( VLOOKUP(""♥️"",показ,2,FALSE),TRUE), TRUE,IFERROR( VLOOKUP(""-"",показ,2,FALSE),TRUE) ))(INDIRECT( aa,FALSE) ) )) }),""Select * Where Col6 is not null and Col8=true Order by Col7, Col6"",0),7,5)) ) ) ) ( COLUMN('1-1 Сбор КП'!$AA11), '1-1 Сбор КП'!$"&"AA11:$HS11, '1-1 Сбор КП'!$ID11, BYROW( TRANSPOSE(Split('1-1 Сбор КП'!$IQ11,""|||"",FALSE)),LAMBDA(rc,Split(rc,""📎"",FALSE,FALSE))), {'3-3 Выбор поставщиков'!$AB$24:$AB$28 , '3-3 Выбор поставщиков'!$AF$24:$AF$28}, {'3-3 Выбор поставщиков'!$AB$24:$AB"&"$28 , '3-3 Выбор поставщиков'!$AD$24:$AD$28} )"),"$AJ$11|||$AJ$1||||||$AK$11|||Подходит: Осн поставщик, Масляный сепаратор ") -> $AJ$11|||$AJ$1||||||$AK$11|||Подходит: Осн поставщик, Масляный сепаратор | IQ11: =IFERROR(__xludf.DUMMYFUNCTION(" IFERROR( TEXTJOIN(""|||"",true , BYROW( ARRAY_CONSTRAIN( SORT( ARRAYFORMULA( Split( TRANSPOSE ( Split(TEXTJOIN(""|||"", TRUE, '1-1 Сбор КП'!$IS11:$JF11) ,""|||"",FALSE,FALSE) ),""📎"",FALSE,FAL"&"SE)),5,FALSE ),100,4) ,LAMBDA(r,TEXTJOIN(""📎"",FALSE ,r)) ) ,))"),"$AJ$1📎📎📎Осн поставщик") -> $AJ$1📎📎📎Осн поставщик | IR11: =IFERROR(__xludf.DUMMYFUNCTION(" LAMBDA(cc,тело,комент,комЭкс,BYROW(тело,LAMBDA(r, TEXTJOIN(""|||"",FALSE, ARRAY_CONSTRAIN( Query( TRANSPOSE( { { ARRAYFORMULA( FILTER( ADDRESS(ROW(r), COLUMN(r) ), MOD(COLUMN(r)-cc,3)=0)) }; { ARRAYFORMULA( FILTER( ADDRESS(1, COLUMN(r) ), MOD(COL"&"UMN(r)-cc,3)=0)) }; { ARRAYFORMULA( FILTER( ADDRESS(ROW(r), COLUMN(r) ), MOD(COLUMN(r)-cc,3)=1)) }; { ARRAYFORMULA( FILTER( ADDRESS(ROW(r), COLUMN(r)+1 ), MOD(COLUMN(r)-cc,3)=1)) }; { ARRAYFORMULA( IFERROR(VLOOKUP( FILTER( ADDRESS(1,"&" COLUMN(r) ), MOD(COLUMN(r)-cc,3)=0),комЭкс,2,0 ),"""")) }; { ARRAYFORMULA( IFERROR(VLOOKUP( FILTER( ADDRESS(1, COLUMN(r) ), MOD(COLUMN(r)-cc,3)=0),комЭкс,3,0 ),"""")) }; { ARRAYFORMULA( IFERROR(VLOOKUP( FILTER( ADDRESS(1, COLUMN(r) ), MOD(COLUMN("&"r)-cc,3)=0),комЭкс,4,0 ),"""")) }; { ARRAYFORMULA( IFERROR(VLOOKUP( FILTER( ADDRESS(1, COLUMN(r) ), MOD(COLUMN(r)-cc,3)=0), { TRANSPOSE (FILTER( {SPLIT(INDEX(комент,1,0),""|||"",FALSE,FALSE)}, ARRAYFORMULA( ISODD({SEQUENCE(1, COLUMNS(SPLIT(INDEX(ком"&"ент,1,0),""|||"",FALSE,FALSE) ), 1, 1)})))) , TRANSPOSE (FILTER( {SPLIT(INDEX(комент,1,0),""|||"",FALSE,FALSE)}, ARRAYFORMULA( ISEVEN({SEQUENCE(1, COLUMNS( SPLIT(INDEX(комент,1,0),""|||"",FALSE,FALSE) ), 1, 1)}))))} ,2,0 ),"""")) }; { ARRAYFORMULA( FIL"&"TER( r, MOD(COLUMN(r)-cc,3)=0)) } } ),""Select * Where Col9 is not null Order by Col9"",0),14,8))) )) ( COLUMN('1-1 Сбор КП'!$AA11), '1-1 Сбор КП'!$AA11:$HS11, '1-1 Сбор КП'!$ID11, BYROW( TRANSPOSE(Split('1-1 Сбор КП'!$IQ11,""|||"",FALSE)),LAMBDA("&"rc,Split(rc,""📎"",FALSE,FALSE))) ) "),"$AJ$11|||$AJ$1|||$AK$11|||$AL$11|||||||||Осн поставщик|||") -> $AJ$11|||$AJ$1|||$AK$11|||$AL$11|||||||||Осн поставщик||| | IS11: $AJ$1📎📎📎Осн поставщик📎1791375415354
C12: 11 | D12: Воздушный фильтр | E12: «Dalgakiran» Inversys +315 зав. №VD 4037, зав. № VD 6420. | F12: шт. | G12: 6 | H12: 0,00 5 100,00 | I12: 0,00 30 600,00 | J12: Мало, всего 1 | Q12: =IFERROR(__xludf.DUMMYFUNCTION("""COMPUTED_VALUE"""),1.0) -> 1 | Z12: ID_T011 | AJ12: 5100 | AK12: 5 рд | AL12: Воздушный фильтр | HT12: =IFERROR(SMALL($R12:$HS12,VALUE(LEFT(HT$1,1))),"") -> 5100 | HU12: =IFERROR(OFFSET($AA$1,0,MATCH(HT12,$AA12:$HS12,0)),"") | HV12: =IFERROR(SMALL($AA12:$HS12,VALUE(LEFT(HV$1,1))),"") | HW12: =IFERROR(OFFSET($A$1,0,MATCH(HV12,$AA12:$HS12,0)),"") | HX12: =IFERROR(SMALL($AA12:$HS12,VALUE(LEFT(HX$1,1))),"") | HY12: =IFERROR(OFFSET($AA$1,0,MATCH(HX12,$AA12:$HS12,0)),"") | ID12: =IFERROR(__xludf.DUMMYFUNCTION(" IFERROR( TEXTJOIN(""|||"",FALSE , ARRAY_CONSTRAIN( SORT( ARRAYFORMULA(Split(TRANSPOSE (Split(TEXTJOIN(""|||"",TRUE,'1-1 Сбор КП'!$IF12:$IL12),""|||"",FALSE,FALSE) ),""|"",FALSE,FALSE)),3,FALSE ),100,2) ) "&",)"),"") | IE12: =IFERROR(__xludf.DUMMYFUNCTION("LAMBDA(cc,тело,комент, комЭкс, порядок,показ, BYROW(тело, LAMBDA(r, TEXTJOIN(""|||"",FALSE,ARRAY_CONSTRAIN( Query( TRANSPOSE( { {ARRAYFORMULA( FILTER( ADDRESS(ROW(r), COLUMN(r) ), MOD(COLUMN(r)-cc,3)=0))}; {ARRAYFORMULA( FILTER( ADDRESS(1, COLUMN(r) ), MO"&"D(COLUMN(r)-cc,3)=0))}; {ARRAYFORMULA( IFERROR(VLOOKUP( FILTER( ADDRESS(1, COLUMN(r) ), MOD(COLUMN(r)-cc,3)=0), { TRANSPOSE (FILTER( {SPLIT(INDEX(комент,1,0),""|||"",FALSE,FALSE)}, ARRAYFORMULA( ISODD({SEQUENCE(1, COLUMNS(SPLIT(INDEX(комент,1,0),""|||"&""",FALSE,FALSE) ), 1, 1)})))) , TRANSPOSE (FILTER( {SPLIT(INDEX(комент,1,0),""|||"",FALSE,FALSE)}, ARRAYFORMULA( ISEVEN({SEQUENCE(1, COLUMNS( SPLIT(INDEX(комент,1,0),""|||"",FALSE,FALSE) ), 1, 1)}))))} ,2,0 ),""""))}; {ARRAYFORMULA( FILTER( ADDRESS(RO"&"W(r), COLUMN(r) ), MOD(COLUMN(r)-cc,3)=1))}; {ARRAYFORMULA( Lambda(f,m,""Подходит: ""& IFERROR( VLOOKUP( f, комЭкс, 4,0 ),""-?"")&"", ""& m&"" ""&IFERROR(VLOOKUP( f, комЭкс, 2,0 ),)&"" ""&IFERROR(VLOOKUP( f, комЭкс, 3,0 ),) ) ( FILTER( ADDRESS(1, COLUM"&"N(r) ), MOD(COLUMN(r)-cc,3)=0), FILTER( r, MOD(COLUMN(r)-cc,3)=2) ) ) }; {ARRAYFORMULA( FILTER( r, MOD(COLUMN(r)-cc,3)=0))}; BYCOL({ARRAYFORMULA( FILTER( ""'1-1 Сбор КП'!""&""R1C""&COLUMN(r) , MOD(COLUMN(r)-cc,3)=0))},LAMBDA(aa, LAMBDA(a,ifs ( IFERR"&"OR(FIND(""(♠)"",a),0)<>0,IFERROR( VLOOKUP(""♠"",порядок,2,FALSE),5), IFERROR(FIND(""(♦️)"",a),0)<>0,IFERROR( VLOOKUP(""♦️"",порядок,2,FALSE),5), IFERROR(FIND(""(♣️)"",a),0)<>0,IFERROR( VLOOKUP(""♣️"",порядок,2,FALSE),5), IFERROR(FIND(""(♥️)"",a),0)<>0,IFE"&"RROR( VLOOKUP(""♥️"",порядок,2,FALSE),5), TRUE,IFERROR( VLOOKUP(""-"",порядок,2,FALSE),5) ))(INDIRECT( aa,FALSE) ) )); BYCOL({ARRAYFORMULA( FILTER( ""'1-1 Сбор КП'!""&""R1C""&COLUMN(r) , MOD(COLUMN(r)-cc,3)=0))},LAMBDA(aa, LAMBDA(a,ifs ( IFERROR(FIND"&"(""(♠)"",a),0)<>0,IFERROR( VLOOKUP(""♠"",показ,2,FALSE),TRUE), IFERROR(FIND(""(♦️)"",a),0)<>0,IFERROR( VLOOKUP(""♦️"",показ,2,FALSE),TRUE), IFERROR(FIND(""(♣️)"",a),0)<>0,IFERROR( VLOOKUP(""♣️"",показ,2,FALSE),TRUE), IFERROR(FIND(""(♥️)"",a),0)<>0,IFERROR"&"( VLOOKUP(""♥️"",показ,2,FALSE),TRUE), TRUE,IFERROR( VLOOKUP(""-"",показ,2,FALSE),TRUE) ))(INDIRECT( aa,FALSE) ) )) }),""Select * Where Col6 is not null and Col8=true Order by Col7, Col6"",0),7,5)) ) ) ) ( COLUMN('1-1 Сбор КП'!$AA12), '1-1 Сбор КП'!$"&"AA12:$HS12, '1-1 Сбор КП'!$ID12, BYROW( TRANSPOSE(Split('1-1 Сбор КП'!$IQ12,""|||"",FALSE)),LAMBDA(rc,Split(rc,""📎"",FALSE,FALSE))), {'3-3 Выбор поставщиков'!$AB$24:$AB$28 , '3-3 Выбор поставщиков'!$AF$24:$AF$28}, {'3-3 Выбор поставщиков'!$AB$24:$AB"&"$28 , '3-3 Выбор поставщиков'!$AD$24:$AD$28} )"),"$AJ$12|||$AJ$1||||||$AK$12|||Подходит: Осн поставщик, Воздушный фильтр ") -> $AJ$12|||$AJ$1||||||$AK$12|||Подходит: Осн поставщик, Воздушный фильтр | IQ12: =IFERROR(__xludf.DUMMYFUNCTION(" IFERROR( TEXTJOIN(""|||"",true , BYROW( ARRAY_CONSTRAIN( SORT( ARRAYFORMULA( Split( TRANSPOSE ( Split(TEXTJOIN(""|||"", TRUE, '1-1 Сбор КП'!$IS12:$JF12) ,""|||"",FALSE,FALSE) ),""📎"",FALSE,FAL"&"SE)),5,FALSE ),100,4) ,LAMBDA(r,TEXTJOIN(""📎"",FALSE ,r)) ) ,))"),"$AJ$1📎📎📎Осн поставщик") -> $AJ$1📎📎📎Осн поставщик | IR12: =IFERROR(__xludf.DUMMYFUNCTION(" LAMBDA(cc,тело,комент,комЭкс,BYROW(тело,LAMBDA(r, TEXTJOIN(""|||"",FALSE, ARRAY_CONSTRAIN( Query( TRANSPOSE( { { ARRAYFORMULA( FILTER( ADDRESS(ROW(r), COLUMN(r) ), MOD(COLUMN(r)-cc,3)=0)) }; { ARRAYFORMULA( FILTER( ADDRESS(1, COLUMN(r) ), MOD(COL"&"UMN(r)-cc,3)=0)) }; { ARRAYFORMULA( FILTER( ADDRESS(ROW(r), COLUMN(r) ), MOD(COLUMN(r)-cc,3)=1)) }; { ARRAYFORMULA( FILTER( ADDRESS(ROW(r), COLUMN(r)+1 ), MOD(COLUMN(r)-cc,3)=1)) }; { ARRAYFORMULA( IFERROR(VLOOKUP( FILTER( ADDRESS(1,"&" COLUMN(r) ), MOD(COLUMN(r)-cc,3)=0),комЭкс,2,0 ),"""")) }; { ARRAYFORMULA( IFERROR(VLOOKUP( FILTER( ADDRESS(1, COLUMN(r) ), MOD(COLUMN(r)-cc,3)=0),комЭкс,3,0 ),"""")) }; { ARRAYFORMULA( IFERROR(VLOOKUP( FILTER( ADDRESS(1, COLUMN(r) ), MOD(COLUMN("&"r)-cc,3)=0),комЭкс,4,0 ),"""")) }; { ARRAYFORMULA( IFERROR(VLOOKUP( FILTER( ADDRESS(1, COLUMN(r) ), MOD(COLUMN(r)-cc,3)=0), { TRANSPOSE (FILTER( {SPLIT(INDEX(комент,1,0),""|||"",FALSE,FALSE)}, ARRAYFORMULA( ISODD({SEQUENCE(1, COLUMNS(SPLIT(INDEX(ком"&"ент,1,0),""|||"",FALSE,FALSE) ), 1, 1)})))) , TRANSPOSE (FILTER( {SPLIT(INDEX(комент,1,0),""|||"",FALSE,FALSE)}, ARRAYFORMULA( ISEVEN({SEQUENCE(1, COLUMNS( SPLIT(INDEX(комент,1,0),""|||"",FALSE,FALSE) ), 1, 1)}))))} ,2,0 ),"""")) }; { ARRAYFORMULA( FIL"&"TER( r, MOD(COLUMN(r)-cc,3)=0)) } } ),""Select * Where Col9 is not null Order by Col9"",0),14,8))) )) ( COLUMN('1-1 Сбор КП'!$AA12), '1-1 Сбор КП'!$AA12:$HS12, '1-1 Сбор КП'!$ID12, BYROW( TRANSPOSE(Split('1-1 Сбор КП'!$IQ12,""|||"",FALSE)),LAMBDA("&"rc,Split(rc,""📎"",FALSE,FALSE))) ) "),"$AJ$12|||$AJ$1|||$AK$12|||$AL$12|||||||||Осн поставщик|||") -> $AJ$12|||$AJ$1|||$AK$12|||$AL$12|||||||||Осн поставщик||| | IS12: $AJ$1📎📎📎Осн поставщик📎1791375481037
C13: 12 | D13: Масляный фильтр | E13: «Dalgakiran» Inversys +315 зав. №VD 4037, зав. № VD 6420. | F13: шт. | G13: 6 | H13: 0,00 3 900,00 | I13: 0,00 23 400,00 | J13: Мало, всего 2 | Q13: =IFERROR(__xludf.DUMMYFUNCTION("""COMPUTED_VALUE"""),2.0) -> 2 | Z13: ID_T012 | AD13: =6536.89*1.22 -> 7975.0058 | AF13: Масляный фильтр для компрессора Dalgakiran Inversys 315+ | AJ13: 3900 | AK13: 5 рд | AL13: Масляный фильтр | HT13: =IFERROR(SMALL($R13:$HS13,VALUE(LEFT(HT$1,1))),"") -> 3900 | HU13: =IFERROR(OFFSET($AA$1,0,MATCH(HT13,$AA13:$HS13,0)),"") | HV13: =IFERROR(SMALL($AA13:$HS13,VALUE(LEFT(HV$1,1))),"") -> 7975.0058 | HW13: =IFERROR(OFFSET($A$1,0,MATCH(HV13,$AA13:$HS13,0)),"") -> Характеристики | HX13: =IFERROR(SMALL($AA13:$HS13,VALUE(LEFT(HX$1,1))),"") | HY13: =IFERROR(OFFSET($AA$1,0,MATCH(HX13,$AA13:$HS13,0)),"") | ID13: =IFERROR(__xludf.DUMMYFUNCTION(" IFERROR( TEXTJOIN(""|||"",FALSE , ARRAY_CONSTRAIN( SORT( ARRAYFORMULA(Split(TRANSPOSE (Split(TEXTJOIN(""|||"",TRUE,'1-1 Сбор КП'!$IF13:$IL13),""|||"",FALSE,FALSE) ),""|"",FALSE,FALSE)),3,FALSE ),100,2) ) "&",)"),"") | IE13: =IFERROR(__xludf.DUMMYFUNCTION("LAMBDA(cc,тело,комент, комЭкс, порядок,показ, BYROW(тело, LAMBDA(r, TEXTJOIN(""|||"",FALSE,ARRAY_CONSTRAIN( Query( TRANSPOSE( { {ARRAYFORMULA( FILTER( ADDRESS(ROW(r), COLUMN(r) ), MOD(COLUMN(r)-cc,3)=0))}; {ARRAYFORMULA( FILTER( ADDRESS(1, COLUMN(r) ), MO"&"D(COLUMN(r)-cc,3)=0))}; {ARRAYFORMULA( IFERROR(VLOOKUP( FILTER( ADDRESS(1, COLUMN(r) ), MOD(COLUMN(r)-cc,3)=0), { TRANSPOSE (FILTER( {SPLIT(INDEX(комент,1,0),""|||"",FALSE,FALSE)}, ARRAYFORMULA( ISODD({SEQUENCE(1, COLUMNS(SPLIT(INDEX(комент,1,0),""|||"&""",FALSE,FALSE) ), 1, 1)})))) , TRANSPOSE (FILTER( {SPLIT(INDEX(комент,1,0),""|||"",FALSE,FALSE)}, ARRAYFORMULA( ISEVEN({SEQUENCE(1, COLUMNS( SPLIT(INDEX(комент,1,0),""|||"",FALSE,FALSE) ), 1, 1)}))))} ,2,0 ),""""))}; {ARRAYFORMULA( FILTER( ADDRESS(RO"&"W(r), COLUMN(r) ), MOD(COLUMN(r)-cc,3)=1))}; {ARRAYFORMULA( Lambda(f,m,""Подходит: ""& IFERROR( VLOOKUP( f, комЭкс, 4,0 ),""-?"")&"", ""& m&"" ""&IFERROR(VLOOKUP( f, комЭкс, 2,0 ),)&"" ""&IFERROR(VLOOKUP( f, комЭкс, 3,0 ),) ) ( FILTER( ADDRESS(1, COLUM"&"N(r) ), MOD(COLUMN(r)-cc,3)=0), FILTER( r, MOD(COLUMN(r)-cc,3)=2) ) ) }; {ARRAYFORMULA( FILTER( r, MOD(COLUMN(r)-cc,3)=0))}; BYCOL({ARRAYFORMULA( FILTER( ""'1-1 Сбор КП'!""&""R1C""&COLUMN(r) , MOD(COLUMN(r)-cc,3)=0))},LAMBDA(aa, LAMBDA(a,ifs ( IFERR"&"OR(FIND(""(♠)"",a),0)<>0,IFERROR( VLOOKUP(""♠"",порядок,2,FALSE),5), IFERROR(FIND(""(♦️)"",a),0)<>0,IFERROR( VLOOKUP(""♦️"",порядок,2,FALSE),5), IFERROR(FIND(""(♣️)"",a),0)<>0,IFERROR( VLOOKUP(""♣️"",порядок,2,FALSE),5), IFERROR(FIND(""(♥️)"",a),0)<>0,IFE"&"RROR( VLOOKUP(""♥️"",порядок,2,FALSE),5), TRUE,IFERROR( VLOOKUP(""-"",порядок,2,FALSE),5) ))(INDIRECT( aa,FALSE) ) )); BYCOL({ARRAYFORMULA( FILTER( ""'1-1 Сбор КП'!""&""R1C""&COLUMN(r) , MOD(COLUMN(r)-cc,3)=0))},LAMBDA(aa, LAMBDA(a,ifs ( IFERROR(FIND"&"(""(♠)"",a),0)<>0,IFERROR( VLOOKUP(""♠"",показ,2,FALSE),TRUE), IFERROR(FIND(""(♦️)"",a),0)<>0,IFERROR( VLOOKUP(""♦️"",показ,2,FALSE),TRUE), IFERROR(FIND(""(♣️)"",a),0)<>0,IFERROR( VLOOKUP(""♣️"",показ,2,FALSE),TRUE), IFERROR(FIND(""(♥️)"",a),0)<>0,IFERROR"&"( VLOOKUP(""♥️"",показ,2,FALSE),TRUE), TRUE,IFERROR( VLOOKUP(""-"",показ,2,FALSE),TRUE) ))(INDIRECT( aa,FALSE) ) )) }),""Select * Where Col6 is not null and Col8=true Order by Col7, Col6"",0),7,5)) ) ) ) ( COLUMN('1-1 Сбор КП'!$AA13), '1-1 Сбор КП'!$"&"AA13:$HS13, '1-1 Сбор КП'!$ID13, BYROW( TRANSPOSE(Split('1-1 Сбор КП'!$IQ13,""|||"",FALSE)),LAMBDA(rc,Split(rc,""📎"",FALSE,FALSE))), {'3-3 Выбор поставщиков'!$AB$24:$AB$28 , '3-3 Выбор поставщиков'!$AF$24:$AF$28}, {'3-3 Выбор поставщиков'!$AB$24:$AB"&"$28 , '3-3 Выбор поставщиков'!$AD$24:$AD$28} )"),"$AJ$13|||$AJ$1||||||$AK$13|||Подходит: Осн поставщик, Масляный фильтр |||$AD$13|||$AD$1||||||$AE$13|||Подходит: Да, Масляный фильтр для компрессора Dalgakiran Inversys 315+ ") -> $AJ$13|||$AJ$1||||||$AK$13|||Подходит: Осн поставщик, Масляный фильтр |||$AD$13|||$AD$1||||||$AE$13|||Подходит: Да, Масляный фильтр для компрессора Dalgakiran Inversys 315+ | IQ13: =IFERROR(__xludf.DUMMYFUNCTION(" IFERROR( TEXTJOIN(""|||"",true , BYROW( ARRAY_CONSTRAIN( SORT( ARRAYFORMULA( Split( TRANSPOSE ( Split(TEXTJOIN(""|||"", TRUE, '1-1 Сбор КП'!$IS13:$JF13) ,""|||"",FALSE,FALSE) ),""📎"",FALSE,FAL"&"SE)),5,FALSE ),100,4) ,LAMBDA(r,TEXTJOIN(""📎"",FALSE ,r)) ) ,))"),"$AD$1📎📎📎Да|||$AJ$1📎📎📎Осн поставщик|||$AJ$1📎📎📎Осн поставщик") -> $AD$1📎📎📎Да|||$AJ$1📎📎📎Осн поставщик|||$AJ$1📎📎📎Осн поставщик | IR13: =IFERROR(__xludf.DUMMYFUNCTION(" LAMBDA(cc,тело,комент,комЭкс,BYROW(тело,LAMBDA(r, TEXTJOIN(""|||"",FALSE, ARRAY_CONSTRAIN( Query( TRANSPOSE( { { ARRAYFORMULA( FILTER( ADDRESS(ROW(r), COLUMN(r) ), MOD(COLUMN(r)-cc,3)=0)) }; { ARRAYFORMULA( FILTER( ADDRESS(1, COLUMN(r) ), MOD(COL"&"UMN(r)-cc,3)=0)) }; { ARRAYFORMULA( FILTER( ADDRESS(ROW(r), COLUMN(r) ), MOD(COLUMN(r)-cc,3)=1)) }; { ARRAYFORMULA( FILTER( ADDRESS(ROW(r), COLUMN(r)+1 ), MOD(COLUMN(r)-cc,3)=1)) }; { ARRAYFORMULA( IFERROR(VLOOKUP( FILTER( ADDRESS(1,"&" COLUMN(r) ), MOD(COLUMN(r)-cc,3)=0),комЭкс,2,0 ),"""")) }; { ARRAYFORMULA( IFERROR(VLOOKUP( FILTER( ADDRESS(1, COLUMN(r) ), MOD(COLUMN(r)-cc,3)=0),комЭкс,3,0 ),"""")) }; { ARRAYFORMULA( IFERROR(VLOOKUP( FILTER( ADDRESS(1, COLUMN(r) ), MOD(COLUMN("&"r)-cc,3)=0),комЭкс,4,0 ),"""")) }; { ARRAYFORMULA( IFERROR(VLOOKUP( FILTER( ADDRESS(1, COLUMN(r) ), MOD(COLUMN(r)-cc,3)=0), { TRANSPOSE (FILTER( {SPLIT(INDEX(комент,1,0),""|||"",FALSE,FALSE)}, ARRAYFORMULA( ISODD({SEQUENCE(1, COLUMNS(SPLIT(INDEX(ком"&"ент,1,0),""|||"",FALSE,FALSE) ), 1, 1)})))) , TRANSPOSE (FILTER( {SPLIT(INDEX(комент,1,0),""|||"",FALSE,FALSE)}, ARRAYFORMULA( ISEVEN({SEQUENCE(1, COLUMNS( SPLIT(INDEX(комент,1,0),""|||"",FALSE,FALSE) ), 1, 1)}))))} ,2,0 ),"""")) }; { ARRAYFORMULA( FIL"&"TER( r, MOD(COLUMN(r)-cc,3)=0)) } } ),""Select * Where Col9 is not null Order by Col9"",0),14,8))) )) ( COLUMN('1-1 Сбор КП'!$AA13), '1-1 Сбор КП'!$AA13:$HS13, '1-1 Сбор КП'!$ID13, BYROW( TRANSPOSE(Split('1-1 Сбор КП'!$IQ13,""|||"",FALSE)),LAMBDA("&"rc,Split(rc,""📎"",FALSE,FALSE))) ) "),"$AJ$13|||$AJ$1|||$AK$13|||$AL$13|||||||||Осн поставщик||||||$AD$13|||$AD$1|||$AE$13|||$AF$13|||||||||Да|||") -> $AJ$13|||$AJ$1|||$AK$13|||$AL$13|||||||||Осн поставщик||||||$AD$13|||$AD$1|||$AE$13|||$AF$13|||||||||Да||| | IS13: $AJ$1📎📎📎Осн поставщик📎1791375284941 | IT13: $AJ$1📎📎📎Осн поставщик📎1791375284941|||$AD$1📎📎📎Да📎1791376222837
C14: 13 | D14: Масляный сепаратор DS 3084 | E14: BB-50/8 ВУЗ АО «НПАО «ВНИИ компрессормаш» | F14: шт. | G14: 2 | H14: 36 900,00 30 825,00 | I14: 73 800,00 61 650,00 | J14: 6, из них аналог 1 | Q14: =IFERROR(__xludf.DUMMYFUNCTION("""COMPUTED_VALUE"""),6.0) -> 6 | Z14: ID_T013 | AA14: 55000 | AB14: 10 д | AC14: Масляный сепаратор DS 3084 = NS 008430 | AG14: 30825 | AH14: нал | AI14: Масляный сепаратор DS 3084 | AS14: 47250 | AT14: 15 рд | AU14: Масляный сепаратор DS 3084 | AV14: 50500 | AW14: 7 д | AX14: DS 3084 | BE14: 36900 | BF14: 5 рд | BG14: Cепаратор DS 3084 [ Аналог DC/S3084 ] | BN14: 58476 | BO14: 10 д | BP14: Фильтр сепаратор SOTRAS DC 3084 | HT14: =IFERROR(SMALL($R14:$HS14,VALUE(LEFT(HT$1,1))),"") -> 30825 | HU14: =IFERROR(OFFSET($AA$1,0,MATCH(HT14,$AA14:$HS14,0)),"") | HV14: =IFERROR(SMALL($AA14:$HS14,VALUE(LEFT(HV$1,1))),"") -> 36900 | HW14: =IFERROR(OFFSET($A$1,0,MATCH(HV14,$AA14:$HS14,0)),"") | HX14: =IFERROR(SMALL($AA14:$HS14,VALUE(LEFT(HX$1,1))),"") -> 47250 | HY14: =IFERROR(OFFSET($AA$1,0,MATCH(HX14,$AA14:$HS14,0)),"") | ID14: =IFERROR(__xludf.DUMMYFUNCTION(" IFERROR( TEXTJOIN(""|||"",FALSE , ARRAY_CONSTRAIN( SORT( ARRAYFORMULA(Split(TRANSPOSE (Split(TEXTJOIN(""|||"",TRUE,'1-1 Сбор КП'!$IF14:$IL14),""|||"",FALSE,FALSE) ),""|"",FALSE,FALSE)),3,FALSE ),100,2) ) "&",)"),"") | IE14: =IFERROR(__xludf.DUMMYFUNCTION("LAMBDA(cc,тело,комент, комЭкс, порядок,показ, BYROW(тело, LAMBDA(r, TEXTJOIN(""|||"",FALSE,ARRAY_CONSTRAIN( Query( TRANSPOSE( { {ARRAYFORMULA( FILTER( ADDRESS(ROW(r), COLUMN(r) ), MOD(COLUMN(r)-cc,3)=0))}; {ARRAYFORMULA( FILTER( ADDRESS(1, COLUMN(r) ), MO"&"D(COLUMN(r)-cc,3)=0))}; {ARRAYFORMULA( IFERROR(VLOOKUP( FILTER( ADDRESS(1, COLUMN(r) ), MOD(COLUMN(r)-cc,3)=0), { TRANSPOSE (FILTER( {SPLIT(INDEX(комент,1,0),""|||"",FALSE,FALSE)}, ARRAYFORMULA( ISODD({SEQUENCE(1, COLUMNS(SPLIT(INDEX(комент,1,0),""|||"&""",FALSE,FALSE) ), 1, 1)})))) , TRANSPOSE (FILTER( {SPLIT(INDEX(комент,1,0),""|||"",FALSE,FALSE)}, ARRAYFORMULA( ISEVEN({SEQUENCE(1, COLUMNS( SPLIT(INDEX(комент,1,0),""|||"",FALSE,FALSE) ), 1, 1)}))))} ,2,0 ),""""))}; {ARRAYFORMULA( FILTER( ADDRESS(RO"&"W(r), COLUMN(r) ), MOD(COLUMN(r)-cc,3)=1))}; {ARRAYFORMULA( Lambda(f,m,""Подходит: ""& IFERROR( VLOOKUP( f, комЭкс, 4,0 ),""-?"")&"", ""& m&"" ""&IFERROR(VLOOKUP( f, комЭкс, 2,0 ),)&"" ""&IFERROR(VLOOKUP( f, комЭкс, 3,0 ),) ) ( FILTER( ADDRESS(1, COLUM"&"N(r) ), MOD(COLUMN(r)-cc,3)=0), FILTER( r, MOD(COLUMN(r)-cc,3)=2) ) ) }; {ARRAYFORMULA( FILTER( r, MOD(COLUMN(r)-cc,3)=0))}; BYCOL({ARRAYFORMULA( FILTER( ""'1-1 Сбор КП'!""&""R1C""&COLUMN(r) , MOD(COLUMN(r)-cc,3)=0))},LAMBDA(aa, LAMBDA(a,ifs ( IFERR"&"OR(FIND(""(♠)"",a),0)<>0,IFERROR( VLOOKUP(""♠"",порядок,2,FALSE),5), IFERROR(FIND(""(♦️)"",a),0)<>0,IFERROR( VLOOKUP(""♦️"",порядок,2,FALSE),5), IFERROR(FIND(""(♣️)"",a),0)<>0,IFERROR( VLOOKUP(""♣️"",порядок,2,FALSE),5), IFERROR(FIND(""(♥️)"",a),0)<>0,IFE"&"RROR( VLOOKUP(""♥️"",порядок,2,FALSE),5), TRUE,IFERROR( VLOOKUP(""-"",порядок,2,FALSE),5) ))(INDIRECT( aa,FALSE) ) )); BYCOL({ARRAYFORMULA( FILTER( ""'1-1 Сбор КП'!""&""R1C""&COLUMN(r) , MOD(COLUMN(r)-cc,3)=0))},LAMBDA(aa, LAMBDA(a,ifs ( IFERROR(FIND"&"(""(♠)"",a),0)<>0,IFERROR( VLOOKUP(""♠"",показ,2,FALSE),TRUE), IFERROR(FIND(""(♦️)"",a),0)<>0,IFERROR( VLOOKUP(""♦️"",показ,2,FALSE),TRUE), IFERROR(FIND(""(♣️)"",a),0)<>0,IFERROR( VLOOKUP(""♣️"",показ,2,FALSE),TRUE), IFERROR(FIND(""(♥️)"",a),0)<>0,IFERROR"&"( VLOOKUP(""♥️"",показ,2,FALSE),TRUE), TRUE,IFERROR( VLOOKUP(""-"",показ,2,FALSE),TRUE) ))(INDIRECT( aa,FALSE) ) )) }),""Select * Where Col6 is not null and Col8=true Order by Col7, Col6"",0),7,5)) ) ) ) ( COLUMN('1-1 Сбор КП'!$AA14), '1-1 Сбор КП'!$"&"AA14:$HS14, '1-1 Сбор КП'!$ID14, BYROW( TRANSPOSE(Split('1-1 Сбор КП'!$IQ14,""|||"",FALSE)),LAMBDA(rc,Split(rc,""📎"",FALSE,FALSE))), {'3-3 Выбор поставщиков'!$AB$24:$AB$28 , '3-3 Выбор поставщиков'!$AF$24:$AF$28}, {'3-3 Выбор поставщиков'!$AB$24:$AB"&"$28 , '3-3 Выбор поставщиков'!$AD$24:$AD$28} )"),"$AG$14|||$AG$1||||||$AH$14|||Подходит: Осн поставщик, Масляный сепаратор DS 3084 |||$BE$14|||$BE$1||||||$BF$14|||Подходит: Да, Cепаратор DS 3084 [ Аналог DC/S3084 ] |||$AS$14|||$AS$1||||||$AT$14|||Подходит: -?, Масляный сепаратор DS 3084 |||$AV$14|||$"&"AV$1||||||$AW$14|||Подходит: -?, DS 3084 |||$AA$14|||$AA$1||||||$AB$14|||Подходит: -?, Масляный сепаратор DS 3084 = NS 008430 |||$BN$14|||$BN$1||||||$BO$14|||Подходит: -?, Фильтр сепаратор SOTRAS DC 3084 ") -> $AG$14|||$AG$1||||||$AH$14|||Подходит: Осн поставщик, Масляный сепаратор DS 3084 |||$BE$14|||$BE$1||||||$BF$14|||Подходит: Да, Cепаратор DS 3084 [ Аналог DC/S3084 ] |||$AS$14|||$AS$1||||||$AT$14|||Подходит: -?, Масляный сепаратор DS 3084 |||$AV$14|||$AV$1||||||$AW$14|||Подходит: -?, DS 3084 |||$AA$14|||$AA$1||||||$AB$14|||Подходит: -?, Масляный сепаратор DS 3084 = NS 008430 |||$BN$14|||$BN$1||||||$BO$14|||Подходит: -?, Фильтр сепаратор SOTRAS DC 3084 | IQ14: =IFERROR(__xludf.DUMMYFUNCTION(" IFERROR( TEXTJOIN(""|||"",true , BYROW( ARRAY_CONSTRAIN( SORT( ARRAYFORMULA( Split( TRANSPOSE ( Split(TEXTJOIN(""|||"", TRUE, '1-1 Сбор КП'!$IS14:$JF14) ,""|||"",FALSE,FALSE) ),""📎"",FALSE,FAL"&"SE)),5,FALSE ),100,4) ,LAMBDA(r,TEXTJOIN(""📎"",FALSE ,r)) ) ,))"),"$BE$1📎📎📎Да|||$AG$1📎📎📎Осн поставщик|||$AG$1📎📎📎Осн поставщик") -> $BE$1📎📎📎Да|||$AG$1📎📎📎Осн поставщик|||$AG$1📎📎📎Осн поставщик | IR14: =IFERROR(__xludf.DUMMYFUNCTION(" LAMBDA(cc,тело,комент,комЭкс,BYROW(тело,LAMBDA(r, TEXTJOIN(""|||"",FALSE, ARRAY_CONSTRAIN( Query( TRANSPOSE( { { ARRAYFORMULA( FILTER( ADDRESS(ROW(r), COLUMN(r) ), MOD(COLUMN(r)-cc,3)=0)) }; { ARRAYFORMULA( FILTER( ADDRESS(1, COLUMN(r) ), MOD(COL"&"UMN(r)-cc,3)=0)) }; { ARRAYFORMULA( FILTER( ADDRESS(ROW(r), COLUMN(r) ), MOD(COLUMN(r)-cc,3)=1)) }; { ARRAYFORMULA( FILTER( ADDRESS(ROW(r), COLUMN(r)+1 ), MOD(COLUMN(r)-cc,3)=1)) }; { ARRAYFORMULA( IFERROR(VLOOKUP( FILTER( ADDRESS(1,"&" COLUMN(r) ), MOD(COLUMN(r)-cc,3)=0),комЭкс,2,0 ),"""")) }; { ARRAYFORMULA( IFERROR(VLOOKUP( FILTER( ADDRESS(1, COLUMN(r) ), MOD(COLUMN(r)-cc,3)=0),комЭкс,3,0 ),"""")) }; { ARRAYFORMULA( IFERROR(VLOOKUP( FILTER( ADDRESS(1, COLUMN(r) ), MOD(COLUMN("&"r)-cc,3)=0),комЭкс,4,0 ),"""")) }; { ARRAYFORMULA( IFERROR(VLOOKUP( FILTER( ADDRESS(1, COLUMN(r) ), MOD(COLUMN(r)-cc,3)=0), { TRANSPOSE (FILTER( {SPLIT(INDEX(комент,1,0),""|||"",FALSE,FALSE)}, ARRAYFORMULA( ISODD({SEQUENCE(1, COLUMNS(SPLIT(INDEX(ком"&"ент,1,0),""|||"",FALSE,FALSE) ), 1, 1)})))) , TRANSPOSE (FILTER( {SPLIT(INDEX(комент,1,0),""|||"",FALSE,FALSE)}, ARRAYFORMULA( ISEVEN({SEQUENCE(1, COLUMNS( SPLIT(INDEX(комент,1,0),""|||"",FALSE,FALSE) ), 1, 1)}))))} ,2,0 ),"""")) }; { ARRAYFORMULA( FIL"&"TER( r, MOD(COLUMN(r)-cc,3)=0)) } } ),""Select * Where Col9 is not null Order by Col9"",0),14,8))) )) ( COLUMN('1-1 Сбор КП'!$AA14), '1-1 Сбор КП'!$AA14:$HS14, '1-1 Сбор КП'!$ID14, BYROW( TRANSPOSE(Split('1-1 Сбор КП'!$IQ14,""|||"",FALSE)),LAMBDA("&"rc,Split(rc,""📎"",FALSE,FALSE))) ) "),"$AG$14|||$AG$1|||$AH$14|||$AI$14|||||||||Осн поставщик||||||$BE$14|||$BE$1|||$BF$14|||$BG$14|||||||||Да||||||$AS$14|||$AS$1|||$AT$14|||$AU$14|||||||||||||||$AV$14|||$AV$1|||$AW$14|||$AX$14|||||||||||||||$AA$14|||$AA$1|||$AB$14|||$AC$14|||||||||||||||$BN$1"&"4|||$BN$1|||$BO$14|||$BP$14||||||||||||") -> $AG$14|||$AG$1|||$AH$14|||$AI$14|||||||||Осн поставщик||||||$BE$14|||$BE$1|||$BF$14|||$BG$14|||||||||Да||||||$AS$14|||$AS$1|||$AT$14|||$AU$14|||||||||||||||$AV$14|||$AV$1|||$AW$14|||$AX$14|||||||||||||||$AA$14|||$AA$1|||$AB$14|||$AC$14|||||||||||||||$BN$14|||$BN$1|||$BO$14|||$BP$14|||||||||||| | IS14: $AG$1📎📎📎Осн поставщик📎1791374860469 | IT14: $AG$1📎📎📎Осн поставщик📎1791374860469|||$BE$1📎📎📎Да📎1791376329796
C15: 14 | D15: Воздушный фильтр ЛААЗ ЭФВ 721.1109560 (7405. 1109560) | E15: BB-50/8 ВУЗ АО «НПАО «ВНИИ компрессормаш» | F15: шт. | G15: 4 | H15: 0,00 900,00 | I15: 0,00 3 600,00 | J15: 6 | Q15: =IFERROR(__xludf.DUMMYFUNCTION("""COMPUTED_VALUE"""),6.0) -> 6 | Z15: ID_T014 | AA15: 2900 | AB15: 7 д | AC15: Воздушный фильтр ЛААЗ ЭФВ 721.1109560 (7405. 1109560) | AG15: 1326 | AH15: нал | AI15: Аналог DIFA4319M | AS15: =4350+1750 -> 6100 | AT15: 7 рд | AU15: 721.1109560, Элемент фильтрующий очистки воздуха (основной), 721.1109560, Элемент фильтрующий очистки воздуха (внутренний) | AV15: 900 | AW15: нал | AX15: 7405. 1109560 | AY15: 1838.86 | BA15: NF4502 Фильтрэлемент очистки воздуха (ФП 207.1-04 Optima) КАМАЗ-7405 Евро-1 / OEM: 7405-1109.560 | BN15: 1064 | BO15: 10 д | BP15: 701.01.059 DOKA Элемент вфильтра | HT15: =IFERROR(SMALL($R15:$HS15,VALUE(LEFT(HT$1,1))),"") -> 900 | HU15: =IFERROR(OFFSET($AA$1,0,MATCH(HT15,$AA15:$HS15,0)),"") | HV15: =IFERROR(SMALL($AA15:$HS15,VALUE(LEFT(HV$1,1))),"") -> 1064 | HW15: =IFERROR(OFFSET($A$1,0,MATCH(HV15,$AA15:$HS15,0)),"") | HX15: =IFERROR(SMALL($AA15:$HS15,VALUE(LEFT(HX$1,1))),"") -> 1326 | HY15: =IFERROR(OFFSET($AA$1,0,MATCH(HX15,$AA15:$HS15,0)),"") | ID15: =IFERROR(__xludf.DUMMYFUNCTION(" IFERROR( TEXTJOIN(""|||"",FALSE , ARRAY_CONSTRAIN( SORT( ARRAYFORMULA(Split(TRANSPOSE (Split(TEXTJOIN(""|||"",TRUE,'1-1 Сбор КП'!$IF15:$IL15),""|||"",FALSE,FALSE) ),""|"",FALSE,FALSE)),3,FALSE ),100,2) ) "&",)"),"") | IE15: =IFERROR(__xludf.DUMMYFUNCTION("LAMBDA(cc,тело,комент, комЭкс, порядок,показ, BYROW(тело, LAMBDA(r, TEXTJOIN(""|||"",FALSE,ARRAY_CONSTRAIN( Query( TRANSPOSE( { {ARRAYFORMULA( FILTER( ADDRESS(ROW(r), COLUMN(r) ), MOD(COLUMN(r)-cc,3)=0))}; {ARRAYFORMULA( FILTER( ADDRESS(1, COLUMN(r) ), MO"&"D(COLUMN(r)-cc,3)=0))}; {ARRAYFORMULA( IFERROR(VLOOKUP( FILTER( ADDRESS(1, COLUMN(r) ), MOD(COLUMN(r)-cc,3)=0), { TRANSPOSE (FILTER( {SPLIT(INDEX(комент,1,0),""|||"",FALSE,FALSE)}, ARRAYFORMULA( ISODD({SEQUENCE(1, COLUMNS(SPLIT(INDEX(комент,1,0),""|||"&""",FALSE,FALSE) ), 1, 1)})))) , TRANSPOSE (FILTER( {SPLIT(INDEX(комент,1,0),""|||"",FALSE,FALSE)}, ARRAYFORMULA( ISEVEN({SEQUENCE(1, COLUMNS( SPLIT(INDEX(комент,1,0),""|||"",FALSE,FALSE) ), 1, 1)}))))} ,2,0 ),""""))}; {ARRAYFORMULA( FILTER( ADDRESS(RO"&"W(r), COLUMN(r) ), MOD(COLUMN(r)-cc,3)=1))}; {ARRAYFORMULA( Lambda(f,m,""Подходит: ""& IFERROR( VLOOKUP( f, комЭкс, 4,0 ),""-?"")&"", ""& m&"" ""&IFERROR(VLOOKUP( f, комЭкс, 2,0 ),)&"" ""&IFERROR(VLOOKUP( f, комЭкс, 3,0 ),) ) ( FILTER( ADDRESS(1, COLUM"&"N(r) ), MOD(COLUMN(r)-cc,3)=0), FILTER( r, MOD(COLUMN(r)-cc,3)=2) ) ) }; {ARRAYFORMULA( FILTER( r, MOD(COLUMN(r)-cc,3)=0))}; BYCOL({ARRAYFORMULA( FILTER( ""'1-1 Сбор КП'!""&""R1C""&COLUMN(r) , MOD(COLUMN(r)-cc,3)=0))},LAMBDA(aa, LAMBDA(a,ifs ( IFERR"&"OR(FIND(""(♠)"",a),0)<>0,IFERROR( VLOOKUP(""♠"",порядок,2,FALSE),5), IFERROR(FIND(""(♦️)"",a),0)<>0,IFERROR( VLOOKUP(""♦️"",порядок,2,FALSE),5), IFERROR(FIND(""(♣️)"",a),0)<>0,IFERROR( VLOOKUP(""♣️"",порядок,2,FALSE),5), IFERROR(FIND(""(♥️)"",a),0)<>0,IFE"&"RROR( VLOOKUP(""♥️"",порядок,2,FALSE),5), TRUE,IFERROR( VLOOKUP(""-"",порядок,2,FALSE),5) ))(INDIRECT( aa,FALSE) ) )); BYCOL({ARRAYFORMULA( FILTER( ""'1-1 Сбор КП'!""&""R1C""&COLUMN(r) , MOD(COLUMN(r)-cc,3)=0))},LAMBDA(aa, LAMBDA(a,ifs ( IFERROR(FIND"&"(""(♠)"",a),0)<>0,IFERROR( VLOOKUP(""♠"",показ,2,FALSE),TRUE), IFERROR(FIND(""(♦️)"",a),0)<>0,IFERROR( VLOOKUP(""♦️"",показ,2,FALSE),TRUE), IFERROR(FIND(""(♣️)"",a),0)<>0,IFERROR( VLOOKUP(""♣️"",показ,2,FALSE),TRUE), IFERROR(FIND(""(♥️)"",a),0)<>0,IFERROR"&"( VLOOKUP(""♥️"",показ,2,FALSE),TRUE), TRUE,IFERROR( VLOOKUP(""-"",показ,2,FALSE),TRUE) ))(INDIRECT( aa,FALSE) ) )) }),""Select * Where Col6 is not null and Col8=true Order by Col7, Col6"",0),7,5)) ) ) ) ( COLUMN('1-1 Сбор КП'!$AA15), '1-1 Сбор КП'!$"&"AA15:$HS15, '1-1 Сбор КП'!$ID15, BYROW( TRANSPOSE(Split('1-1 Сбор КП'!$IQ15,""|||"",FALSE)),LAMBDA(rc,Split(rc,""📎"",FALSE,FALSE))), {'3-3 Выбор поставщиков'!$AB$24:$AB$28 , '3-3 Выбор поставщиков'!$AF$24:$AF$28}, {'3-3 Выбор поставщиков'!$AB$24:$AB"&"$28 , '3-3 Выбор поставщиков'!$AD$24:$AD$28} )"),"$AV$15|||$AV$1||||||$AW$15|||Подходит: Осн поставщик, 7405. 1109560 |||$BN$15|||$BN$1||||||$BO$15|||Подходит: Нет, 701.01.059 DOKA Элемент вфильтра |||$AG$15|||$AG$1||||||$AH$15|||Подходит: Да, Аналог DIFA4319M |||$AY$15|||$AY$1||||||$AZ$15|||Подходит:"&" Да, NF4502 Фильтрэлемент очистки воздуха (ФП 207.1-04 Optima) КАМАЗ-7405 Евро-1 / OEM: 7405-1109.560 |||$AA$15|||$AA$1||||||$AB$15|||Подходит: -?, Воздушный фильтр ЛААЗ ЭФВ 721.1109560 (7405. 1109560) |||$AS$15|||$AS$1||||||$AT$15|||Подходит: -?, 721"&".1109560, Элемент фильтрующий очистки воздуха (основной), 721.1109560, Элемент фильтрующий очистки воздуха (внутренний) ") -> $AV$15|||$AV$1||||||$AW$15|||Подходит: Осн поставщик, 7405. 1109560 |||$BN$15|||$BN$1||||||$BO$15|||Подходит: Нет, 701.01.059 DOKA Элемент вфильтра |||$AG$15|||$AG$1||||||$AH$15|||Подходит: Да, Аналог DIFA4319M |||$AY$15|||$AY$1||||||$AZ$15|||Подходит: Да, NF4502 Фильтрэлемент очистки воздуха (ФП 207.1-04 Optima) КАМАЗ-7405 Евро-1 / OEM: 7405-1109.560 |||$AA$15|||$AA$1||||||$AB$15|||Подходит: -?, Воздушный фильтр ЛААЗ ЭФВ 721.1109560 (7405. 1109560) |||$AS$15|||$AS$1||||||$AT$15|||Подходит: -?, 721.1109560, Элемент фильтрующий очистки воздуха (основной), 721.1109560, Элемент фильтрующий очистки воздуха (внутренний) | IQ15: =IFERROR(__xludf.DUMMYFUNCTION(" IFERROR( TEXTJOIN(""|||"",true , BYROW( ARRAY_CONSTRAIN( SORT( ARRAYFORMULA( Split( TRANSPOSE ( Split(TEXTJOIN(""|||"", TRUE, '1-1 Сбор КП'!$IS15:$JF15) ,""|||"",FALSE,FALSE) ),""📎"",FALSE,FAL"&"SE)),5,FALSE ),100,4) ,LAMBDA(r,TEXTJOIN(""📎"",FALSE ,r)) ) ,))"),"$AY$1📎📎📎Да|||$AG$1📎📎📎Да|||$AG$1📎📎📎Да|||$BN$1📎📎📎Нет|||$BN$1📎📎📎Нет|||$BN$1📎📎📎Нет|||$AV$1📎📎📎Осн поставщик|||$AV$1📎📎📎Осн поставщик|||$AV$1📎📎📎Осн поставщик|||$AV$1📎📎📎Осн поставщик") -> $AY$1📎📎📎Да|||$AG$1📎📎📎Да|||$AG$1📎📎📎Да|||$BN$1📎📎📎Нет|||$BN$1📎📎📎Нет|||$BN$1📎📎📎Нет|||$AV$1📎📎📎Осн поставщик|||$AV$1📎📎📎Осн поставщик|||$AV$1📎📎📎Осн поставщик|||$AV$1📎📎📎Осн поставщик | IR15: =IFERROR(__xludf.DUMMYFUNCTION(" LAMBDA(cc,тело,комент,комЭкс,BYROW(тело,LAMBDA(r, TEXTJOIN(""|||"",FALSE, ARRAY_CONSTRAIN( Query( TRANSPOSE( { { ARRAYFORMULA( FILTER( ADDRESS(ROW(r), COLUMN(r) ), MOD(COLUMN(r)-cc,3)=0)) }; { ARRAYFORMULA( FILTER( ADDRESS(1, COLUMN(r) ), MOD(COL"&"UMN(r)-cc,3)=0)) }; { ARRAYFORMULA( FILTER( ADDRESS(ROW(r), COLUMN(r) ), MOD(COLUMN(r)-cc,3)=1)) }; { ARRAYFORMULA( FILTER( ADDRESS(ROW(r), COLUMN(r)+1 ), MOD(COLUMN(r)-cc,3)=1)) }; { ARRAYFORMULA( IFERROR(VLOOKUP( FILTER( ADDRESS(1,"&" COLUMN(r) ), MOD(COLUMN(r)-cc,3)=0),комЭкс,2,0 ),"""")) }; { ARRAYFORMULA( IFERROR(VLOOKUP( FILTER( ADDRESS(1, COLUMN(r) ), MOD(COLUMN(r)-cc,3)=0),комЭкс,3,0 ),"""")) }; { ARRAYFORMULA( IFERROR(VLOOKUP( FILTER( ADDRESS(1, COLUMN(r) ), MOD(COLUMN("&"r)-cc,3)=0),комЭкс,4,0 ),"""")) }; { ARRAYFORMULA( IFERROR(VLOOKUP( FILTER( ADDRESS(1, COLUMN(r) ), MOD(COLUMN(r)-cc,3)=0), { TRANSPOSE (FILTER( {SPLIT(INDEX(комент,1,0),""|||"",FALSE,FALSE)}, ARRAYFORMULA( ISODD({SEQUENCE(1, COLUMNS(SPLIT(INDEX(ком"&"ент,1,0),""|||"",FALSE,FALSE) ), 1, 1)})))) , TRANSPOSE (FILTER( {SPLIT(INDEX(комент,1,0),""|||"",FALSE,FALSE)}, ARRAYFORMULA( ISEVEN({SEQUENCE(1, COLUMNS( SPLIT(INDEX(комент,1,0),""|||"",FALSE,FALSE) ), 1, 1)}))))} ,2,0 ),"""")) }; { ARRAYFORMULA( FIL"&"TER( r, MOD(COLUMN(r)-cc,3)=0)) } } ),""Select * Where Col9 is not null Order by Col9"",0),14,8))) )) ( COLUMN('1-1 Сбор КП'!$AA15), '1-1 Сбор КП'!$AA15:$HS15, '1-1 Сбор КП'!$ID15, BYROW( TRANSPOSE(Split('1-1 Сбор КП'!$IQ15,""|||"",FALSE)),LAMBDA("&"rc,Split(rc,""📎"",FALSE,FALSE))) ) "),"$AV$15|||$AV$1|||$AW$15|||$AX$15|||||||||Осн поставщик||||||$BN$15|||$BN$1|||$BO$15|||$BP$15|||||||||Нет||||||$AG$15|||$AG$1|||$AH$15|||$AI$15|||||||||Да||||||$AY$15|||$AY$1|||$AZ$15|||$BA$15|||||||||Да||||||$AA$15|||$AA$1|||$AB$15|||$AC$15|||||||||||||||"&"$AS$15|||$AS$1|||$AT$15|||$AU$15||||||||||||") -> $AV$15|||$AV$1|||$AW$15|||$AX$15|||||||||Осн поставщик||||||$BN$15|||$BN$1|||$BO$15|||$BP$15|||||||||Нет||||||$AG$15|||$AG$1|||$AH$15|||$AI$15|||||||||Да||||||$AY$15|||$AY$1|||$AZ$15|||$BA$15|||||||||Да||||||$AA$15|||$AA$1|||$AB$15|||$AC$15|||||||||||||||$AS$15|||$AS$1|||$AT$15|||$AU$15|||||||||||| | IS15: $AV$1📎📎📎Осн поставщик📎1791374871112 | IT15: $AV$1📎📎📎Осн поставщик📎1791374871112|||$BN$1📎📎📎Нет📎1791376394976 | IU15: $AV$1📎📎📎Осн поставщик📎1791374871112|||$BN$1📎📎📎Нет📎1791376394976|||$AG$1📎📎📎Да📎1791376504295 | IV15: $AV$1📎📎📎Осн поставщик📎1791374871112|||$BN$1📎📎📎Нет📎1791376394976|||$AG$1📎📎📎Да📎1791376504295|||$AY$1📎📎📎Да📎1791376592568
C16: 15 | D16: Масляный фильтр W13145/3 | E16: BB-50/8 ВУЗ АО «НПАО «ВНИИ компрессормаш» | F16: шт. | G16: 4 | H16: 3 600,00 2 200,00 | I16: 14 400,00 8 800,00 | J16: 6, из них аналог 1 | Q16: =IFERROR(__xludf.DUMMYFUNCTION("""COMPUTED_VALUE"""),6.0) -> 6 | Z16: ID_T015 | AA16: 3900 | AB16: еал | AC16: Масляный фильтр W13145/3 = PO14300 | AG16: 2855 | AH16: нал | AI16: Аналог SP4146 | AS16: 4200 | AT16: 15 рд | AU16: Масляный фильтр W13145/3- Аналог | AV16: 2200 | AW16: 14 д | AX16: W13145/3 | BE16: 3600 | BF16: 5 рд | BG16: Масляный фильтр W13145/3 [ Аналог W13145 ] | BN16: 2781 | BO16: 10 д | BP16: P550341 Donaldson Фильтр масляный | HT16: =IFERROR(SMALL($R16:$HS16,VALUE(LEFT(HT$1,1))),"") -> 2200 | HU16: =IFERROR(OFFSET($AA$1,0,MATCH(HT16,$AA16:$HS16,0)),"") | HV16: =IFERROR(SMALL($AA16:$HS16,VALUE(LEFT(HV$1,1))),"") -> 2781 | HW16: =IFERROR(OFFSET($A$1,0,MATCH(HV16,$AA16:$HS16,0)),"") | HX16: =IFERROR(SMALL($AA16:$HS16,VALUE(LEFT(HX$1,1))),"") -> 2855 | HY16: =IFERROR(OFFSET($AA$1,0,MATCH(HX16,$AA16:$HS16,0)),"") | ID16: =IFERROR(__xludf.DUMMYFUNCTION(" IFERROR( TEXTJOIN(""|||"",FALSE , ARRAY_CONSTRAIN( SORT( ARRAYFORMULA(Split(TRANSPOSE (Split(TEXTJOIN(""|||"",TRUE,'1-1 Сбор КП'!$IF16:$IL16),""|||"",FALSE,FALSE) ),""|"",FALSE,FALSE)),3,FALSE ),100,2) ) "&",)"),"") | IE16: =IFERROR(__xludf.DUMMYFUNCTION("LAMBDA(cc,тело,комент, комЭкс, порядок,показ, BYROW(тело, LAMBDA(r, TEXTJOIN(""|||"",FALSE,ARRAY_CONSTRAIN( Query( TRANSPOSE( { {ARRAYFORMULA( FILTER( ADDRESS(ROW(r), COLUMN(r) ), MOD(COLUMN(r)-cc,3)=0))}; {ARRAYFORMULA( FILTER( ADDRESS(1, COLUMN(r) ), MO"&"D(COLUMN(r)-cc,3)=0))}; {ARRAYFORMULA( IFERROR(VLOOKUP( FILTER( ADDRESS(1, COLUMN(r) ), MOD(COLUMN(r)-cc,3)=0), { TRANSPOSE (FILTER( {SPLIT(INDEX(комент,1,0),""|||"",FALSE,FALSE)}, ARRAYFORMULA( ISODD({SEQUENCE(1, COLUMNS(SPLIT(INDEX(комент,1,0),""|||"&""",FALSE,FALSE) ), 1, 1)})))) , TRANSPOSE (FILTER( {SPLIT(INDEX(комент,1,0),""|||"",FALSE,FALSE)}, ARRAYFORMULA( ISEVEN({SEQUENCE(1, COLUMNS( SPLIT(INDEX(комент,1,0),""|||"",FALSE,FALSE) ), 1, 1)}))))} ,2,0 ),""""))}; {ARRAYFORMULA( FILTER( ADDRESS(RO"&"W(r), COLUMN(r) ), MOD(COLUMN(r)-cc,3)=1))}; {ARRAYFORMULA( Lambda(f,m,""Подходит: ""& IFERROR( VLOOKUP( f, комЭкс, 4,0 ),""-?"")&"", ""& m&"" ""&IFERROR(VLOOKUP( f, комЭкс, 2,0 ),)&"" ""&IFERROR(VLOOKUP( f, комЭкс, 3,0 ),) ) ( FILTER( ADDRESS(1, COLUM"&"N(r) ), MOD(COLUMN(r)-cc,3)=0), FILTER( r, MOD(COLUMN(r)-cc,3)=2) ) ) }; {ARRAYFORMULA( FILTER( r, MOD(COLUMN(r)-cc,3)=0))}; BYCOL({ARRAYFORMULA( FILTER( ""'1-1 Сбор КП'!""&""R1C""&COLUMN(r) , MOD(COLUMN(r)-cc,3)=0))},LAMBDA(aa, LAMBDA(a,ifs ( IFERR"&"OR(FIND(""(♠)"",a),0)<>0,IFERROR( VLOOKUP(""♠"",порядок,2,FALSE),5), IFERROR(FIND(""(♦️)"",a),0)<>0,IFERROR( VLOOKUP(""♦️"",порядок,2,FALSE),5), IFERROR(FIND(""(♣️)"",a),0)<>0,IFERROR( VLOOKUP(""♣️"",порядок,2,FALSE),5), IFERROR(FIND(""(♥️)"",a),0)<>0,IFE"&"RROR( VLOOKUP(""♥️"",порядок,2,FALSE),5), TRUE,IFERROR( VLOOKUP(""-"",порядок,2,FALSE),5) ))(INDIRECT( aa,FALSE) ) )); BYCOL({ARRAYFORMULA( FILTER( ""'1-1 Сбор КП'!""&""R1C""&COLUMN(r) , MOD(COLUMN(r)-cc,3)=0))},LAMBDA(aa, LAMBDA(a,ifs ( IFERROR(FIND"&"(""(♠)"",a),0)<>0,IFERROR( VLOOKUP(""♠"",показ,2,FALSE),TRUE), IFERROR(FIND(""(♦️)"",a),0)<>0,IFERROR( VLOOKUP(""♦️"",показ,2,FALSE),TRUE), IFERROR(FIND(""(♣️)"",a),0)<>0,IFERROR( VLOOKUP(""♣️"",показ,2,FALSE),TRUE), IFERROR(FIND(""(♥️)"",a),0)<>0,IFERROR"&"( VLOOKUP(""♥️"",показ,2,FALSE),TRUE), TRUE,IFERROR( VLOOKUP(""-"",показ,2,FALSE),TRUE) ))(INDIRECT( aa,FALSE) ) )) }),""Select * Where Col6 is not null and Col8=true Order by Col7, Col6"",0),7,5)) ) ) ) ( COLUMN('1-1 Сбор КП'!$AA16), '1-1 Сбор КП'!$"&"AA16:$HS16, '1-1 Сбор КП'!$ID16, BYROW( TRANSPOSE(Split('1-1 Сбор КП'!$IQ16,""|||"",FALSE)),LAMBDA(rc,Split(rc,""📎"",FALSE,FALSE))), {'3-3 Выбор поставщиков'!$AB$24:$AB$28 , '3-3 Выбор поставщиков'!$AF$24:$AF$28}, {'3-3 Выбор поставщиков'!$AB$24:$AB"&"$28 , '3-3 Выбор поставщиков'!$AD$24:$AD$28} )"),"$AV$16|||$AV$1||||||$AW$16|||Подходит: Осн поставщик, W13145/3 |||$BN$16|||$BN$1||||||$BO$16|||Подходит: -?, P550341 Donaldson Фильтр масляный |||$AG$16|||$AG$1||||||$AH$16|||Подходит: Да, Аналог SP4146 |||$BE$16|||$BE$1||||||$BF$16|||Подходит: -?, Ма"&"сляный фильтр W13145/3 [ Аналог W13145 ] |||$AA$16|||$AA$1||||||$AB$16|||Подходит: -?, Масляный фильтр W13145/3 = PO14300 |||$AS$16|||$AS$1||||||$AT$16|||Подходит: -?, Масляный фильтр W13145/3- Аналог ") -> $AV$16|||$AV$1||||||$AW$16|||Подходит: Осн поставщик, W13145/3 |||$BN$16|||$BN$1||||||$BO$16|||Подходит: -?, P550341 Donaldson Фильтр масляный |||$AG$16|||$AG$1||||||$AH$16|||Подходит: Да, Аналог SP4146 |||$BE$16|||$BE$1||||||$BF$16|||Подходит: -?, Масляный фильтр W13145/3 [ Аналог W13145 ] |||$AA$16|||$AA$1||||||$AB$16|||Подходит: -?, Масляный фильтр W13145/3 = PO14300 |||$AS$16|||$AS$1||||||$AT$16|||Подходит: -?, Масляный фильтр W13145/3- Аналог | IQ16: =IFERROR(__xludf.DUMMYFUNCTION(" IFERROR( TEXTJOIN(""|||"",true , BYROW( ARRAY_CONSTRAIN( SORT( ARRAYFORMULA( Split( TRANSPOSE ( Split(TEXTJOIN(""|||"", TRUE, '1-1 Сбор КП'!$IS16:$JF16) ,""|||"",FALSE,FALSE) ),""📎"",FALSE,FAL"&"SE)),5,FALSE ),100,4) ,LAMBDA(r,TEXTJOIN(""📎"",FALSE ,r)) ) ,))"),"$AG$1📎📎📎Да|||$AV$1📎📎📎Осн поставщик|||$AV$1📎📎📎Осн поставщик") -> $AG$1📎📎📎Да|||$AV$1📎📎📎Осн поставщик|||$AV$1📎📎📎Осн поставщик | IR16: =IFERROR(__xludf.DUMMYFUNCTION(" LAMBDA(cc,тело,комент,комЭкс,BYROW(тело,LAMBDA(r, TEXTJOIN(""|||"",FALSE, ARRAY_CONSTRAIN( Query( TRANSPOSE( { { ARRAYFORMULA( FILTER( ADDRESS(ROW(r), COLUMN(r) ), MOD(COLUMN(r)-cc,3)=0)) }; { ARRAYFORMULA( FILTER( ADDRESS(1, COLUMN(r) ), MOD(COL"&"UMN(r)-cc,3)=0)) }; { ARRAYFORMULA( FILTER( ADDRESS(ROW(r), COLUMN(r) ), MOD(COLUMN(r)-cc,3)=1)) }; { ARRAYFORMULA( FILTER( ADDRESS(ROW(r), COLUMN(r)+1 ), MOD(COLUMN(r)-cc,3)=1)) }; { ARRAYFORMULA( IFERROR(VLOOKUP( FILTER( ADDRESS(1,"&" COLUMN(r) ), MOD(COLUMN(r)-cc,3)=0),комЭкс,2,0 ),"""")) }; { ARRAYFORMULA( IFERROR(VLOOKUP( FILTER( ADDRESS(1, COLUMN(r) ), MOD(COLUMN(r)-cc,3)=0),комЭкс,3,0 ),"""")) }; { ARRAYFORMULA( IFERROR(VLOOKUP( FILTER( ADDRESS(1, COLUMN(r) ), MOD(COLUMN("&"r)-cc,3)=0),комЭкс,4,0 ),"""")) }; { ARRAYFORMULA( IFERROR(VLOOKUP( FILTER( ADDRESS(1, COLUMN(r) ), MOD(COLUMN(r)-cc,3)=0), { TRANSPOSE (FILTER( {SPLIT(INDEX(комент,1,0),""|||"",FALSE,FALSE)}, ARRAYFORMULA( ISODD({SEQUENCE(1, COLUMNS(SPLIT(INDEX(ком"&"ент,1,0),""|||"",FALSE,FALSE) ), 1, 1)})))) , TRANSPOSE (FILTER( {SPLIT(INDEX(комент,1,0),""|||"",FALSE,FALSE)}, ARRAYFORMULA( ISEVEN({SEQUENCE(1, COLUMNS( SPLIT(INDEX(комент,1,0),""|||"",FALSE,FALSE) ), 1, 1)}))))} ,2,0 ),"""")) }; { ARRAYFORMULA( FIL"&"TER( r, MOD(COLUMN(r)-cc,3)=0)) } } ),""Select * Where Col9 is not null Order by Col9"",0),14,8))) )) ( COLUMN('1-1 Сбор КП'!$AA16), '1-1 Сбор КП'!$AA16:$HS16, '1-1 Сбор КП'!$ID16, BYROW( TRANSPOSE(Split('1-1 Сбор КП'!$IQ16,""|||"",FALSE)),LAMBDA("&"rc,Split(rc,""📎"",FALSE,FALSE))) ) "),"$AV$16|||$AV$1|||$AW$16|||$AX$16|||||||||Осн поставщик||||||$BN$16|||$BN$1|||$BO$16|||$BP$16|||||||||||||||$AG$16|||$AG$1|||$AH$16|||$AI$16|||||||||Да||||||$BE$16|||$BE$1|||$BF$16|||$BG$16|||||||||||||||$AA$16|||$AA$1|||$AB$16|||$AC$16|||||||||||||||$AS$1"&"6|||$AS$1|||$AT$16|||$AU$16||||||||||||") -> $AV$16|||$AV$1|||$AW$16|||$AX$16|||||||||Осн поставщик||||||$BN$16|||$BN$1|||$BO$16|||$BP$16|||||||||||||||$AG$16|||$AG$1|||$AH$16|||$AI$16|||||||||Да||||||$BE$16|||$BE$1|||$BF$16|||$BG$16|||||||||||||||$AA$16|||$AA$1|||$AB$16|||$AC$16|||||||||||||||$AS$16|||$AS$1|||$AT$16|||$AU$16|||||||||||| | IS16: $AV$1📎📎📎Осн поставщик📎1791374935487 | IU16: $AV$1📎📎📎Осн поставщик📎1791374935487|||$AG$1📎📎📎Да📎1791376531925
C17: 16 | H17: 0,00 0,00 | I17: 0,00 0,00 | Z17: ID_T016 | HT17: =IFERROR(SMALL($R17:$HS17,VALUE(LEFT(HT$1,1))),"") | HU17: =IFERROR(OFFSET($AA$1,0,MATCH(HT17,$AA17:$HS17,0)),"") | HV17: =IFERROR(SMALL($AA17:$HS17,VALUE(LEFT(HV$1,1))),"") | HW17: =IFERROR(OFFSET($A$1,0,MATCH(HV17,$AA17:$HS17,0)),"") | HX17: =IFERROR(SMALL($AA17:$HS17,VALUE(LEFT(HX$1,1))),"") | HY17: =IFERROR(OFFSET($AA$1,0,MATCH(HX17,$AA17:$HS17,0)),"") | ID17: =IFERROR(__xludf.DUMMYFUNCTION(" IFERROR( TEXTJOIN(""|||"",FALSE , ARRAY_CONSTRAIN( SORT( ARRAYFORMULA(Split(TRANSPOSE (Split(TEXTJOIN(""|||"",TRUE,'1-1 Сбор КП'!$IF17:$IL17),""|||"",FALSE,FALSE) ),""|"",FALSE,FALSE)),3,FALSE ),100,2) ) "&",)"),"") | IE17: =IFERROR(__xludf.DUMMYFUNCTION("LAMBDA(cc,тело,комент, комЭкс, порядок,показ, BYROW(тело, LAMBDA(r, TEXTJOIN(""|||"",FALSE,ARRAY_CONSTRAIN( Query( TRANSPOSE( { {ARRAYFORMULA( FILTER( ADDRESS(ROW(r), COLUMN(r) ), MOD(COLUMN(r)-cc,3)=0))}; {ARRAYFORMULA( FILTER( ADDRESS(1, COLUMN(r) ), MO"&"D(COLUMN(r)-cc,3)=0))}; {ARRAYFORMULA( IFERROR(VLOOKUP( FILTER( ADDRESS(1, COLUMN(r) ), MOD(COLUMN(r)-cc,3)=0), { TRANSPOSE (FILTER( {SPLIT(INDEX(комент,1,0),""|||"",FALSE,FALSE)}, ARRAYFORMULA( ISODD({SEQUENCE(1, COLUMNS(SPLIT(INDEX(комент,1,0),""|||"&""",FALSE,FALSE) ), 1, 1)})))) , TRANSPOSE (FILTER( {SPLIT(INDEX(комент,1,0),""|||"",FALSE,FALSE)}, ARRAYFORMULA( ISEVEN({SEQUENCE(1, COLUMNS( SPLIT(INDEX(комент,1,0),""|||"",FALSE,FALSE) ), 1, 1)}))))} ,2,0 ),""""))}; {ARRAYFORMULA( FILTER( ADDRESS(RO"&"W(r), COLUMN(r) ), MOD(COLUMN(r)-cc,3)=1))}; {ARRAYFORMULA( Lambda(f,m,""Подходит: ""& IFERROR( VLOOKUP( f, комЭкс, 4,0 ),""-?"")&"", ""& m&"" ""&IFERROR(VLOOKUP( f, комЭкс, 2,0 ),)&"" ""&IFERROR(VLOOKUP( f, комЭкс, 3,0 ),) ) ( FILTER( ADDRESS(1, COLUM"&"N(r) ), MOD(COLUMN(r)-cc,3)=0), FILTER( r, MOD(COLUMN(r)-cc,3)=2) ) ) }; {ARRAYFORMULA( FILTER( r, MOD(COLUMN(r)-cc,3)=0))}; BYCOL({ARRAYFORMULA( FILTER( ""'1-1 Сбор КП'!""&""R1C""&COLUMN(r) , MOD(COLUMN(r)-cc,3)=0))},LAMBDA(aa, LAMBDA(a,ifs ( IFERR"&"OR(FIND(""(♠)"",a),0)<>0,IFERROR( VLOOKUP(""♠"",порядок,2,FALSE),5), IFERROR(FIND(""(♦️)"",a),0)<>0,IFERROR( VLOOKUP(""♦️"",порядок,2,FALSE),5), IFERROR(FIND(""(♣️)"",a),0)<>0,IFERROR( VLOOKUP(""♣️"",порядок,2,FALSE),5), IFERROR(FIND(""(♥️)"",a),0)<>0,IFE"&"RROR( VLOOKUP(""♥️"",порядок,2,FALSE),5), TRUE,IFERROR( VLOOKUP(""-"",порядок,2,FALSE),5) ))(INDIRECT( aa,FALSE) ) )); BYCOL({ARRAYFORMULA( FILTER( ""'1-1 Сбор КП'!""&""R1C""&COLUMN(r) , MOD(COLUMN(r)-cc,3)=0))},LAMBDA(aa, LAMBDA(a,ifs ( IFERROR(FIND"&"(""(♠)"",a),0)<>0,IFERROR( VLOOKUP(""♠"",показ,2,FALSE),TRUE), IFERROR(FIND(""(♦️)"",a),0)<>0,IFERROR( VLOOKUP(""♦️"",показ,2,FALSE),TRUE), IFERROR(FIND(""(♣️)"",a),0)<>0,IFERROR( VLOOKUP(""♣️"",показ,2,FALSE),TRUE), IFERROR(FIND(""(♥️)"",a),0)<>0,IFERROR"&"( VLOOKUP(""♥️"",показ,2,FALSE),TRUE), TRUE,IFERROR( VLOOKUP(""-"",показ,2,FALSE),TRUE) ))(INDIRECT( aa,FALSE) ) )) }),""Select * Where Col6 is not null and Col8=true Order by Col7, Col6"",0),7,5)) ) ) ) ( COLUMN('1-1 Сбор КП'!$AA17), '1-1 Сбор КП'!$"&"AA17:$HS17, '1-1 Сбор КП'!$ID17, BYROW( TRANSPOSE(Split('1-1 Сбор КП'!$IQ17,""|||"",FALSE)),LAMBDA(rc,Split(rc,""📎"",FALSE,FALSE))), {'3-3 Выбор поставщиков'!$AB$24:$AB$28 , '3-3 Выбор поставщиков'!$AF$24:$AF$28}, {'3-3 Выбор поставщиков'!$AB$24:$AB"&"$28 , '3-3 Выбор поставщиков'!$AD$24:$AD$28} )"),"#N/A") -> #N/A | IQ17: =IFERROR(__xludf.DUMMYFUNCTION(" IFERROR( TEXTJOIN(""|||"",true , BYROW( ARRAY_CONSTRAIN( SORT( ARRAYFORMULA( Split( TRANSPOSE ( Split(TEXTJOIN(""|||"", TRUE, '1-1 Сбор КП'!$IS17:$JF17) ,""|||"",FALSE,FALSE) ),""📎"",FALSE,FAL"&"SE)),5,FALSE ),100,4) ,LAMBDA(r,TEXTJOIN(""📎"",FALSE ,r)) ) ,))"),"") | IR17: =IFERROR(__xludf.DUMMYFUNCTION(" LAMBDA(cc,тело,комент,комЭкс,BYROW(тело,LAMBDA(r, TEXTJOIN(""|||"",FALSE, ARRAY_CONSTRAIN( Query( TRANSPOSE( { { ARRAYFORMULA( FILTER( ADDRESS(ROW(r), COLUMN(r) ), MOD(COLUMN(r)-cc,3)=0)) }; { ARRAYFORMULA( FILTER( ADDRESS(1, COLUMN(r) ), MOD(COL"&"UMN(r)-cc,3)=0)) }; { ARRAYFORMULA( FILTER( ADDRESS(ROW(r), COLUMN(r) ), MOD(COLUMN(r)-cc,3)=1)) }; { ARRAYFORMULA( FILTER( ADDRESS(ROW(r), COLUMN(r)+1 ), MOD(COLUMN(r)-cc,3)=1)) }; { ARRAYFORMULA( IFERROR(VLOOKUP( FILTER( ADDRESS(1,"&" COLUMN(r) ), MOD(COLUMN(r)-cc,3)=0),комЭкс,2,0 ),"""")) }; { ARRAYFORMULA( IFERROR(VLOOKUP( FILTER( ADDRESS(1, COLUMN(r) ), MOD(COLUMN(r)-cc,3)=0),комЭкс,3,0 ),"""")) }; { ARRAYFORMULA( IFERROR(VLOOKUP( FILTER( ADDRESS(1, COLUMN(r) ), MOD(COLUMN("&"r)-cc,3)=0),комЭкс,4,0 ),"""")) }; { ARRAYFORMULA( IFERROR(VLOOKUP( FILTER( ADDRESS(1, COLUMN(r) ), MOD(COLUMN(r)-cc,3)=0), { TRANSPOSE (FILTER( {SPLIT(INDEX(комент,1,0),""|||"",FALSE,FALSE)}, ARRAYFORMULA( ISODD({SEQUENCE(1, COLUMNS(SPLIT(INDEX(ком"&"ент,1,0),""|||"",FALSE,FALSE) ), 1, 1)})))) , TRANSPOSE (FILTER( {SPLIT(INDEX(комент,1,0),""|||"",FALSE,FALSE)}, ARRAYFORMULA( ISEVEN({SEQUENCE(1, COLUMNS( SPLIT(INDEX(комент,1,0),""|||"",FALSE,FALSE) ), 1, 1)}))))} ,2,0 ),"""")) }; { ARRAYFORMULA( FIL"&"TER( r, MOD(COLUMN(r)-cc,3)=0)) } } ),""Select * Where Col9 is not null Order by Col9"",0),14,8))) )) ( COLUMN('1-1 Сбор КП'!$AA17), '1-1 Сбор КП'!$AA17:$HS17, '1-1 Сбор КП'!$ID17, BYROW( TRANSPOSE(Split('1-1 Сбор КП'!$IQ17,""|||"",FALSE)),LAMBDA("&"rc,Split(rc,""📎"",FALSE,FALSE))) ) "),"#N/A") -> #N/A
C18: 17 | H18: 0,00 0,00 | I18: 0,00 0,00 | Z18: ID_T017 | HT18: =IFERROR(SMALL($R18:$HS18,VALUE(LEFT(HT$1,1))),"") | HU18: =IFERROR(OFFSET($AA$1,0,MATCH(HT18,$AA18:$HS18,0)),"") | HV18: =IFERROR(SMALL($AA18:$HS18,VALUE(LEFT(HV$1,1))),"") | HW18: =IFERROR(OFFSET($A$1,0,MATCH(HV18,$AA18:$HS18,0)),"") | HX18: =IFERROR(SMALL($AA18:$HS18,VALUE(LEFT(HX$1,1))),"") | HY18: =IFERROR(OFFSET($AA$1,0,MATCH(HX18,$AA18:$HS18,0)),"") | ID18: =IFERROR(__xludf.DUMMYFUNCTION(" IFERROR( TEXTJOIN(""|||"",FALSE , ARRAY_CONSTRAIN( SORT( ARRAYFORMULA(Split(TRANSPOSE (Split(TEXTJOIN(""|||"",TRUE,'1-1 Сбор КП'!$IF18:$IL18),""|||"",FALSE,FALSE) ),""|"",FALSE,FALSE)),3,FALSE ),100,2) ) "&",)"),"") | IE18: =IFERROR(__xludf.DUMMYFUNCTION("LAMBDA(cc,тело,комент, комЭкс, порядок,показ, BYROW(тело, LAMBDA(r, TEXTJOIN(""|||"",FALSE,ARRAY_CONSTRAIN( Query( TRANSPOSE( { {ARRAYFORMULA( FILTER( ADDRESS(ROW(r), COLUMN(r) ), MOD(COLUMN(r)-cc,3)=0))}; {ARRAYFORMULA( FILTER( ADDRESS(1, COLUMN(r) ), MO"&"D(COLUMN(r)-cc,3)=0))}; {ARRAYFORMULA( IFERROR(VLOOKUP( FILTER( ADDRESS(1, COLUMN(r) ), MOD(COLUMN(r)-cc,3)=0), { TRANSPOSE (FILTER( {SPLIT(INDEX(комент,1,0),""|||"",FALSE,FALSE)}, ARRAYFORMULA( ISODD({SEQUENCE(1, COLUMNS(SPLIT(INDEX(комент,1,0),""|||"&""",FALSE,FALSE) ), 1, 1)})))) , TRANSPOSE (FILTER( {SPLIT(INDEX(комент,1,0),""|||"",FALSE,FALSE)}, ARRAYFORMULA( ISEVEN({SEQUENCE(1, COLUMNS( SPLIT(INDEX(комент,1,0),""|||"",FALSE,FALSE) ), 1, 1)}))))} ,2,0 ),""""))}; {ARRAYFORMULA( FILTER( ADDRESS(RO"&"W(r), COLUMN(r) ), MOD(COLUMN(r)-cc,3)=1))}; {ARRAYFORMULA( Lambda(f,m,""Подходит: ""& IFERROR( VLOOKUP( f, комЭкс, 4,0 ),""-?"")&"", ""& m&"" ""&IFERROR(VLOOKUP( f, комЭкс, 2,0 ),)&"" ""&IFERROR(VLOOKUP( f, комЭкс, 3,0 ),) ) ( FILTER( ADDRESS(1, COLUM"&"N(r) ), MOD(COLUMN(r)-cc,3)=0), FILTER( r, MOD(COLUMN(r)-cc,3)=2) ) ) }; {ARRAYFORMULA( FILTER( r, MOD(COLUMN(r)-cc,3)=0))}; BYCOL({ARRAYFORMULA( FILTER( ""'1-1 Сбор КП'!""&""R1C""&COLUMN(r) , MOD(COLUMN(r)-cc,3)=0))},LAMBDA(aa, LAMBDA(a,ifs ( IFERR"&"OR(FIND(""(♠)"",a),0)<>0,IFERROR( VLOOKUP(""♠"",порядок,2,FALSE),5), IFERROR(FIND(""(♦️)"",a),0)<>0,IFERROR( VLOOKUP(""♦️"",порядок,2,FALSE),5), IFERROR(FIND(""(♣️)"",a),0)<>0,IFERROR( VLOOKUP(""♣️"",порядок,2,FALSE),5), IFERROR(FIND(""(♥️)"",a),0)<>0,IFE"&"RROR( VLOOKUP(""♥️"",порядок,2,FALSE),5), TRUE,IFERROR( VLOOKUP(""-"",порядок,2,FALSE),5) ))(INDIRECT( aa,FALSE) ) )); BYCOL({ARRAYFORMULA( FILTER( ""'1-1 Сбор КП'!""&""R1C""&COLUMN(r) , MOD(COLUMN(r)-cc,3)=0))},LAMBDA(aa, LAMBDA(a,ifs ( IFERROR(FIND"&"(""(♠)"",a),0)<>0,IFERROR( VLOOKUP(""♠"",показ,2,FALSE),TRUE), IFERROR(FIND(""(♦️)"",a),0)<>0,IFERROR( VLOOKUP(""♦️"",показ,2,FALSE),TRUE), IFERROR(FIND(""(♣️)"",a),0)<>0,IFERROR( VLOOKUP(""♣️"",показ,2,FALSE),TRUE), IFERROR(FIND(""(♥️)"",a),0)<>0,IFERROR"&"( VLOOKUP(""♥️"",показ,2,FALSE),TRUE), TRUE,IFERROR( VLOOKUP(""-"",показ,2,FALSE),TRUE) ))(INDIRECT( aa,FALSE) ) )) }),""Select * Where Col6 is not null and Col8=true Order by Col7, Col6"",0),7,5)) ) ) ) ( COLUMN('1-1 Сбор КП'!$AA18), '1-1 Сбор КП'!$"&"AA18:$HS18, '1-1 Сбор КП'!$ID18, BYROW( TRANSPOSE(Split('1-1 Сбор КП'!$IQ18,""|||"",FALSE)),LAMBDA(rc,Split(rc,""📎"",FALSE,FALSE))), {'3-3 Выбор поставщиков'!$AB$24:$AB$28 , '3-3 Выбор поставщиков'!$AF$24:$AF$28}, {'3-3 Выбор поставщиков'!$AB$24:$AB"&"$28 , '3-3 Выбор поставщиков'!$AD$24:$AD$28} )"),"#N/A") -> #N/A | IQ18: =IFERROR(__xludf.DUMMYFUNCTION(" IFERROR( TEXTJOIN(""|||"",true , BYROW( ARRAY_CONSTRAIN( SORT( ARRAYFORMULA( Split( TRANSPOSE ( Split(TEXTJOIN(""|||"", TRUE, '1-1 Сбор КП'!$IS18:$JF18) ,""|||"",FALSE,FALSE) ),""📎"",FALSE,FAL"&"SE)),5,FALSE ),100,4) ,LAMBDA(r,TEXTJOIN(""📎"",FALSE ,r)) ) ,))"),"") | IR18: =IFERROR(__xludf.DUMMYFUNCTION(" LAMBDA(cc,тело,комент,комЭкс,BYROW(тело,LAMBDA(r, TEXTJOIN(""|||"",FALSE, ARRAY_CONSTRAIN( Query( TRANSPOSE( { { ARRAYFORMULA( FILTER( ADDRESS(ROW(r), COLUMN(r) ), MOD(COLUMN(r)-cc,3)=0)) }; { ARRAYFORMULA( FILTER( ADDRESS(1, COLUMN(r) ), MOD(COL"&"UMN(r)-cc,3)=0)) }; { ARRAYFORMULA( FILTER( ADDRESS(ROW(r), COLUMN(r) ), MOD(COLUMN(r)-cc,3)=1)) }; { ARRAYFORMULA( FILTER( ADDRESS(ROW(r), COLUMN(r)+1 ), MOD(COLUMN(r)-cc,3)=1)) }; { ARRAYFORMULA( IFERROR(VLOOKUP( FILTER( ADDRESS(1,"&" COLUMN(r) ), MOD(COLUMN(r)-cc,3)=0),комЭкс,2,0 ),"""")) }; { ARRAYFORMULA( IFERROR(VLOOKUP( FILTER( ADDRESS(1, COLUMN(r) ), MOD(COLUMN(r)-cc,3)=0),комЭкс,3,0 ),"""")) }; { ARRAYFORMULA( IFERROR(VLOOKUP( FILTER( ADDRESS(1, COLUMN(r) ), MOD(COLUMN("&"r)-cc,3)=0),комЭкс,4,0 ),"""")) }; { ARRAYFORMULA( IFERROR(VLOOKUP( FILTER( ADDRESS(1, COLUMN(r) ), MOD(COLUMN(r)-cc,3)=0), { TRANSPOSE (FILTER( {SPLIT(INDEX(комент,1,0),""|||"",FALSE,FALSE)}, ARRAYFORMULA( ISODD({SEQUENCE(1, COLUMNS(SPLIT(INDEX(ком"&"ент,1,0),""|||"",FALSE,FALSE) ), 1, 1)})))) , TRANSPOSE (FILTER( {SPLIT(INDEX(комент,1,0),""|||"",FALSE,FALSE)}, ARRAYFORMULA( ISEVEN({SEQUENCE(1, COLUMNS( SPLIT(INDEX(комент,1,0),""|||"",FALSE,FALSE) ), 1, 1)}))))} ,2,0 ),"""")) }; { ARRAYFORMULA( FIL"&"TER( r, MOD(COLUMN(r)-cc,3)=0)) } } ),""Select * Where Col9 is not null Order by Col9"",0),14,8))) )) ( COLUMN('1-1 Сбор КП'!$AA18), '1-1 Сбор КП'!$AA18:$HS18, '1-1 Сбор КП'!$ID18, BYROW( TRANSPOSE(Split('1-1 Сбор КП'!$IQ18,""|||"",FALSE)),LAMBDA("&"rc,Split(rc,""📎"",FALSE,FALSE))) ) "),"#N/A") -> #N/A
C19: 18 | H19: 0,00 0,00 | I19: 0,00 0,00 | Z19: ID_T018 | HT19: =IFERROR(SMALL($R19:$HS19,VALUE(LEFT(HT$1,1))),"") | HU19: =IFERROR(OFFSET($AA$1,0,MATCH(HT19,$AA19:$HS19,0)),"") | HV19: =IFERROR(SMALL($AA19:$HS19,VALUE(LEFT(HV$1,1))),"") | HW19: =IFERROR(OFFSET($A$1,0,MATCH(HV19,$AA19:$HS19,0)),"") | HX19: =IFERROR(SMALL($AA19:$HS19,VALUE(LEFT(HX$1,1))),"") | HY19: =IFERROR(OFFSET($AA$1,0,MATCH(HX19,$AA19:$HS19,0)),"") | ID19: =IFERROR(__xludf.DUMMYFUNCTION(" IFERROR( TEXTJOIN(""|||"",FALSE , ARRAY_CONSTRAIN( SORT( ARRAYFORMULA(Split(TRANSPOSE (Split(TEXTJOIN(""|||"",TRUE,'1-1 Сбор КП'!$IF19:$IL19),""|||"",FALSE,FALSE) ),""|"",FALSE,FALSE)),3,FALSE ),100,2) ) "&",)"),"") | IE19: =IFERROR(__xludf.DUMMYFUNCTION("LAMBDA(cc,тело,комент, комЭкс, порядок,показ, BYROW(тело, LAMBDA(r, TEXTJOIN(""|||"",FALSE,ARRAY_CONSTRAIN( Query( TRANSPOSE( { {ARRAYFORMULA( FILTER( ADDRESS(ROW(r), COLUMN(r) ), MOD(COLUMN(r)-cc,3)=0))}; {ARRAYFORMULA( FILTER( ADDRESS(1, COLUMN(r) ), MO"&"D(COLUMN(r)-cc,3)=0))}; {ARRAYFORMULA( IFERROR(VLOOKUP( FILTER( ADDRESS(1, COLUMN(r) ), MOD(COLUMN(r)-cc,3)=0), { TRANSPOSE (FILTER( {SPLIT(INDEX(комент,1,0),""|||"",FALSE,FALSE)}, ARRAYFORMULA( ISODD({SEQUENCE(1, COLUMNS(SPLIT(INDEX(комент,1,0),""|||"&""",FALSE,FALSE) ), 1, 1)})))) , TRANSPOSE (FILTER( {SPLIT(INDEX(комент,1,0),""|||"",FALSE,FALSE)}, ARRAYFORMULA( ISEVEN({SEQUENCE(1, COLUMNS( SPLIT(INDEX(комент,1,0),""|||"",FALSE,FALSE) ), 1, 1)}))))} ,2,0 ),""""))}; {ARRAYFORMULA( FILTER( ADDRESS(RO"&"W(r), COLUMN(r) ), MOD(COLUMN(r)-cc,3)=1))}; {ARRAYFORMULA( Lambda(f,m,""Подходит: ""& IFERROR( VLOOKUP( f, комЭкс, 4,0 ),""-?"")&"", ""& m&"" ""&IFERROR(VLOOKUP( f, комЭкс, 2,0 ),)&"" ""&IFERROR(VLOOKUP( f, комЭкс, 3,0 ),) ) ( FILTER( ADDRESS(1, COLUM"&"N(r) ), MOD(COLUMN(r)-cc,3)=0), FILTER( r, MOD(COLUMN(r)-cc,3)=2) ) ) }; {ARRAYFORMULA( FILTER( r, MOD(COLUMN(r)-cc,3)=0))}; BYCOL({ARRAYFORMULA( FILTER( ""'1-1 Сбор КП'!""&""R1C""&COLUMN(r) , MOD(COLUMN(r)-cc,3)=0))},LAMBDA(aa, LAMBDA(a,ifs ( IFERR"&"OR(FIND(""(♠)"",a),0)<>0,IFERROR( VLOOKUP(""♠"",порядок,2,FALSE),5), IFERROR(FIND(""(♦️)"",a),0)<>0,IFERROR( VLOOKUP(""♦️"",порядок,2,FALSE),5), IFERROR(FIND(""(♣️)"",a),0)<>0,IFERROR( VLOOKUP(""♣️"",порядок,2,FALSE),5), IFERROR(FIND(""(♥️)"",a),0)<>0,IFE"&"RROR( VLOOKUP(""♥️"",порядок,2,FALSE),5), TRUE,IFERROR( VLOOKUP(""-"",порядок,2,FALSE),5) ))(INDIRECT( aa,FALSE) ) )); BYCOL({ARRAYFORMULA( FILTER( ""'1-1 Сбор КП'!""&""R1C""&COLUMN(r) , MOD(COLUMN(r)-cc,3)=0))},LAMBDA(aa, LAMBDA(a,ifs ( IFERROR(FIND"&"(""(♠)"",a),0)<>0,IFERROR( VLOOKUP(""♠"",показ,2,FALSE),TRUE), IFERROR(FIND(""(♦️)"",a),0)<>0,IFERROR( VLOOKUP(""♦️"",показ,2,FALSE),TRUE), IFERROR(FIND(""(♣️)"",a),0)<>0,IFERROR( VLOOKUP(""♣️"",показ,2,FALSE),TRUE), IFERROR(FIND(""(♥️)"",a),0)<>0,IFERROR"&"( VLOOKUP(""♥️"",показ,2,FALSE),TRUE), TRUE,IFERROR( VLOOKUP(""-"",показ,2,FALSE),TRUE) ))(INDIRECT( aa,FALSE) ) )) }),""Select * Where Col6 is not null and Col8=true Order by Col7, Col6"",0),7,5)) ) ) ) ( COLUMN('1-1 Сбор КП'!$AA19), '1-1 Сбор КП'!$"&"AA19:$HS19, '1-1 Сбор КП'!$ID19, BYROW( TRANSPOSE(Split('1-1 Сбор КП'!$IQ19,""|||"",FALSE)),LAMBDA(rc,Split(rc,""📎"",FALSE,FALSE))), {'3-3 Выбор поставщиков'!$AB$24:$AB$28 , '3-3 Выбор поставщиков'!$AF$24:$AF$28}, {'3-3 Выбор поставщиков'!$AB$24:$AB"&"$28 , '3-3 Выбор поставщиков'!$AD$24:$AD$28} )"),"#N/A") -> #N/A | IQ19: =IFERROR(__xludf.DUMMYFUNCTION(" IFERROR( TEXTJOIN(""|||"",true , BYROW( ARRAY_CONSTRAIN( SORT( ARRAYFORMULA( Split( TRANSPOSE ( Split(TEXTJOIN(""|||"", TRUE, '1-1 Сбор КП'!$IS19:$JF19) ,""|||"",FALSE,FALSE) ),""📎"",FALSE,FAL"&"SE)),5,FALSE ),100,4) ,LAMBDA(r,TEXTJOIN(""📎"",FALSE ,r)) ) ,))"),"") | IR19: =IFERROR(__xludf.DUMMYFUNCTION(" LAMBDA(cc,тело,комент,комЭкс,BYROW(тело,LAMBDA(r, TEXTJOIN(""|||"",FALSE, ARRAY_CONSTRAIN( Query( TRANSPOSE( { { ARRAYFORMULA( FILTER( ADDRESS(ROW(r), COLUMN(r) ), MOD(COLUMN(r)-cc,3)=0)) }; { ARRAYFORMULA( FILTER( ADDRESS(1, COLUMN(r) ), MOD(COL"&"UMN(r)-cc,3)=0)) }; { ARRAYFORMULA( FILTER( ADDRESS(ROW(r), COLUMN(r) ), MOD(COLUMN(r)-cc,3)=1)) }; { ARRAYFORMULA( FILTER( ADDRESS(ROW(r), COLUMN(r)+1 ), MOD(COLUMN(r)-cc,3)=1)) }; { ARRAYFORMULA( IFERROR(VLOOKUP( FILTER( ADDRESS(1,"&" COLUMN(r) ), MOD(COLUMN(r)-cc,3)=0),комЭкс,2,0 ),"""")) }; { ARRAYFORMULA( IFERROR(VLOOKUP( FILTER( ADDRESS(1, COLUMN(r) ), MOD(COLUMN(r)-cc,3)=0),комЭкс,3,0 ),"""")) }; { ARRAYFORMULA( IFERROR(VLOOKUP( FILTER( ADDRESS(1, COLUMN(r) ), MOD(COLUMN("&"r)-cc,3)=0),комЭкс,4,0 ),"""")) }; { ARRAYFORMULA( IFERROR(VLOOKUP( FILTER( ADDRESS(1, COLUMN(r) ), MOD(COLUMN(r)-cc,3)=0), { TRANSPOSE (FILTER( {SPLIT(INDEX(комент,1,0),""|||"",FALSE,FALSE)}, ARRAYFORMULA( ISODD({SEQUENCE(1, COLUMNS(SPLIT(INDEX(ком"&"ент,1,0),""|||"",FALSE,FALSE) ), 1, 1)})))) , TRANSPOSE (FILTER( {SPLIT(INDEX(комент,1,0),""|||"",FALSE,FALSE)}, ARRAYFORMULA( ISEVEN({SEQUENCE(1, COLUMNS( SPLIT(INDEX(комент,1,0),""|||"",FALSE,FALSE) ), 1, 1)}))))} ,2,0 ),"""")) }; { ARRAYFORMULA( FIL"&"TER( r, MOD(COLUMN(r)-cc,3)=0)) } } ),""Select * Where Col9 is not null Order by Col9"",0),14,8))) )) ( COLUMN('1-1 Сбор КП'!$AA19), '1-1 Сбор КП'!$AA19:$HS19, '1-1 Сбор КП'!$ID19, BYROW( TRANSPOSE(Split('1-1 Сбор КП'!$IQ19,""|||"",FALSE)),LAMBDA("&"rc,Split(rc,""📎"",FALSE,FALSE))) ) "),"#N/A") -> #N/A
C20: 19 | H20: 0,00 0,00 | I20: 0,00 0,00 | Z20: ID_T019 | HT20: =IFERROR(SMALL($R20:$HS20,VALUE(LEFT(HT$1,1))),"") | HU20: =IFERROR(OFFSET($AA$1,0,MATCH(HT20,$AA20:$HS20,0)),"") | HV20: =IFERROR(SMALL($AA20:$HS20,VALUE(LEFT(HV$1,1))),"") | HW20: =IFERROR(OFFSET($A$1,0,MATCH(HV20,$AA20:$HS20,0)),"") | HX20: =IFERROR(SMALL($AA20:$HS20,VALUE(LEFT(HX$1,1))),"") | HY20: =IFERROR(OFFSET($AA$1,0,MATCH(HX20,$AA20:$HS20,0)),"") | ID20: =IFERROR(__xludf.DUMMYFUNCTION(" IFERROR( TEXTJOIN(""|||"",FALSE , ARRAY_CONSTRAIN( SORT( ARRAYFORMULA(Split(TRANSPOSE (Split(TEXTJOIN(""|||"",TRUE,'1-1 Сбор КП'!$IF20:$IL20),""|||"",FALSE,FALSE) ),""|"",FALSE,FALSE)),3,FALSE ),100,2) ) "&",)"),"") | IE20: =IFERROR(__xludf.DUMMYFUNCTION("LAMBDA(cc,тело,комент, комЭкс, порядок,показ, BYROW(тело, LAMBDA(r, TEXTJOIN(""|||"",FALSE,ARRAY_CONSTRAIN( Query( TRANSPOSE( { {ARRAYFORMULA( FILTER( ADDRESS(ROW(r), COLUMN(r) ), MOD(COLUMN(r)-cc,3)=0))}; {ARRAYFORMULA( FILTER( ADDRESS(1, COLUMN(r) ), MO"&"D(COLUMN(r)-cc,3)=0))}; {ARRAYFORMULA( IFERROR(VLOOKUP( FILTER( ADDRESS(1, COLUMN(r) ), MOD(COLUMN(r)-cc,3)=0), { TRANSPOSE (FILTER( {SPLIT(INDEX(комент,1,0),""|||"",FALSE,FALSE)}, ARRAYFORMULA( ISODD({SEQUENCE(1, COLUMNS(SPLIT(INDEX(комент,1,0),""|||"&""",FALSE,FALSE) ), 1, 1)})))) , TRANSPOSE (FILTER( {SPLIT(INDEX(комент,1,0),""|||"",FALSE,FALSE)}, ARRAYFORMULA( ISEVEN({SEQUENCE(1, COLUMNS( SPLIT(INDEX(комент,1,0),""|||"",FALSE,FALSE) ), 1, 1)}))))} ,2,0 ),""""))}; {ARRAYFORMULA( FILTER( ADDRESS(RO"&"W(r), COLUMN(r) ), MOD(COLUMN(r)-cc,3)=1))}; {ARRAYFORMULA( Lambda(f,m,""Подходит: ""& IFERROR( VLOOKUP( f, комЭкс, 4,0 ),""-?"")&"", ""& m&"" ""&IFERROR(VLOOKUP( f, комЭкс, 2,0 ),)&"" ""&IFERROR(VLOOKUP( f, комЭкс, 3,0 ),) ) ( FILTER( ADDRESS(1, COLUM"&"N(r) ), MOD(COLUMN(r)-cc,3)=0), FILTER( r, MOD(COLUMN(r)-cc,3)=2) ) ) }; {ARRAYFORMULA( FILTER( r, MOD(COLUMN(r)-cc,3)=0))}; BYCOL({ARRAYFORMULA( FILTER( ""'1-1 Сбор КП'!""&""R1C""&COLUMN(r) , MOD(COLUMN(r)-cc,3)=0))},LAMBDA(aa, LAMBDA(a,ifs ( IFERR"&"OR(FIND(""(♠)"",a),0)<>0,IFERROR( VLOOKUP(""♠"",порядок,2,FALSE),5), IFERROR(FIND(""(♦️)"",a),0)<>0,IFERROR( VLOOKUP(""♦️"",порядок,2,FALSE),5), IFERROR(FIND(""(♣️)"",a),0)<>0,IFERROR( VLOOKUP(""♣️"",порядок,2,FALSE),5), IFERROR(FIND(""(♥️)"",a),0)<>0,IFE"&"RROR( VLOOKUP(""♥️"",порядок,2,FALSE),5), TRUE,IFERROR( VLOOKUP(""-"",порядок,2,FALSE),5) ))(INDIRECT( aa,FALSE) ) )); BYCOL({ARRAYFORMULA( FILTER( ""'1-1 Сбор КП'!""&""R1C""&COLUMN(r) , MOD(COLUMN(r)-cc,3)=0))},LAMBDA(aa, LAMBDA(a,ifs ( IFERROR(FIND"&"(""(♠)"",a),0)<>0,IFERROR( VLOOKUP(""♠"",показ,2,FALSE),TRUE), IFERROR(FIND(""(♦️)"",a),0)<>0,IFERROR( VLOOKUP(""♦️"",показ,2,FALSE),TRUE), IFERROR(FIND(""(♣️)"",a),0)<>0,IFERROR( VLOOKUP(""♣️"",показ,2,FALSE),TRUE), IFERROR(FIND(""(♥️)"",a),0)<>0,IFERROR"&"( VLOOKUP(""♥️"",показ,2,FALSE),TRUE), TRUE,IFERROR( VLOOKUP(""-"",показ,2,FALSE),TRUE) ))(INDIRECT( aa,FALSE) ) )) }),""Select * Where Col6 is not null and Col8=true Order by Col7, Col6"",0),7,5)) ) ) ) ( COLUMN('1-1 Сбор КП'!$AA20), '1-1 Сбор КП'!$"&"AA20:$HS20, '1-1 Сбор КП'!$ID20, BYROW( TRANSPOSE(Split('1-1 Сбор КП'!$IQ20,""|||"",FALSE)),LAMBDA(rc,Split(rc,""📎"",FALSE,FALSE))), {'3-3 Выбор поставщиков'!$AB$24:$AB$28 , '3-3 Выбор поставщиков'!$AF$24:$AF$28}, {'3-3 Выбор поставщиков'!$AB$24:$AB"&"$28 , '3-3 Выбор поставщиков'!$AD$24:$AD$28} )"),"#N/A") -> #N/A | IQ20: =IFERROR(__xludf.DUMMYFUNCTION(" IFERROR( TEXTJOIN(""|||"",true , BYROW( ARRAY_CONSTRAIN( SORT( ARRAYFORMULA( Split( TRANSPOSE ( Split(TEXTJOIN(""|||"", TRUE, '1-1 Сбор КП'!$IS20:$JF20) ,""|||"",FALSE,FALSE) ),""📎"",FALSE,FAL"&"SE)),5,FALSE ),100,4) ,LAMBDA(r,TEXTJOIN(""📎"",FALSE ,r)) ) ,))"),"") | IR20: =IFERROR(__xludf.DUMMYFUNCTION(" LAMBDA(cc,тело,комент,комЭкс,BYROW(тело,LAMBDA(r, TEXTJOIN(""|||"",FALSE, ARRAY_CONSTRAIN( Query( TRANSPOSE( { { ARRAYFORMULA( FILTER( ADDRESS(ROW(r), COLUMN(r) ), MOD(COLUMN(r)-cc,3)=0)) }; { ARRAYFORMULA( FILTER( ADDRESS(1, COLUMN(r) ), MOD(COL"&"UMN(r)-cc,3)=0)) }; { ARRAYFORMULA( FILTER( ADDRESS(ROW(r), COLUMN(r) ), MOD(COLUMN(r)-cc,3)=1)) }; { ARRAYFORMULA( FILTER( ADDRESS(ROW(r), COLUMN(r)+1 ), MOD(COLUMN(r)-cc,3)=1)) }; { ARRAYFORMULA( IFERROR(VLOOKUP( FILTER( ADDRESS(1,"&" COLUMN(r) ), MOD(COLUMN(r)-cc,3)=0),комЭкс,2,0 ),"""")) }; { ARRAYFORMULA( IFERROR(VLOOKUP( FILTER( ADDRESS(1, COLUMN(r) ), MOD(COLUMN(r)-cc,3)=0),комЭкс,3,0 ),"""")) }; { ARRAYFORMULA( IFERROR(VLOOKUP( FILTER( ADDRESS(1, COLUMN(r) ), MOD(COLUMN("&"r)-cc,3)=0),комЭкс,4,0 ),"""")) }; { ARRAYFORMULA( IFERROR(VLOOKUP( FILTER( ADDRESS(1, COLUMN(r) ), MOD(COLUMN(r)-cc,3)=0), { TRANSPOSE (FILTER( {SPLIT(INDEX(комент,1,0),""|||"",FALSE,FALSE)}, ARRAYFORMULA( ISODD({SEQUENCE(1, COLUMNS(SPLIT(INDEX(ком"&"ент,1,0),""|||"",FALSE,FALSE) ), 1, 1)})))) , TRANSPOSE (FILTER( {SPLIT(INDEX(комент,1,0),""|||"",FALSE,FALSE)}, ARRAYFORMULA( ISEVEN({SEQUENCE(1, COLUMNS( SPLIT(INDEX(комент,1,0),""|||"",FALSE,FALSE) ), 1, 1)}))))} ,2,0 ),"""")) }; { ARRAYFORMULA( FIL"&"TER( r, MOD(COLUMN(r)-cc,3)=0)) } } ),""Select * Where Col9 is not null Order by Col9"",0),14,8))) )) ( COLUMN('1-1 Сбор КП'!$AA20), '1-1 Сбор КП'!$AA20:$HS20, '1-1 Сбор КП'!$ID20, BYROW( TRANSPOSE(Split('1-1 Сбор КП'!$IQ20,""|||"",FALSE)),LAMBDA("&"rc,Split(rc,""📎"",FALSE,FALSE))) ) "),"#N/A") -> #N/A
C21: 20 | H21: 0,00 0,00 | I21: 0,00 0,00 | Z21: ID_T020 | HT21: =IFERROR(SMALL($R21:$HS21,VALUE(LEFT(HT$1,1))),"") | HU21: =IFERROR(OFFSET($AA$1,0,MATCH(HT21,$AA21:$HS21,0)),"") | HV21: =IFERROR(SMALL($AA21:$HS21,VALUE(LEFT(HV$1,1))),"") | HW21: =IFERROR(OFFSET($A$1,0,MATCH(HV21,$AA21:$HS21,0)),"") | HX21: =IFERROR(SMALL($AA21:$HS21,VALUE(LEFT(HX$1,1))),"") | HY21: =IFERROR(OFFSET($AA$1,0,MATCH(HX21,$AA21:$HS21,0)),"") | ID21: =IFERROR(__xludf.DUMMYFUNCTION(" IFERROR( TEXTJOIN(""|||"",FALSE , ARRAY_CONSTRAIN( SORT( ARRAYFORMULA(Split(TRANSPOSE (Split(TEXTJOIN(""|||"",TRUE,'1-1 Сбор КП'!$IF21:$IL21),""|||"",FALSE,FALSE) ),""|"",FALSE,FALSE)),3,FALSE ),100,2) ) "&",)"),"") | IE21: =IFERROR(__xludf.DUMMYFUNCTION("LAMBDA(cc,тело,комент, комЭкс, порядок,показ, BYROW(тело, LAMBDA(r, TEXTJOIN(""|||"",FALSE,ARRAY_CONSTRAIN( Query( TRANSPOSE( { {ARRAYFORMULA( FILTER( ADDRESS(ROW(r), COLUMN(r) ), MOD(COLUMN(r)-cc,3)=0))}; {ARRAYFORMULA( FILTER( ADDRESS(1, COLUMN(r) ), MO"&"D(COLUMN(r)-cc,3)=0))}; {ARRAYFORMULA( IFERROR(VLOOKUP( FILTER( ADDRESS(1, COLUMN(r) ), MOD(COLUMN(r)-cc,3)=0), { TRANSPOSE (FILTER( {SPLIT(INDEX(комент,1,0),""|||"",FALSE,FALSE)}, ARRAYFORMULA( ISODD({SEQUENCE(1, COLUMNS(SPLIT(INDEX(комент,1,0),""|||"&""",FALSE,FALSE) ), 1, 1)})))) , TRANSPOSE (FILTER( {SPLIT(INDEX(комент,1,0),""|||"",FALSE,FALSE)}, ARRAYFORMULA( ISEVEN({SEQUENCE(1, COLUMNS( SPLIT(INDEX(комент,1,0),""|||"",FALSE,FALSE) ), 1, 1)}))))} ,2,0 ),""""))}; {ARRAYFORMULA( FILTER( ADDRESS(RO"&"W(r), COLUMN(r) ), MOD(COLUMN(r)-cc,3)=1))}; {ARRAYFORMULA( Lambda(f,m,""Подходит: ""& IFERROR( VLOOKUP( f, комЭкс, 4,0 ),""-?"")&"", ""& m&"" ""&IFERROR(VLOOKUP( f, комЭкс, 2,0 ),)&"" ""&IFERROR(VLOOKUP( f, комЭкс, 3,0 ),) ) ( FILTER( ADDRESS(1, COLUM"&"N(r) ), MOD(COLUMN(r)-cc,3)=0), FILTER( r, MOD(COLUMN(r)-cc,3)=2) ) ) }; {ARRAYFORMULA( FILTER( r, MOD(COLUMN(r)-cc,3)=0))}; BYCOL({ARRAYFORMULA( FILTER( ""'1-1 Сбор КП'!""&""R1C""&COLUMN(r) , MOD(COLUMN(r)-cc,3)=0))},LAMBDA(aa, LAMBDA(a,ifs ( IFERR"&"OR(FIND(""(♠)"",a),0)<>0,IFERROR( VLOOKUP(""♠"",порядок,2,FALSE),5), IFERROR(FIND(""(♦️)"",a),0)<>0,IFERROR( VLOOKUP(""♦️"",порядок,2,FALSE),5), IFERROR(FIND(""(♣️)"",a),0)<>0,IFERROR( VLOOKUP(""♣️"",порядок,2,FALSE),5), IFERROR(FIND(""(♥️)"",a),0)<>0,IFE"&"RROR( VLOOKUP(""♥️"",порядок,2,FALSE),5), TRUE,IFERROR( VLOOKUP(""-"",порядок,2,FALSE),5) ))(INDIRECT( aa,FALSE) ) )); BYCOL({ARRAYFORMULA( FILTER( ""'1-1 Сбор КП'!""&""R1C""&COLUMN(r) , MOD(COLUMN(r)-cc,3)=0))},LAMBDA(aa, LAMBDA(a,ifs ( IFERROR(FIND"&"(""(♠)"",a),0)<>0,IFERROR( VLOOKUP(""♠"",показ,2,FALSE),TRUE), IFERROR(FIND(""(♦️)"",a),0)<>0,IFERROR( VLOOKUP(""♦️"",показ,2,FALSE),TRUE), IFERROR(FIND(""(♣️)"",a),0)<>0,IFERROR( VLOOKUP(""♣️"",показ,2,FALSE),TRUE), IFERROR(FIND(""(♥️)"",a),0)<>0,IFERROR"&"( VLOOKUP(""♥️"",показ,2,FALSE),TRUE), TRUE,IFERROR( VLOOKUP(""-"",показ,2,FALSE),TRUE) ))(INDIRECT( aa,FALSE) ) )) }),""Select * Where Col6 is not null and Col8=true Order by Col7, Col6"",0),7,5)) ) ) ) ( COLUMN('1-1 Сбор КП'!$AA21), '1-1 Сбор КП'!$"&"AA21:$HS21, '1-1 Сбор КП'!$ID21, BYROW( TRANSPOSE(Split('1-1 Сбор КП'!$IQ21,""|||"",FALSE)),LAMBDA(rc,Split(rc,""📎"",FALSE,FALSE))), {'3-3 Выбор поставщиков'!$AB$24:$AB$28 , '3-3 Выбор поставщиков'!$AF$24:$AF$28}, {'3-3 Выбор поставщиков'!$AB$24:$AB"&"$28 , '3-3 Выбор поставщиков'!$AD$24:$AD$28} )"),"#N/A") -> #N/A | IQ21: =IFERROR(__xludf.DUMMYFUNCTION(" IFERROR( TEXTJOIN(""|||"",true , BYROW( ARRAY_CONSTRAIN( SORT( ARRAYFORMULA( Split( TRANSPOSE ( Split(TEXTJOIN(""|||"", TRUE, '1-1 Сбор КП'!$IS21:$JF21) ,""|||"",FALSE,FALSE) ),""📎"",FALSE,FAL"&"SE)),5,FALSE ),100,4) ,LAMBDA(r,TEXTJOIN(""📎"",FALSE ,r)) ) ,))"),"") | IR21: =IFERROR(__xludf.DUMMYFUNCTION(" LAMBDA(cc,тело,комент,комЭкс,BYROW(тело,LAMBDA(r, TEXTJOIN(""|||"",FALSE, ARRAY_CONSTRAIN( Query( TRANSPOSE( { { ARRAYFORMULA( FILTER( ADDRESS(ROW(r), COLUMN(r) ), MOD(COLUMN(r)-cc,3)=0)) }; { ARRAYFORMULA( FILTER( ADDRESS(1, COLUMN(r) ), MOD(COL"&"UMN(r)-cc,3)=0)) }; { ARRAYFORMULA( FILTER( ADDRESS(ROW(r), COLUMN(r) ), MOD(COLUMN(r)-cc,3)=1)) }; { ARRAYFORMULA( FILTER( ADDRESS(ROW(r), COLUMN(r)+1 ), MOD(COLUMN(r)-cc,3)=1)) }; { ARRAYFORMULA( IFERROR(VLOOKUP( FILTER( ADDRESS(1,"&" COLUMN(r) ), MOD(COLUMN(r)-cc,3)=0),комЭкс,2,0 ),"""")) }; { ARRAYFORMULA( IFERROR(VLOOKUP( FILTER( ADDRESS(1, COLUMN(r) ), MOD(COLUMN(r)-cc,3)=0),комЭкс,3,0 ),"""")) }; { ARRAYFORMULA( IFERROR(VLOOKUP( FILTER( ADDRESS(1, COLUMN(r) ), MOD(COLUMN("&"r)-cc,3)=0),комЭкс,4,0 ),"""")) }; { ARRAYFORMULA( IFERROR(VLOOKUP( FILTER( ADDRESS(1, COLUMN(r) ), MOD(COLUMN(r)-cc,3)=0), { TRANSPOSE (FILTER( {SPLIT(INDEX(комент,1,0),""|||"",FALSE,FALSE)}, ARRAYFORMULA( ISODD({SEQUENCE(1, COLUMNS(SPLIT(INDEX(ком"&"ент,1,0),""|||"",FALSE,FALSE) ), 1, 1)})))) , TRANSPOSE (FILTER( {SPLIT(INDEX(комент,1,0),""|||"",FALSE,FALSE)}, ARRAYFORMULA( ISEVEN({SEQUENCE(1, COLUMNS( SPLIT(INDEX(комент,1,0),""|||"",FALSE,FALSE) ), 1, 1)}))))} ,2,0 ),"""")) }; { ARRAYFORMULA( FIL"&"TER( r, MOD(COLUMN(r)-cc,3)=0)) } } ),""Select * Where Col9 is not null Order by Col9"",0),14,8))) )) ( COLUMN('1-1 Сбор КП'!$AA21), '1-1 Сбор КП'!$AA21:$HS21, '1-1 Сбор КП'!$ID21, BYROW( TRANSPOSE(Split('1-1 Сбор КП'!$IQ21,""|||"",FALSE)),LAMBDA("&"rc,Split(rc,""📎"",FALSE,FALSE))) ) "),"#N/A") -> #N/A
C22: @ | H22: Аналог Остальные | I22: 2 754 800,00 1 207 831,12 | K22: =SUMPRODUCT(G2:G21,K2:K21) -> 0 | Q22: =IFERROR(__xludf.DUMMYFUNCTION("""COMPUTED_VALUE"""),78.0) -> 78 | R22: =IFERROR(__xludf.DUMMYFUNCTION("""COMPUTED_VALUE""")," ") | AA22: {=LAMBDA(vls,pr,fc, BYCOL(vls,LAMBDA(cl, ifs( MOD( COLUMN(cl)-COLUMN(fc),3)=0,IF((COUNTA(cl)-COUNT(IF(cl="",,cl*1) )) =0,LAMBDA(ss,IF(ss<>0,ss,) )(SUMPRODUCT(cl,pr)),"Ошибка: Цена должна быть числом"), MOD( COLUMN(cl)-COLUMN(fc),3)=1,IF(SUM(cl)>0,"Ошибка: Срок должен быть текстом или пусто",), MOD( COLUMN(cl)-COLUMN(fc),3)=2,IF(SUM(cl)>0,"Ошибка: Модель должена быть текстом или пусто",), TRUE, ) ))) ( AA2:HS21, G2:G21, AA2 )} -> 137200 | AD22: 47850.035 | AG22: 78374 | AJ22: 233400 | AM22: 2268000 | AP22: 3485820 | AS22: 135700 | AV22: 113400 | AY22: 7355.44 | BB22: 6098220 | BE22: 304900 | BH22: 589200 | BK22: 245000 | BN22: 132332 | BQ22: 176900 | BT22: Ошибка: Цена должна быть числом | BW22: Ошибка: Цена должна быть числом | BZ22: 219804.12 | CC22: 680577 | CF22: Ошибка: Цена должна быть числом | CI22: 174500
H23: 46308.59 | I23: Меню > Email рассылка > Пересчитать Цена Итого Предложений. Если дата меньше текущей более чем на пол часа, либо поля 'Цена', 'Итого' и 'Предложений' пусты или вы считаете, что они устарели, то выполните команду из меню. | K23: =IF(K22<>'0-Паспорт проекта'!C40,"Ошибка проверить попозиционное НМЦ","ok") -> ok

Sheet 5-0 Товары
C1: header_first | D1: {={'5-0 Передача в закупку'!$D$10 ,'5-0 Передача в закупку'!$E$10 ,'5-0 Передача в закупку'!$H$10 ,'5-0 Передача в закупку'!$J$10 ,'5-0 Передача в закупку'!$K$10 ,'5-0 Передача в закупку'!$L$10 ,'5-0 Передача в закупку'!$F$10 ,'5-0 Передача в закупку'!$G$10 , "" , "" ,'5-0 Передача в закупку'!$M$10 ,'5-0 Передача в закупку'!$N$10 ,'5-0 Передача в закупку'!$O$10 ,'5-0 Передача в закупку'!$I$10 }} -> № | E1: Номенклатура | F1: Характеристики | G1: Ед. Изм | H1: Кол-во | I1: НМЦ | J1: Название товара по договору | K1: Изготовитель товара по договору | N1: Срок поставки по договору | O1: Нац режим 1875 | P1: Код ОКПД 2 | Q1: Состав поставляемой с продукцией технической документации
C2: key | D2: Номер | E2: Номенклатура | F2: Характеристики | G2: ЕдИзм | H2: Количевство | I2: НМЦ | J2: НазваниеТовараПоДоговору | K2: ИзготовительТовараПоДоговору | L2: Группа_1_2 | M2: Группа_5_2 | N2: СрокПоставкиПоДоговору
C3: formulaColl | D3: formulaColl | E3: formulaFree | F3: formulaFree | G3: formulaFree | H3: formulaFree | I3: formulaFree | J3: formulaColl | K3: formulaColl | L3: formulaColl | M3: formulaColl | N3: formulaColl
C4: var_key
C5: var_name
C6: var_value
C7: header_07
C8: header_08
C9: header_last
B10: {={ '5-4 Изменения в товарах'!$C10; Let( _do_row, LAMBDA(_id,_ds, IFERROR( VLOOKUP( _id, _ds, 2, FALSE) ,)), _ids, '5-0 Товары'!$C$11:$C310, _ids_org, '5-0 Передача в закупку'!$C$1:$C310, _ids_izm, '5-4 Изменения в товарах'!$E1:$E310 , _ds_org, '5-0 Передача в закупку'!$A$1:$A310, _ds_izm, '5-4 Изменения в товарах'!$C1:$C310 , _map_org, map(_ids_org,LAMBDA(_id,{ _id , ROW(_id)})), _map_izm, map(_ids_izm,LAMBDA(_id,{ _id , ROW(_id)})), _rez, MAP(_ids, LAMBDA(_id, LAMBDA(izm,org, IF(izm<>"",INDEX(_ds_izm,izm,),IF(org<>"",INDEX(_ds_org,org),)) ) ( _do_row(_id,_map_izm), _do_row(_id,_map_org)) ) ) , _rez ) }} -> Исключить по причине | C10: {={"ID_Товара";let( _t_org, '5-0 Передача в закупку'!$C$11:$C310, _t_izm, '5-4 Изменения в товарах'!$E$11:$E$60 , _t_dop, '5-4 Изменения в товарах'!$E$62:$E310, IFERROR( Sort(UNIQUE({ _t_org; _t_izm; _t_dop })),) )}} -> ID_Товара | D10: {={ {'5-0 Передача в закупку'!$D$10 ,'5-0 Передача в закупку'!$E$10 ,'5-0 Передача в закупку'!$H$10 ,'5-0 Передача в закупку'!$J$10 ,'5-0 Передача в закупку'!$K$10 ,'5-0 Передача в закупку'!$L$10}; Let( _do_row, LAMBDA(_id,_ds, IFERROR( VLOOKUP( _id, _ds, 2, FALSE) ,)), _ids, '5-0 Товары'!$C$11:$C310, _ids_org, '5-0 Передача в закупку'!$C$1:$C310, _ids_izm, '5-4 Изменения в товарах'!$E1:$E310 , _ds_org, {'5-0 Передача в закупку'!$D$1:$D310 ,'5-0 Передача в закупку'!$E$1:$E310 ,'5-0 Передача в закупку'!$H$1:$H310 ,'5-0 Передача в закупку'!$J$1:$J310 ,'5-0 Передача в закупку'!$K$1:$K310 ,'5-0 Передача в закупку'!$L$1:$L310}, _ds_izm, {'5-4 Изменения в товарах'!$F1:$F310,'5-4 Изменения в товарах'!$G1:$G310,'5-4 Изменения в товарах'!$J1:$J310,'5-4 Изменения в товарах'!$L1:$L310,'5-4 Изменения в товарах'!$M1:$M310,'5-4 Изменения в товарах'!$N1:$N310 } , _map_org, map(_ids_org,LAMBDA(_id,{ _id , ROW(_id)})), _map_izm, map(_ids_izm,LAMBDA(_id,{ _id , ROW(_id)})), _rez, MAP(_ids, LAMBDA(_id, LAMBDA(izm,org, IF(izm<>"",INDEX(_ds_izm,izm,),IF(org<>"",INDEX(_ds_org,org),)) ) ( _do_row(_id,_map_izm), _do_row(_id,_map_org)) ) ) , _rez ) }} -> № | E10: Номенклатура | F10: Характеристики | G10: Ед. Изм | H10: Кол-во | I10: НМЦ | J10: {=IF('5-0 Товары'!$E$10:$E310<>"",IFERROR(VLOOKUP('5-0 Товары'!$E$10:$E310,{'5-1 Сбор КП Закупки'!$E$10:$E310,'5-1 Сбор КП Закупки'!$F10:$F310},2,FALSE) ,),)} -> Название товара по договору | K10: {=IF('5-0 Товары'!$E$10:$E310<>"",IFERROR(VLOOKUP('5-0 Товары'!$E$10:$E310,{'5-1 Сбор КП Закупки'!$E$10:$E310,'5-1 Сбор КП Закупки'!$G$10:$G310},2,FALSE) ,),)} -> Изготовитель товара по договору | L10: =IFERROR(__xludf.DUMMYFUNCTION("BYROW({ {'1-1 Сбор КП'!O1}; {LAMBDA( doFindRow, doFilter, theWordStart, theCStart, theWordEnd, theCEnd, theDataWord, theData, doFilter(doFindRow(theDataWord,theWordStart,theCStart),doFindRow(theDataWord,theWordEnd,theCEnd),theData) )( LAMBDA(theWord"&"s,theWord,theC , VLOOKUP( theWord, BYROW(theWords,LAMBDA(theW,{theW , ROW(theW)})),2,FALSE ) +theC), LAMBDA(bodyStart,bodyEnd,theData, FILTER(theData,bodyStart <= BYROW(theData,lambda(d,ROW(d))) ,BYROW(theData,lambda(d,ROW(d)))<=bodyEnd )), ""№"",1,"""&"@"",-1,'1-1 Сбор КП'!C1:C21 ,'1-1 Сбор КП'!O1:O21 )} },LAMBDA(theG,IFERROR(theG,)))"),"Группа") -> Группа | M10: {={"Группа";LAMBDA(doFind,theIds,theData, doFind(theIds,theData) )( LAMBDA(theIds,theData, BYROW(theIds,LAMBDA(ti,IF(ti<>"", IFERROR(VLOOKUP(ti,theData,2,0),),)))), '5-0 Товары'!C11:C310, {'5-2 Запросы КП Закупки'!C11:C310,'5-2 Запросы КП Закупки'!N11:N310} )}} -> Группа | N10: {={ {'5-0 Передача в закупку'!$M$10 ,'5-0 Передача в закупку'!$N$10 ,'5-0 Передача в закупку'!$O$10}; Let( _do_row, LAMBDA(_id,_ds, IFERROR( VLOOKUP( _id, _ds, 2, FALSE) ,)), _ids, '5-0 Товары'!$C$11:$C310, _ids_org, '5-0 Передача в закупку'!$C$1:$C310, _ids_izm, '5-4 Изменения в товарах'!$E1:$E310 , _ds_org, {'5-0 Передача в закупку'!$M$1:$M310 ,'5-0 Передача в закупку'!$N$1:$N310 ,'5-0 Передача в закупку'!$O$1:$O310}, _ds_izm, {'5-4 Изменения в товарах'!$O1:$O310 , '5-4 Изменения в товарах'!$P1:$P310,'5-4 Изменения в товарах'!$Q1:$Q310 }, _map_org, map(_ids_org,LAMBDA(_id,{ _id , ROW(_id)})), _map_izm, map(_ids_izm,LAMBDA(_id,{ _id , ROW(_id)})), _rez, MAP(_ids, LAMBDA(_id, LAMBDA(izm,org, IF(izm<>"",INDEX(_ds_izm,izm,),IF(org<>"",INDEX(_ds_org,org),)) ) ( _do_row(_id,_map_izm), _do_row(_id,_map_org)) ) ) , _rez ) }} -> Срок поставки по договору | O10: Нац режим 1875 | P10: Код ОКПД 2
C11: ID_T001 | D11: 1 | E11: Масляный фильтр - Артикул 89781969 ESG-315 зав.№ F010451 | G11: шт. | H11: 3
C12: ID_T002 | D12: 2 | E12: Масляный фильтр - Артикул 85062259 | G12: шт. | H12: 6
C13: ID_T003 | D13: 3 | E13: Воздушный фильтр - Артикул 85067179 | G13: шт. | H13: 16
C14: ID_T004 | D14: 4 | E14: Термостат в сборе ESM-200; «Gardner Denver» | G14: шт. | H14: 2
C15: ID_T005 | D15: 5 | E15: Масляный сепаратор Артикул 03498328 | G15: шт. | H15: 3
C16: ID_T006 | D16: 6 | E16: Масляный фильтр Артикул 89675429 | G16: шт. | H16: 3
C17: ID_T007 | D17: 7 | E17: Воздушный фильтр - Артикул 81166609 | G17: шт. | H17: 3
C18: ID_T008 | D18: 8 | E18: Сервисный набор арт. 2906020000 | G18: шт. | H18: 3
C19: ID_T009 | D19: 9 | E19: Сервисный набор 8000 ч. арт. 2906075700 | G19: шт. | H19: 3
C20: ID_T010 | D20: 10 | E20: Масляный сепаратор | G20: шт. | H20: 3
C21: ID_T011 | D21: 11 | E21: Воздушный фильтр | G21: шт. | H21: 6
C22: ID_T012 | D22: 12 | E22: Масляный фильтр | G22: шт. | H22: 6
... C25: ID_T015 | D25: 15 | E25: Масляный фильтр W13145/3 | G25: шт. | H25: 4
C26: ID_T016 | D26: 16
C27: ID_T017 | D27: 17
C28: ID_T018 | D28: 18
C29: ID_T019 | D29: 19
C30: ID_T020 | D30: 20

Sheet 5-0 Передача в закупку
C1: header_first
A2: err | B2: РазличиеМужду | C2: key | D2: Номер | E2: Номенклатура | F2: НазваниеТовараПоДоговору | G2: ИзготовительТовараПоДоговору | H2: Характеристики | I2: СоставТехническойДокументации
A3: formulaColl | B3: formulaColl | C3: formulaCell | D3: formulaCell | E3: formulaCell | H3: formulaCell
C4: var_key
C5: var_name
C6: var_value
A7: Скрыть | B7: Скрыть | C7: hide_col | H7: аываываыв dasd fsdf ываыва gsdfsd аыаыва ыаыва а
C8: header_08
C9: header_last
B10: {='5-1 Сбор КП Закупки'!$Y$10:$Y$310} -> РазличиеМужду | C10: ='1-0 Товары'!C10 -> ID_Товара | D10: ='5-1 Сбор КП Закупки'!D10 -> № | E10: ='5-1 Сбор КП Закупки'!E10 -> Номенклатура | F10: ='5-1 Сбор КП Закупки'!F10 -> Название товара по договору | G10: ='5-1 Сбор КП Закупки'!G10 -> Изготовитель товара по договору | H10: ='5-1 Сбор КП Закупки'!H10 -> Характеристики | I10: ='5-1 Сбор КП Закупки'!I10 -> Состав поставляемой с продукцией технической документации | J10: ='1-0 Товары'!G$10 -> Ед. Изм | K10: ='1-0 Товары'!H$10 -> Кол-во | L10: ='1-0 Товары'!I$10 -> НМЦ | M10: ='1-0 Товары'!N$10 -> Срок поставки по договору | N10: ='1-0 Товары'!O$10 -> Нац режим 1875 | O10: ='1-0 Товары'!P$10 -> Код ОКПД 2
C11: ='1-0 Товары'!C11 -> ID_T001 | D11: ='1-0 Товары'!D11 -> 1 | E11: ='1-0 Товары'!E11 -> Масляный фильтр - Артикул 89781969 ESG-315 зав.№ F010451 | J11: ='1-0 Товары'!$G11 -> шт. | K11: ='1-0 Товары'!$H11 -> 3 | L11: ='1-0 Товары'!$I11 | M11: ='1-0 Товары'!$N11 | N11: ='1-0 Товары'!$O11 | O11: ='1-0 Товары'!$P11
C12: ='1-0 Товары'!C12 -> ID_T002 | D12: ='1-0 Товары'!D12 -> 2 | E12: ='1-0 Товары'!E12 -> Масляный фильтр - Артикул 85062259 | J12: ='1-0 Товары'!$G12 -> шт. | K12: ='1-0 Товары'!$H12 -> 6 | L12: ='1-0 Товары'!$I12 | M12: ='1-0 Товары'!$N12 | N12: ='1-0 Товары'!$O12 | O12: ='1-0 Товары'!$P12
C13: ='1-0 Товары'!C13 -> ID_T003 | D13: ='1-0 Товары'!D13 -> 3 | E13: ='1-0 Товары'!E13 -> Воздушный фильтр - Артикул 85067179 | J13: ='1-0 Товары'!$G13 -> шт. | K13: ='1-0 Товары'!$H13 -> 16 | L13: ='1-0 Товары'!$I13 | M13: ='1-0 Товары'!$N13 | N13: ='1-0 Товары'!$O13 | O13: ='1-0 Товары'!$P13
C14: ='1-0 Товары'!C14 -> ID_T004 | D14: ='1-0 Товары'!D14 -> 4 | E14: ='1-0 Товары'!E14 -> Термостат в сборе ESM-200; «Gardner Denver» | J14: ='1-0 Товары'!$G14 -> шт. | K14: ='1-0 Товары'!$H14 -> 2 | L14: ='1-0 Товары'!$I14 | M14: ='1-0 Товары'!$N14 | N14: ='1-0 Товары'!$O14 | O14: ='1-0 Товары'!$P14
C15: ='1-0 Товары'!C15 -> ID_T005 | D15: ='1-0 Товары'!D15 -> 5 | E15: ='1-0 Товары'!E15 -> Масляный сепаратор Артикул 03498328 | J15: ='1-0 Товары'!$G15 -> шт. | K15: ='1-0 Товары'!$H15 -> 3 | L15: ='1-0 Товары'!$I15 | M15: ='1-0 Товары'!$N15 | N15: ='1-0 Товары'!$O15 | O15: ='1-0 Товары'!$P15
C16: ='1-0 Товары'!C16 -> ID_T006 | D16: ='1-0 Товары'!D16 -> 6 | E16: ='1-0 Товары'!E16 -> Масляный фильтр Артикул 89675429 | J16: ='1-0 Товары'!$G16 -> шт. | K16: ='1-0 Товары'!$H16 -> 3 | L16: ='1-0 Товары'!$I16 | M16: ='1-0 Товары'!$N16 | N16: ='1-0 Товары'!$O16 | O16: ='1-0 Товары'!$P16
C17: ='1-0 Товары'!C17 -> ID_T007 | D17: ='1-0 Товары'!D17 -> 7 | E17: ='1-0 Товары'!E17 -> Воздушный фильтр - Артикул 81166609 | J17: ='1-0 Товары'!$G17 -> шт. | K17: ='1-0 Товары'!$H17 -> 3 | L17: ='1-0 Товары'!$I17 | M17: ='1-0 Товары'!$N17 | N17: ='1-0 Товары'!$O17 | O17: ='1-0 Товары'!$P17
C18: ='1-0 Товары'!C18 -> ID_T008 | D18: ='1-0 Товары'!D18 -> 8 | E18: ='1-0 Товары'!E18 -> Сервисный набор арт. 2906020000 | J18: ='1-0 Товары'!$G18 -> шт. | K18: ='1-0 Товары'!$H18 -> 3 | L18: ='1-0 Товары'!$I18 | M18: ='1-0 Товары'!$N18 | N18: ='1-0 Товары'!$O18 | O18: ='1-0 Товары'!$P18
C19: ='1-0 Товары'!C19 -> ID_T009 | D19: ='1-0 Товары'!D19 -> 9 | E19: ='1-0 Товары'!E19 -> Сервисный набор 8000 ч. арт. 2906075700 | J19: ='1-0 Товары'!$G19 -> шт. | K19: ='1-0 Товары'!$H19 -> 3 | L19: ='1-0 Товары'!$I19 | M19: ='1-0 Товары'!$N19 | N19: ='1-0 Товары'!$O19 | O19: ='1-0 Товары'!$P19
C20: ='1-0 Товары'!C20 -> ID_T010 | D20: ='1-0 Товары'!D20 -> 10 | E20: ='1-0 Товары'!E20 -> Масляный сепаратор | J20: ='1-0 Товары'!$G20 -> шт. | K20: ='1-0 Товары'!$H20 -> 3 | L20: ='1-0 Товары'!$I20 | M20: ='1-0 Товары'!$N20 | N20: ='1-0 Товары'!$O20 | O20: ='1-0 Товары'!$P20
C21: ='1-0 Товары'!C21 -> ID_T011 | D21: ='1-0 Товары'!D21 -> 11 | E21: ='1-0 Товары'!E21 -> Воздушный фильтр | J21: ='1-0 Товары'!$G21 -> шт. | K21: ='1-0 Товары'!$H21 -> 6 | L21: ='1-0 Товары'!$I21 | M21: ='1-0 Товары'!$N21 | N21: ='1-0 Товары'!$O21 | O21: ='1-0 Товары'!$P21
C22: ='1-0 Товары'!C22 -> ID_T012 | D22: ='1-0 Товары'!D22 -> 12 | E22: ='1-0 Товары'!E22 -> Масляный фильтр | J22: ='1-0 Товары'!$G22 -> шт. | K22: ='1-0 Товары'!$H22 -> 6 | L22: ='1-0 Товары'!$I22 | M22: ='1-0 Товары'!$N22 | N22: ='1-0 Товары'!$O22 | O22: ='1-0 Товары'!$P22
... C310: ='1-0 Товары'!C310 | D310: ='1-0 Товары'!D310 | E310: ='1-0 Товары'!E310 | J310: ='1-0 Товары'!$G310 | K310: ='1-0 Товары'!$H310 | L310: ='1-0 Товары'!$I310 | M310: ='1-0 Товары'!$N310 | N310: ='1-0 Товары'!$O310 | O310: ='1-0 Товары'!$P310
C311: footer_first | D311: ='5-1 Сбор КП Закупки'!D311 | E311: ='5-1 Сбор КП Закупки'!E311 | F311: ='5-1 Сбор КП Закупки'!F311 | G311: ='5-1 Сбор КП Закупки'!G311 | H311: ='5-1 Сбор КП Закупки'!H311 | I311: ='5-1 Сбор КП Закупки'!I311
C312: footer_00 | D312: ='5-1 Сбор КП Закупки'!D312 | E312: ='5-1 Сбор КП Закупки'!E312 | F312: ='5-1 Сбор КП Закупки'!F312 | G312: ='5-1 Сбор КП Закупки'!G312 | H312: ='5-1 Сбор КП Закупки'!H312 | I312: ='5-1 Сбор КП Закупки'!I312
C313: footer_01 | D313: ='5-1 Сбор КП Закупки'!D313 | E313: ='5-1 Сбор КП Закупки'!E313 | F313: ='5-1 Сбор КП Закупки'!F313 | G313: ='5-1 Сбор КП Закупки'!G313 | H313: ='5-1 Сбор КП Закупки'!H313 | I313: ='5-1 Сбор КП Закупки'!I313
C314: footer_02 | D314: ='5-1 Сбор КП Закупки'!D314 | E314: ='5-1 Сбор КП Закупки'!E314 | F314: ='5-1 Сбор КП Закупки'!F314 | G314: ='5-1 Сбор КП Закупки'!G314 | H314: ='5-1 Сбор КП Закупки'!H314 | I314: ='5-1 Сбор КП Закупки'!I314
C315: footer_03 | D315: ='5-1 Сбор КП Закупки'!D315 | E315: ='5-1 Сбор КП Закупки'!E315 | F315: ='5-1 Сбор КП Закупки'!F315 | G315: ='5-1 Сбор КП Закупки'!G315 | H315: ='5-1 Сбор КП Закупки'!H315 | I315: ='5-1 Сбор КП Закупки'!I315
C316: footer_04 | D316: ='5-1 Сбор КП Закупки'!D316 | E316: ='5-1 Сбор КП Закупки'!E316 | F316: ='5-1 Сбор КП Закупки'!F316 | G316: ='5-1 Сбор КП Закупки'!G316 | H316: ='5-1 Сбор КП Закупки'!H316 | I316: ='5-1 Сбор КП Закупки'!I316
C317: footer_05 | D317: ='5-1 Сбор КП Закупки'!D317 | E317: ='5-1 Сбор КП Закупки'!E317 | F317: ='5-1 Сбор КП Закупки'!F317 | G317: ='5-1 Сбор КП Закупки'!G317 | H317: ='5-1 Сбор КП Закупки'!H317 | I317: ='5-1 Сбор КП Закупки'!I317
C318: footer_06 | D318: ='5-1 Сбор КП Закупки'!D318 | E318: ='5-1 Сбор КП Закупки'!E318 | F318: ='5-1 Сбор КП Закупки'!F318 | G318: ='5-1 Сбор КП Закупки'!G318 | H318: ='5-1 Сбор КП Закупки'!H318 | I318: ='5-1 Сбор КП Закупки'!I318
C319: footer_last | D319: ='5-1 Сбор КП Закупки'!D319 | E319: ='5-1 Сбор КП Закупки'!E319 | F319: ='5-1 Сбор КП Закупки'!F319 | G319: ='5-1 Сбор КП Закупки'!G319 | H319: ='5-1 Сбор КП Закупки'!H319 | I319: ='5-1 Сбор КП Закупки'!I319

Sheet 5-1 Сбор КП Закупки
C1: header_first | L1: Итог | M1: =M311 -> 0 | O1: =O311
A2: err | B2: err2 | C2: key | D2: Номер | E2: Номенклатура | F2: НазваниеТовараПоДоговору | G2: ИзготовительТовараПоДоговору | H2: Характеристики | I2: СоставТехническойДокументации | J2: ЕдИзм | K2: Количевство | L2: Цена | M2: Итого | N2: Предложений | O2: НМЦ | P2: СрокПоставкиПоДоговору | Q2: Запросить | R2: Группа | S2: свободные_01 | T2: свободные_02 | U2: свободные_03 | V2: свободные_04 | W2: свободные_05 | X2: свободные_06 | Y2: РазличиеМужду | Z2: =IFERROR(__xludf.DUMMYFUNCTION("{""ЦеныНачало"",LAMBDA(нач,макс,ячейки,la, TRANSPOSE( FLATTEN( ByRow( TRANSPOSE( FILTER( ByCol(ячейки,la), ByCol(ячейки,LAMBDA(ст,MOD((COLUMN(ст)-COLUMN(нач)-1),3)=0)), ByCol(ячейки,LAMBDA(ст,(COLUMN(ст)-макс)<0)) ) ),LAMBDA(пред,{пред&"".цена"",пред"&"&"".срок"",пред&"".модель"" }) )) ) )($Z$1, MAX(ARRAYFORMULA(COLUMN($AA$1:CZ$1)))-1, $AA$1:CZ$1,Lambda(ст, REGEXEXTRACT( CELL(""address"",ст),""[A-Z]+"")))}"),"ЦеныНачало") -> ЦеныНачало | AA2: =IFERROR(__xludf.DUMMYFUNCTION("""COMPUTED_VALUE"""),"AA.цена") -> AA.цена | AB2: =IFERROR(__xludf.DUMMYFUNCTION("""COMPUTED_VALUE"""),"AA.срок") -> AA.срок | AC2: =IFERROR(__xludf.DUMMYFUNCTION("""COMPUTED_VALUE"""),"AA.модель") -> AA.модель | AD2: =IFERROR(__xludf.DUMMYFUNCTION("""COMPUTED_VALUE"""),"AD.цена") -> AD.цена | AE2: =IFERROR(__xludf.DUMMYFUNCTION("""COMPUTED_VALUE"""),"AD.срок") -> AD.срок | AF2: =IFERROR(__xludf.DUMMYFUNCTION("""COMPUTED_VALUE"""),"AD.модель") -> AD.модель | AG2: =IFERROR(__xludf.DUMMYFUNCTION("""COMPUTED_VALUE"""),"AG.цена") -> AG.цена | AH2: =IFERROR(__xludf.DUMMYFUNCTION("""COMPUTED_VALUE"""),"AG.срок") -> AG.срок | AI2: =IFERROR(__xludf.DUMMYFUNCTION("""COMPUTED_VALUE"""),"AG.модель") -> AG.модель | AJ2: =IFERROR(__xludf.DUMMYFUNCTION("""COMPUTED_VALUE"""),"AJ.цена") -> AJ.цена | AK2: =IFERROR(__xludf.DUMMYFUNCTION("""COMPUTED_VALUE"""),"AJ.срок") -> AJ.срок | AL2: =IFERROR(__xludf.DUMMYFUNCTION("""COMPUTED_VALUE"""),"AJ.модель") -> AJ.модель | AM2: =IFERROR(__xludf.DUMMYFUNCTION("""COMPUTED_VALUE"""),"AM.цена") -> AM.цена | AN2: =IFERROR(__xludf.DUMMYFUNCTION("""COMPUTED_VALUE"""),"AM.срок") -> AM.срок | AO2: =IFERROR(__xludf.DUMMYFUNCTION("""COMPUTED_VALUE"""),"AM.модель") -> AM.модель | AP2: =IFERROR(__xludf.DUMMYFUNCTION("""COMPUTED_VALUE"""),"AP.цена") -> AP.цена | AQ2: =IFERROR(__xludf.DUMMYFUNCTION("""COMPUTED_VALUE"""),"AP.срок") -> AP.срок | AR2: =IFERROR(__xludf.DUMMYFUNCTION("""COMPUTED_VALUE"""),"AP.модель") -> AP.модель | AS2: =IFERROR(__xludf.DUMMYFUNCTION("""COMPUTED_VALUE"""),"AS.цена") -> AS.цена | AT2: =IFERROR(__xludf.DUMMYFUNCTION("""COMPUTED_VALUE"""),"AS.срок") -> AS.срок | AU2: =IFERROR(__xludf.DUMMYFUNCTION("""COMPUTED_VALUE"""),"AS.модель") -> AS.модель | AV2: =IFERROR(__xludf.DUMMYFUNCTION("""COMPUTED_VALUE"""),"AV.цена") -> AV.цена | AW2: =IFERROR(__xludf.DUMMYFUNCTION("""COMPUTED_VALUE"""),"AV.срок") -> AV.срок | AX2: =IFERROR(__xludf.DUMMYFUNCTION("""COMPUTED_VALUE"""),"AV.модель") -> AV.модель | AY2: =IFERROR(__xludf.DUMMYFUNCTION("""COMPUTED_VALUE"""),"AY.цена") -> AY.цена | AZ2: =IFERROR(__xludf.DUMMYFUNCTION("""COMPUTED_VALUE"""),"AY.срок") -> AY.срок | BA2: =IFERROR(__xludf.DUMMYFUNCTION("""COMPUTED_VALUE"""),"AY.модель") -> AY.модель | BB2: =IFERROR(__xludf.DUMMYFUNCTION("""COMPUTED_VALUE"""),"BB.цена") -> BB.цена | BC2: =IFERROR(__xludf.DUMMYFUNCTION("""COMPUTED_VALUE"""),"BB.срок") -> BB.срок | BD2: =IFERROR(__xludf.DUMMYFUNCTION("""COMPUTED_VALUE"""),"BB.модель") -> BB.модель | BE2: =IFERROR(__xludf.DUMMYFUNCTION("""COMPUTED_VALUE"""),"BE.цена") -> BE.цена | BF2: =IFERROR(__xludf.DUMMYFUNCTION("""COMPUTED_VALUE"""),"BE.срок") -> BE.срок | BG2: =IFERROR(__xludf.DUMMYFUNCTION("""COMPUTED_VALUE"""),"BE.модель") -> BE.модель | BH2: =IFERROR(__xludf.DUMMYFUNCTION("""COMPUTED_VALUE"""),"BH.цена") -> BH.цена | BI2: =IFERROR(__xludf.DUMMYFUNCTION("""COMPUTED_VALUE"""),"BH.срок") -> BH.срок | BJ2: =IFERROR(__xludf.DUMMYFUNCTION("""COMPUTED_VALUE"""),"BH.модель") -> BH.модель | BK2: =IFERROR(__xludf.DUMMYFUNCTION("""COMPUTED_VALUE"""),"BK.цена") -> BK.цена | BL2: =IFERROR(__xludf.DUMMYFUNCTION("""COMPUTED_VALUE"""),"BK.срок") -> BK.срок | BM2: =IFERROR(__xludf.DUMMYFUNCTION("""COMPUTED_VALUE"""),"BK.модель") -> BK.модель | BN2: =IFERROR(__xludf.DUMMYFUNCTION("""COMPUTED_VALUE"""),"BN.цена") -> BN.цена | BO2: =IFERROR(__xludf.DUMMYFUNCTION("""COMPUTED_VALUE"""),"BN.срок") -> BN.срок | BP2: =IFERROR(__xludf.DUMMYFUNCTION("""COMPUTED_VALUE"""),"BN.модель") -> BN.модель | BQ2: =IFERROR(__xludf.DUMMYFUNCTION("""COMPUTED_VALUE"""),"BQ.цена") -> BQ.цена | BR2: =IFERROR(__xludf.DUMMYFUNCTION("""COMPUTED_VALUE"""),"BQ.срок") -> BQ.срок | BS2: =IFERROR(__xludf.DUMMYFUNCTION("""COMPUTED_VALUE"""),"BQ.модель") -> BQ.модель | BT2: =IFERROR(__xludf.DUMMYFUNCTION("""COMPUTED_VALUE"""),"BT.цена") -> BT.цена | BU2: =IFERROR(__xludf.DUMMYFUNCTION("""COMPUTED_VALUE"""),"BT.срок") -> BT.срок | BV2: =IFERROR(__xludf.DUMMYFUNCTION("""COMPUTED_VALUE"""),"BT.модель") -> BT.модель | BW2: =IFERROR(__xludf.DUMMYFUNCTION("""COMPUTED_VALUE"""),"BW.цена") -> BW.цена | BX2: =IFERROR(__xludf.DUMMYFUNCTION("""COMPUTED_VALUE"""),"BW.срок") -> BW.срок | BY2: =IFERROR(__xludf.DUMMYFUNCTION("""COMPUTED_VALUE"""),"BW.модель") -> BW.модель | BZ2: =IFERROR(__xludf.DUMMYFUNCTION("""COMPUTED_VALUE"""),"BZ.цена") -> BZ.цена | CA2: =IFERROR(__xludf.DUMMYFUNCTION("""COMPUTED_VALUE"""),"BZ.срок") -> BZ.срок | CB2: =IFERROR(__xludf.DUMMYFUNCTION("""COMPUTED_VALUE"""),"BZ.модель") -> BZ.модель | CC2: =IFERROR(__xludf.DUMMYFUNCTION("""COMPUTED_VALUE"""),"CC.цена") -> CC.цена | CD2: =IFERROR(__xludf.DUMMYFUNCTION("""COMPUTED_VALUE"""),"CC.срок") -> CC.срок | CE2: =IFERROR(__xludf.DUMMYFUNCTION("""COMPUTED_VALUE"""),"CC.модель") -> CC.модель | CF2: =IFERROR(__xludf.DUMMYFUNCTION("""COMPUTED_VALUE"""),"CF.цена") -> CF.цена | CG2: =IFERROR(__xludf.DUMMYFUNCTION("""COMPUTED_VALUE"""),"CF.срок") -> CF.срок | CH2: =IFERROR(__xludf.DUMMYFUNCTION("""COMPUTED_VALUE"""),"CF.модель") -> CF.модель | CI2: =IFERROR(__xludf.DUMMYFUNCTION("""COMPUTED_VALUE"""),"CI.цена") -> CI.цена | CJ2: =IFERROR(__xludf.DUMMYFUNCTION("""COMPUTED_VALUE"""),"CI.срок") -> CI.срок | CK2: =IFERROR(__xludf.DUMMYFUNCTION("""COMPUTED_VALUE"""),"CI.модель") -> CI.модель | CL2: =IFERROR(__xludf.DUMMYFUNCTION("""COMPUTED_VALUE"""),"CL.цена") -> CL.цена | CM2: =IFERROR(__xludf.DUMMYFUNCTION("""COMPUTED_VALUE"""),"CL.срок") -> CL.срок | CN2: =IFERROR(__xludf.DUMMYFUNCTION("""COMPUTED_VALUE"""),"CL.модель") -> CL.модель | CO2: =IFERROR(__xludf.DUMMYFUNCTION("""COMPUTED_VALUE"""),"CO.цена") -> CO.цена | CP2: =IFERROR(__xludf.DUMMYFUNCTION("""COMPUTED_VALUE"""),"CO.срок") -> CO.срок | CQ2: =IFERROR(__xludf.DUMMYFUNCTION("""COMPUTED_VALUE"""),"CO.модель") -> CO.модель | CR2: =IFERROR(__xludf.DUMMYFUNCTION("""COMPUTED_VALUE"""),"CR.цена") -> CR.цена | CS2: =IFERROR(__xludf.DUMMYFUNCTION("""COMPUTED_VALUE"""),"CR.срок") -> CR.срок | CT2: =IFERROR(__xludf.DUMMYFUNCTION("""COMPUTED_VALUE"""),"CR.модель") -> CR.модель | CU2: =IFERROR(__xludf.DUMMYFUNCTION("""COMPUTED_VALUE"""),"CU.цена") -> CU.цена | CV2: =IFERROR(__xludf.DUMMYFUNCTION("""COMPUTED_VALUE"""),"CU.срок") -> CU.срок | CW2: =IFERROR(__xludf.DUMMYFUNCTION("""COMPUTED_VALUE"""),"CU.модель") -> CU.модель | CX2: =IFERROR(__xludf.DUMMYFUNCTION("""COMPUTED_VALUE"""),"CX.цена") -> CX.цена | CY2: =IFERROR(__xludf.DUMMYFUNCTION("""COMPUTED_VALUE"""),"CX.срок") -> CX.срок | CZ2: =IFERROR(__xludf.DUMMYFUNCTION("""COMPUTED_VALUE"""),"CX.модель") -> CX.модель
A3: formulaColl | B3: formulaFree | C3: formulaCell | D3: formulaCell | E3: formulaCell | H3: formulaCell | J3: formulaCell | K3: formulaCell | L3: formulaCell | M3: formulaColl | N3: formulaColl | O3: formulaColl | R3: formulaColl | Y3: formulaColl | Z3: formulaCell
C4: var_key | D4: theUrl | M4: total
C5: var_name | D5: Доллар | M5: Итого
C6: var_value | D6: =IFERROR(__xludf.DUMMYFUNCTION("LAMBDA(doJoin,doSplit,doFind,theStr,theData,doJoin(doFind(doSplit(theStr),theData)))( LAMBDA(theVls,TEXTJOIN("", "",FALSE,theVls)), LAMBDA(theStr,Split(theStr,"", "",FALSE,TRUE)), LAMBDA(theNames,theData,BYCOL(theNames,LAMBDA(theN,VLOOKUP(theN,theData,2,0"&")))), D$5,'1-1 Сбор КП'!$A$2:$B$15)"),"#REF!") -> #REF! | M6: =SUM(M11:M310) -> 0
C7: hide_col | E7: Сгрупировать | G7: Сгрупировать | H7: Сгрупировать | I7: Сгрупировать | L7: Сгрупировать | M7: Сгрупировать | N7: Сгрупировать | O7: Сгрупировать | S7: СкрытьСгрупировать | T7: СкрытьСгрупировать | U7: СкрытьСгрупировать | V7: СкрытьСгрупировать | W7: СкрытьСгрупировать | X7: СкрытьСгрупировать | Y7: СкрытьСгрупировать | Z7: СкрытьСгрупировать
C8: header_08 | Z8: тут начинаются цены
C9: header_last
A10: {='1-1 Сбор КП'!A1:B9} | C10: ='5-0 Товары'!C10 -> ID_Товара | D10: № | E10: Номенклатура | F10: Название товара по договору | G10: Изготовитель товара по договору | H10: Характеристики | I10: Состав поставляемой с продукцией технической документации | J10: Ед. Изм | K10: Кол-во | L10: ="Цена" -> Цена | M10: {={"Итого";LAMBDA(theData,{theData;SUM(theData)})( IF(D11:D310="",,K11:K310*L11:L310) )}} -> Итого | N10: =IFERROR(__xludf.DUMMYFUNCTION("{""Предложений"";LAMBDA(doCommet,doFind,doSum,theMalo,theIds,theData,doCommet(theMalo,doFind(theIds,doSum(theData))))( LAMBDA(theMalo,theV,ByRow(theV,LAMBDA(tv, ifs(tv="""",,tv<=theMalo,""Мало ""&tv,TRUE,tv)))), LAMBDA(theIds,theSum,BYROW(theIds,LAMBDA(ti"&",IF (ti="""",,IFERROR(VLOOKUP(ti,theSum,2,0),0))))), LAMBDA(theData,QUERY( BYROW( theData,LAMBDA(theR,{theR , IF(theR<>"""",1,0)})),""Select Col1, sum(Col2) where Col1 is not null group by Col1 "",0)), '5-1 Сбор КП Закупки'!$B$17,'5-1 Сбор КП Закупки'!C1"&"1:C310,'S-10 Предложения'!$BC11:$BC319 )}"),"Предложений") -> Предложений | O10: ='5-0 Товары'!I10 -> НМЦ | P10: ='5-0 Товары'!N10 -> Срок поставки по договору | Q10: Запросить | R10: {={"Группа";IFERROR( VLOOKUP(C11:C310,{ '5-0 Товары'!C11:C319,IF('5-0 Товары'!M11:M319<>"","5-1 "&'5-0 Товары'!M11:M319, IF('5-0 Товары'!L11:L319<>"", "1-1 "&'5-0 Товары'!L11:L319,))},2,0),)}} -> Группа | S10: =IFERROR(__xludf.DUMMYFUNCTION("{{""Доля ответов"",""Предложение"",""Писем""};let( _t_em_map , let( _t_gr, '5-2 Запросы КП Закупки'!$N11:$N312, _t_nm, '5-2 Запросы КП Закупки'!$O11:$O312, _t_em, '5-2 Запросы КП Закупки'!$AB11:CZ$312, do_sm, LAMBDA(em_mp, BYROW(em_mp,LAMBDA("&"e_ar,COUNTA(e_ar)))), QUERY( {{""Группа"" , ""Кол-во""};{Map(_t_gr,_t_nm,do_sm(_t_em),LAMBDA(g,n,s,IF(n=2,{g,s},{"""",""""})) )}},""Select * Where Col1 is not null"") ), _t_ot_mp , BYROW('5-1 Сбор КП Закупки'!$AA11:$CZ319, LAMBDA(r, IFERROR(COUNTA( "&"FILTER(r,MOD( COLUMN(r),3)=0 ) ),) )), _t_mp_stat_tov, MAP('5-1 Сбор КП Закупки'!$Z11:$Z319,'5-1 Сбор КП Закупки'!$E11:$E319,_t_ot_mp,'5-1 Сбор КП Закупки'!$R11:$R319, LAMBDA(z,t,r,g, {z,IF(t<>"""",IFERROR( r/VLOOKUP(g,_t_em_map,2,FALSE) ,),),IF(t<>"""",r"&",),IFERROR( VLOOKUP(g,_t_em_map,2,FALSE) ,)})), _t_mp_stat_itog, LAMBDA(_t, let ( _t_dolya, LAMBDA(_a,IFERROR( SUM(_a)/COUNT(_a),0))(INDEX( _t,,2)) ,_t_predl, LAMBDA(_a,SUM(_a*1))(INDEX( _t,,3)) , {""@"",_t_dolya , _t_predl , "" ""}))(_t_mp_stat_tov), _t_"&"raw_rez,{_t_mp_stat_tov;_t_mp_stat_itog}, _t_ord, LET( _t_nrs, '5-1 Сбор КП Закупки'!$C$10:$C319, _t_ids, '5-1 Сбор КП Закупки'!$Z$10:$Z319, _t_fr, MATCH(""ID_Товара"", _t_nrs, 0) + 1, _t_to, MATCH(""footer_first"", _t_nrs, 0) - 1, {INDEX(_t_ids"&", _t_fr,1):INDEX(_t_ids, _t_to,1); ""@""}), rez,Byrow(_t_ord,LAMBDA(o, ARRAYFORMULA( IFERROR(VLOOKUP(o,_t_raw_rez,{2,3,4},FALSE) , ) ))), rez )}"),"Доля ответов") -> Доля ответов | T10: =IFERROR(__xludf.DUMMYFUNCTION("""COMPUTED_VALUE"""),"Предложение") -> Предложение | U10: =IFERROR(__xludf.DUMMYFUNCTION("""COMPUTED_VALUE"""),"Писем") -> Писем | V10: свободные | W10: свободные | X10: свободные | Y10: {={"РазличиеМужду";LAMBDA(doCompFild,doCon,doCompare,theICol,theIRow,theName,theD1,theD2, byRow(theIRow,LAMBDA(theIR, IF( OR(doCon(INDEX(theD1,theIR,))="",doCompare(doCon,INDEX(theD1,theIR,),INDEX(theD2,theIR,))), doCompFild(theICol,theName,INDEX(theD1,theIR,),INDEX(theD2,theIR,)) ,))) )( LAMBDA(theICol,theName,theR1,theR2, TEXTJOIN(" ",TRUE,BYCOL(theICol,LAMBDA(theIC, IF( INDEX(theR1,,theIC)<>INDEX(theR2,,theIC),"'"&INDEX(theName,,theIC)&"'",) ))) ), LAMBDA(theD,TEXTJOIN("",TRUE,theD)), LaMbda(doCon, theD1,theD2, doCon(theD1)<>doCon(theD2) ), LAMBDA(theM,BYCOL(theM,LAMBDA(tm,COLUMN(tM)+1-COLUMN(theM))))('5-1 Сбор КП Закупки'!$F$10:$I$10), LAMBDA(theM,BYrow(theM,LAMBDA(tm,ROW(tM)+1-ROW(theM))))('5-1 Сбор КП Закупки'!$F$11:$F$310), '5-1 Сбор КП Закупки'!$F$10:$I$10,'5-0 Передача в закупку'!$F$11:$I$310, '5-1 Сбор КП Закупки'!$F$11:$I$310 )}} -> РазличиеМужду | Z10: ="Цены Начало" -> Цены Начало
A11: Доллар | B11: #REF! | C11: ='5-0 Товары'!C11 -> ID_T001 | D11: ='5-0 Товары'!D11 -> 1 | E11: ='5-0 Товары'!E11 -> Масляный фильтр - Артикул 89781969 ESG-315 зав.№ F010451 | H11: ='5-0 Товары'!F11 | J11: ='5-0 Товары'!G11 -> шт. | K11: ='5-0 Товары'!H11 -> 3 | L11: =If( C11="",,MIN(AA11:CZ11)) -> 0 | M11: 0 | N11: =IFERROR(__xludf.DUMMYFUNCTION("""COMPUTED_VALUE"""),"Мало 0") -> Мало 0 | O11: ='5-0 Товары'!I11 | P11: ='5-0 Товары'!N11 | T11: =IFERROR(__xludf.DUMMYFUNCTION("""COMPUTED_VALUE"""),0.0) -> 0 | Z11: =$C11 -> ID_T001
A12: Евро | B12: #REF! | C12: ='5-0 Товары'!C12 -> ID_T002 | D12: ='5-0 Товары'!D12 -> 2 | E12: ='5-0 Товары'!E12 -> Масляный фильтр - Артикул 85062259 | H12: ='5-0 Товары'!F12 | J12: ='5-0 Товары'!G12 -> шт. | K12: ='5-0 Товары'!H12 -> 6 | L12: =If( C12="",,MIN(AA12:CZ12)) -> 0 | M12: 0 | N12: =IFERROR(__xludf.DUMMYFUNCTION("""COMPUTED_VALUE"""),"Мало 0") -> Мало 0 | O12: ='5-0 Товары'!I12 | P12: ='5-0 Товары'!N12 | T12: =IFERROR(__xludf.DUMMYFUNCTION("""COMPUTED_VALUE"""),0.0) -> 0 | Z12: =$C12 -> ID_T002
A13: CNY | B13: #REF! | C13: ='5-0 Товары'!C13 -> ID_T003 | D13: ='5-0 Товары'!D13 -> 3 | E13: ='5-0 Товары'!E13 -> Воздушный фильтр - Артикул 85067179 | H13: ='5-0 Товары'!F13 | J13: ='5-0 Товары'!G13 -> шт. | K13: ='5-0 Товары'!H13 -> 16 | L13: =If( C13="",,MIN(AA13:CZ13)) -> 0 | M13: 0 | N13: =IFERROR(__xludf.DUMMYFUNCTION("""COMPUTED_VALUE"""),"Мало 0") -> Мало 0 | O13: ='5-0 Товары'!I13 | P13: ='5-0 Товары'!N13 | T13: =IFERROR(__xludf.DUMMYFUNCTION("""COMPUTED_VALUE"""),0.0) -> 0 | Z13: =$C13 -> ID_T003
C14: ='5-0 Товары'!C14 -> ID_T004 | D14: ='5-0 Товары'!D14 -> 4 | E14: ='5-0 Товары'!E14 -> Термостат в сборе ESM-200; «Gardner Denver» | H14: ='5-0 Товары'!F14 | J14: ='5-0 Товары'!G14 -> шт. | K14: ='5-0 Товары'!H14 -> 2 | L14: =If( C14="",,MIN(AA14:CZ14)) -> 0 | M14: 0 | N14: =IFERROR(__xludf.DUMMYFUNCTION("""COMPUTED_VALUE"""),"Мало 0") -> Мало 0 | O14: ='5-0 Товары'!I14 | P14: ='5-0 Товары'!N14 | T14: =IFERROR(__xludf.DUMMYFUNCTION("""COMPUTED_VALUE"""),0.0) -> 0 | Z14: =$C14 -> ID_T004
A15: откл от ср | B15: 0.5 | C15: ='5-0 Товары'!C15 -> ID_T005 | D15: ='5-0 Товары'!D15 -> 5 | E15: ='5-0 Товары'!E15 -> Масляный сепаратор Артикул 03498328 | H15: ='5-0 Товары'!F15 | J15: ='5-0 Товары'!G15 -> шт. | K15: ='5-0 Товары'!H15 -> 3 | L15: =If( C15="",,MIN(AA15:CZ15)) -> 0 | M15: 0 | N15: =IFERROR(__xludf.DUMMYFUNCTION("""COMPUTED_VALUE"""),"Мало 0") -> Мало 0 | O15: ='5-0 Товары'!I15 | P15: ='5-0 Товары'!N15 | T15: =IFERROR(__xludf.DUMMYFUNCTION("""COMPUTED_VALUE"""),0.0) -> 0 | Z15: =$C15 -> ID_T005
A16: Первые мин знач | C16: ='5-0 Товары'!C16 -> ID_T006 | D16: ='5-0 Товары'!D16 -> 6 | E16: ='5-0 Товары'!E16 -> Масляный фильтр Артикул 89675429 | H16: ='5-0 Товары'!F16 | J16: ='5-0 Товары'!G16 -> шт. | K16: ='5-0 Товары'!H16 -> 3 | L16: =If( C16="",,MIN(AA16:CZ16)) -> 0 | M16: 0 | N16: =IFERROR(__xludf.DUMMYFUNCTION("""COMPUTED_VALUE"""),"Мало 0") -> Мало 0 | O16: ='5-0 Товары'!I16 | P16: ='5-0 Товары'!N16 | T16: =IFERROR(__xludf.DUMMYFUNCTION("""COMPUTED_VALUE"""),0.0) -> 0 | Z16: =$C16 -> ID_T006
